Workbook

Sheet Objetivos e Elaboração
AO2: 6. e 8.
C3: Objetivos do Quadro de Polivalência | R3: 1. e 9. | AM3: 3. | AN3: 5. | AO3: 1º Trim | AP3: 2º Trim | AQ3: 3º Trim
B4: 1. | C4: Mapeamento de todas as tarefas do departamento | AM4: Colaborador 3 | AO4: 138 | AP4: =+AO4+2 -> 140 | AQ4: 142
B5: 2. | C5: Geração de cronograma de entrega das obrigações/tarefas | AM5: Colaborador 2 | AO5: 126 | AP5: =AO5+20 -> 146 | AQ5: 158
B6: 3. | C6: Posicionamento do colaborador no departamento / Avaliação individual | AM6: Colaborador 1 | AO6: 99 | AP6: =AO6+30 -> 129 | AQ6: 131
B7: 4. | C7: Identificação do grau de conhecimento em tarefas específicas de cada colaborador | AM7: Colaborador 4 | AO7: 45 | AP7: =AO7+50 -> 95 | AQ7: 131
B8: 5. | C8: Motivação para troca de conhecimentos, identificando quem conhece e quem gostaria de conhecer a execução da tarefa
B9: 6. | C9: Gerador de desempenho do colaborador ao longo do período
B10: 7. | C10: Identificação de risco em caso de desligamento ou ausência temporária
B11: 8. | C11: Ferramenta base para adequação/promoção/desligamento do colaborador
B12: 9. | C12: Indicador de riscos a partir da visão "da empresa" e não apenas do gestor, a partir da consolidação das informações. | AM12: 4.
AM13: Aprendendo | AP13: 1
C15: Forma de elaboração
B16: 1. | C16: Colaborador informa as tarefas que executa, em formulário individual | AM16: Consegue fazer com ajuda | AP16: 1
B17: 2. | C17: Colaborador informa o nível de conhecimento das tarefas que executa, em formulário individual | AP17: 1
B18: 3. | C18: Gestor compila as tarefas em duplicidade
B19: 4. | C19: Gestor efetua a revisão das informações | AM19: Consegue fazer sem ajuda | AP19: 1 | AQ19: 1
B20: 5. | C20: A ferramenta aplica as análises | AM20: (Sei fazer, mas não sei porque faço) | AP20: 1
B21: 6. | C21: Gestor decide qual o destinatário das informações
B22: 7. | C22: Gestor decide sobre as tomadas de decisões necessárias | AM22: Consegue fazer e ensinar | AP22: 1 | AQ22: 1
B23: 8. | C23: Compilação dos dados e consolidação dos relatórios de todos os departamentos para gestão de risco por parte da empresa ao todo. | AM23: (Sei fazer, e sei porque faço) | AP23: 1 | AQ23: 1

Sheet Agosto 2025
B2: Setorização | D2: Tarefas | F2: Periodicidade | H2: Luis | K2: Alexandre | N2: Lucas | Q2: Pamella | T2: Loraine | W2: Semáforo | AA2: Aprendendo | AB2: 1
H3: Gerente | K3: Supervisor
D5: Classificação do Colaborador | H5: =H11+H83+H86+H89+H92+H95+H98+H200+H203+H206+H14+H17+H20+H23+H26+H29+H32+H35+H41+H38+H44+H47+H50+H53+H56+H59+H62+H65+H68+H71+H74+H77+H80+H101+H104+H107+H110+H113+H116+H119+H122+H125+H128+H131+H134+H137+H140+H143+H146+H149+H152+H155+H158+H161+H164+H167+H170+H173+H176+H179+H182+H185+H188+H191+H194+H197+H209+H212+H215+H218+H221+H224+H227+H230+H233+H236+H239+H242+H245+H248+H251+H254+H257+H260+H263+H266+H269+H272 -> 30 | I5: =I11+I83+I86+I89+I92+I95+I98+I200+I203+I206+I14+I17+I20+I23+I26+I29+I32+I35+I41+I38+I44+I47+I50+I53+I56+I59+I62+I65+I68+I71+I74+I77+I80+I101+I104+I107+I110+I113+I116+I119+I122+I125+I128+I131+I134+I137+I140+I143+I146+I149+I152+I155+I158+I161+I164+I167+I170+I173+I176+I179+I182+I185+I188+I191+I194+I197+I209+I212+I215+I218+I221+I224+I227+I230+I233+I236+I239+I242+I245+I248+I251+I254+I257+I260+I263+I266+I269+I272 -> 30 | K5: =K11+K83+K86+K89+K92+K95+K98+K200+K203+K206+K14+K17+K20+K23+K26+K29+K32+K35+K41+K38+K44+K47+K50+K53+K56+K59+K62+K65+K68+K71+K74+K77+K80+K101+K104+K107+K110+K113+K116+K119+K122+K125+K128+K131+K134+K137+K140+K143+K146+K149+K152+K155+K158+K161+K164+K167+K170+K173+K176+K179+K182+K185+K188+K191+K194+K197+K209+K212+K215+K218+K221+K224+K227+K230+K233+K236+K239+K242+K245+K248+K251+K254+K257+K260+K263+K266+K269+K272 -> 35 | L5: =L11+L83+L86+L89+L92+L95+L98+L200+L203+L206+L14+L17+L20+L23+L26+L29+L32+L35+L41+L38+L44+L47+L50+L53+L56+L59+L62+L65+L68+L71+L74+L77+L80+L101+L104+L107+L110+L113+L116+L119+L122+L125+L128+L131+L134+L137+L140+L143+L146+L149+L152+L155+L158+L161+L164+L167+L170+L173+L176+L179+L182+L185+L188+L191+L194+L197+L209+L212+L215+L218+L221+L224+L227+L230+L233+L236+L239+L242+L245+L248+L251+L254+L257+L260+L263+L266+L269+L272 -> 30 | N5: =N11+N83+N86+N89+N92+N95+N98+N200+N203+N206+N14+N17+N20+N23+N26+N29+N32+N35+N41+N38+N44+N47+N50+N53+N56+N59+N62+N65+N68+N71+N74+N77+N80+N101+N104+N107+N110+N113+N116+N119+N122+N125+N128+N131+N134+N137+N140+N143+N146+N149+N152+N155+N158+N161+N164+N167+N170+N173+N176+N179+N182+N185+N188+N191+N194+N197+N209+N212+N215+N218+N221+N224+N227+N230+N233+N236+N239+N242+N245+N248+N251+N254+N257+N260+N263+N266+N269+N272 -> 50 | O5: =O11+O83+O86+O89+O92+O95+O98+O200+O203+O206+O14+O17+O20+O23+O26+O29+O32+O35+O41+O38+O44+O47+O50+O53+O56+O59+O62+O65+O68+O71+O74+O77+O80+O101+O104+O107+O110+O113+O116+O119+O122+O125+O128+O131+O134+O137+O140+O143+O146+O149+O152+O155+O158+O161+O164+O167+O170+O173+O176+O179+O182+O185+O188+O191+O194+O197+O209+O212+O215+O218+O221+O224+O227+O230+O233+O236+O239+O242+O245+O248+O251+O254+O257+O260+O263+O266+O269+O272 -> 41 | Q5: =Q11+Q83+Q86+Q89+Q92+Q95+Q98+Q200+Q203+Q206+Q14+Q17+Q20+Q23+Q26+Q29+Q32+Q35+Q41+Q38+Q44+Q47+Q50+Q53+Q56+Q59+Q62+Q65+Q68+Q71+Q74+Q77+Q80+Q101+Q104+Q107+Q110+Q113+Q116+Q119+Q122+Q125+Q128+Q131+Q134+Q137+Q140+Q143+Q146+Q149+Q152+Q155+Q158+Q161+Q164+Q167+Q170+Q173+Q176+Q179+Q182+Q185+Q188+Q191+Q194+Q197+Q209+Q212+Q215+Q218+Q221+Q224+Q227+Q230+Q233+Q236+Q239+Q242+Q245+Q248+Q251+Q254+Q257+Q260+Q263+Q266+Q269+Q272 -> 14 | R5: =R11+R83+R86+R89+R92+R95+R98+R200+R203+R206+R14+R17+R20+R23+R26+R29+R32+R35+R41+R38+R44+R47+R50+R53+R56+R59+R62+R65+R68+R71+R74+R77+R80+R101+R104+R107+R110+R113+R116+R119+R122+R125+R128+R131+R134+R137+R140+R143+R146+R149+R152+R155+R158+R161+R164+R167+R170+R173+R176+R179+R182+R185+R188+R191+R194+R197+R209+R212+R215+R218+R221+R224+R227+R230+R233+R236+R239+R242+R245+R248+R251+R254+R257+R260+R263+R266+R269+R272 -> 14 | T5: =T11+T83+T86+T89+T92+T95+T98+T200+T203+T206+T14+T17+T20+T23+T26+T29+T32+T35+T41+T38+T44+T47+T50+T53+T56+T59+T62+T65+T68+T71+T74+T77+T80+T101+T104+T107+T110+T113+T116+T119+T122+T125+T128+T131+T134+T137+T140+T143+T146+T149+T152+T155+T158+T161+T164+T167+T170+T173+T176+T179+T182+T185+T188+T191+T194+T197+T209+T212+T215+T218+T221+T224+T227+T230+T233+T236+T239+T242+T245+T248+T251+T254+T257+T260+T263+T266+T269+T272 -> 14 | U5: =U11+U83+U86+U89+U92+U95+U98+U200+U203+U206+U14+U17+U20+U23+U26+U29+U32+U35+U41+U38+U44+U47+U50+U53+U56+U59+U62+U65+U68+U71+U74+U77+U80+U101+U104+U107+U110+U113+U116+U119+U122+U125+U128+U131+U134+U137+U140+U143+U146+U149+U152+U155+U158+U161+U164+U167+U170+U173+U176+U179+U182+U185+U188+U191+U194+U197+U209+U212+U215+U218+U221+U224+U227+U230+U233+U236+U239+U242+U245+U248+U251+U254+U257+U260+U263+U266+U269+U272 -> 14 | Z5: Consegue fazer | AA5: com ajuda | AB5: 1
H6: =H12+H84+H87+H90+H93+H96+H99+H201+H204+H207+H15+H18+H21+H24+H27+H30+H33+H36+H42+H39+H45+H48+H51+H54+H57+H60+H63+H66+H69+H72+H75+H78+H81+H102+H105+H108+H111+H114+H117+H120+H123+H126+H129+H132+H135+H138+H141+H144+H147+H150+H153+H156+H159+H162+H165+H168+H171+H174+H177+H180+H183+H186+H189+H192+H195+H198+H210+H213+H216+H219+H222+H225+H228+H231+H234+H237+H240+H243+H246+H249+H252+H255+H258+H261+H264+H267+H270+H273 -> 30 | I6: =I12+I84+I87+I90+I93+I96+I99+I201+I204+I207+I15+I18+I21+I24+I27+I30+I33+I36+I42+I39+I45+I48+I51+I54+I57+I60+I63+I66+I69+I72+I75+I78+I81+I102+I105+I108+I111+I114+I117+I120+I123+I126+I129+I132+I135+I138+I141+I144+I147+I150+I153+I156+I159+I162+I165+I168+I171+I174+I177+I180+I183+I186+I189+I192+I195+I198+I210+I213+I216+I219+I222+I225+I228+I231+I234+I237+I240+I243+I246+I249+I252+I255+I258+I261+I264+I267+I270+I273 -> 30 | K6: =K12+K84+K87+K90+K93+K96+K99+K201+K204+K207+K15+K18+K21+K24+K27+K30+K33+K36+K42+K39+K45+K48+K51+K54+K57+K60+K63+K66+K69+K72+K75+K78+K81+K102+K105+K108+K111+K114+K117+K120+K123+K126+K129+K132+K135+K138+K141+K144+K147+K150+K153+K156+K159+K162+K165+K168+K171+K174+K177+K180+K183+K186+K189+K192+K195+K198+K210+K213+K216+K219+K222+K225+K228+K231+K234+K237+K240+K243+K246+K249+K252+K255+K258+K261+K264+K267+K270+K273 -> 30 | L6: =L12+L84+L87+L90+L93+L96+L99+L201+L204+L207+L15+L18+L21+L24+L27+L30+L33+L36+L42+L39+L45+L48+L51+L54+L57+L60+L63+L66+L69+L72+L75+L78+L81+L102+L105+L108+L111+L114+L117+L120+L123+L126+L129+L132+L135+L138+L141+L144+L147+L150+L153+L156+L159+L162+L165+L168+L171+L174+L177+L180+L183+L186+L189+L192+L195+L198+L210+L213+L216+L219+L222+L225+L228+L231+L234+L237+L240+L243+L246+L249+L252+L255+L258+L261+L264+L267+L270+L273 -> 26 | N6: =N12+N84+N87+N90+N93+N96+N99+N201+N204+N207+N15+N18+N21+N24+N27+N30+N33+N36+N42+N39+N45+N48+N51+N54+N57+N60+N63+N66+N69+N72+N75+N78+N81+N102+N105+N108+N111+N114+N117+N120+N123+N126+N129+N132+N135+N138+N141+N144+N147+N150+N153+N156+N159+N162+N165+N168+N171+N174+N177+N180+N183+N186+N189+N192+N195+N198+N210+N213+N216+N219+N222+N225+N228+N231+N234+N237+N240+N243+N246+N249+N252+N255+N258+N261+N264+N267+N270+N273 -> 38 | O6: =O12+O84+O87+O90+O93+O96+O99+O201+O204+O207+O15+O18+O21+O24+O27+O30+O33+O36+O42+O39+O45+O48+O51+O54+O57+O60+O63+O66+O69+O72+O75+O78+O81+O102+O105+O108+O111+O114+O117+O120+O123+O126+O129+O132+O135+O138+O141+O144+O147+O150+O153+O156+O159+O162+O165+O168+O171+O174+O177+O180+O183+O186+O189+O192+O195+O198+O210+O213+O216+O219+O222+O225+O228+O231+O234+O237+O240+O243+O246+O249+O252+O255+O258+O261+O264+O267+O270+O273 -> 37 | Q6: =Q12+Q84+Q87+Q90+Q93+Q96+Q99+Q201+Q204+Q207+Q15+Q18+Q21+Q24+Q27+Q30+Q33+Q36+Q42+Q39+Q45+Q48+Q51+Q54+Q57+Q60+Q63+Q66+Q69+Q72+Q75+Q78+Q81+Q102+Q105+Q108+Q111+Q114+Q117+Q120+Q123+Q126+Q129+Q132+Q135+Q138+Q141+Q144+Q147+Q150+Q153+Q156+Q159+Q162+Q165+Q168+Q171+Q174+Q177+Q180+Q183+Q186+Q189+Q192+Q195+Q198+Q210+Q213+Q216+Q219+Q222+Q225+Q228+Q231+Q234+Q237+Q240+Q243+Q246+Q249+Q252+Q255+Q258+Q261+Q264+Q267+Q270+Q273 -> 13 | R6: =R12+R84+R87+R90+R93+R96+R99+R201+R204+R207+R15+R18+R21+R24+R27+R30+R33+R36+R42+R39+R45+R48+R51+R54+R57+R60+R63+R66+R69+R72+R75+R78+R81+R102+R105+R108+R111+R114+R117+R120+R123+R126+R129+R132+R135+R138+R141+R144+R147+R150+R153+R156+R159+R162+R165+R168+R171+R174+R177+R180+R183+R186+R189+R192+R195+R198+R210+R213+R216+R219+R222+R225+R228+R231+R234+R237+R240+R243+R246+R249+R252+R255+R258+R261+R264+R267+R270+R273 -> 13 | T6: =T12+T84+T87+T90+T93+T96+T99+T201+T204+T207+T15+T18+T21+T24+T27+T30+T33+T36+T42+T39+T45+T48+T51+T54+T57+T60+T63+T66+T69+T72+T75+T78+T81+T102+T105+T108+T111+T114+T117+T120+T123+T126+T129+T132+T135+T138+T141+T144+T147+T150+T153+T156+T159+T162+T165+T168+T171+T174+T177+T180+T183+T186+T189+T192+T195+T198+T210+T213+T216+T219+T222+T225+T228+T231+T234+T237+T240+T243+T246+T249+T252+T255+T258+T261+T264+T267+T270+T273 -> 13 | U6: =U12+U84+U87+U90+U93+U96+U99+U201+U204+U207+U15+U18+U21+U24+U27+U30+U33+U36+U42+U39+U45+U48+U51+U54+U57+U60+U63+U66+U69+U72+U75+U78+U81+U102+U105+U108+U111+U114+U117+U120+U123+U126+U129+U132+U135+U138+U141+U144+U147+U150+U153+U156+U159+U162+U165+U168+U171+U174+U177+U180+U183+U186+U189+U192+U195+U198+U210+U213+U216+U219+U222+U225+U228+U231+U234+U237+U240+U243+U246+U249+U252+U255+U258+U261+U264+U267+U270+U273 -> 13 | AB6: 1
D8: ----------------------------------------------------------------------------------------------------------------------------------------------------------------------> | H8: =H5+I5+H6+I6 -> 120 | I8: Pontos | K8: =K5+L5+K6+L6 -> 121 | L8: Pontos | N8: =N5+O5+N6+O6 -> 166 | O8: Pontos | Q8: =Q5+R5+Q6+R6 -> 54 | R8: Pontos | T8: =T5+U5+T6+U6 -> 54 | U8: Pontos | Z8: Consegue fazer | AA8: sem ajuda | AB8: 1 | AC8: 1
AB9: 1
B11: Faturamento | D11: Emissão de NF de venda (NF-e) | F11: Diario | H11: 1 | I11: 1 | K11: 1 | L11: 1 | N11: 1 | O11: 1 | W11: =H11+K11+N11+Q11+T11 -> 3 | X11: =I11+L11+O11+R11 -> 3 | Z11: Consegue fazer | AA11: e ensinar | AB11: 1 | AC11: 1
H12: 1 | I12: 1 | K12: 1 | L12: 1 | N12: 1 | O12: 1 | W12: =H12+K12+N12+Q12 -> 3 | X12: =I12+L12+O12+R12 -> 3 | AB12: 1 | AC12: 1
B14: Faturamento | D14: Emissão de NF de exportação (NF-e) | F14: Diario | H14: 1 | I14: 1 | K14: 1 | L14: 1 | N14: 1 | O14: 1 | W14: =H14+K14+N14+Q14+T14 -> 3 | X14: =I14+L14+O14+R14 -> 3
H15: 1 | I15: 1 | K15: 1 | L15: 1 | N15: 1 | O15: 1 | W15: =H15+K15+N15+Q15 -> 3 | X15: =I15+L15+O15+R15 -> 3
B17: Faturamento | D17: Emissão de NF de importação (NF-e) | F17: Diario | H17: 1 | I17: 1 | K17: 1 | L17: 1 | N17: 1 | O17: 1 | W17: =H17+K17+N17+Q17+T17 -> 3 | X17: =I17+L17+O17+R17 -> 3
H18: 1 | I18: 1 | K18: 1 | L18: 1 | N18: 1 | O18: 1 | W18: =H18+K18+N18+Q18 -> 3 | X18: =I18+L18+O18+R18 -> 3
B20: Faturamento | D20: Emissão de NF de comodato (NF-e) | F20: Diario | H20: 1 | I20: 1 | K20: 1 | L20: 1 | N20: 1 | O20: 1 | W20: =H20+K20+N20+Q20+T20 -> 3 | X20: =I20+L20+O20+R20 -> 3
H21: 1 | I21: 1 | K21: 1 | L21: 1 | N21: 1 | O21: 1 | W21: =H21+K21+N21+Q21 -> 3 | X21: =I21+L21+O21+R21 -> 3
B23: Faturamento | D23: Emissão de NF de bonificação ou brinde (NF-e) | F23: Diario | H23: 1 | I23: 1 | K23: 1 | L23: 1 | N23: 1 | O23: 1 | W23: =H23+K23+N23+Q23+T23 -> 3 | X23: =I23+L23+O23+R23 -> 3
H24: 1 | I24: 1 | K24: 1 | L24: 1 | N24: 1 | O24: 1 | W24: =H24+K24+N24+Q24 -> 3 | X24: =I24+L24+O24+R24 -> 3
B26: Faturamento | D26: Emissão de NF de demonstração (NF-e) | F26: Diario | H26: 1 | I26: 1 | K26: 1 | L26: 1 | N26: 1 | O26: 1 | W26: =H26+K26+N26+Q26+T26 -> 3 | X26: =I26+L26+O26+R26 -> 3
H27: 1 | I27: 1 | K27: 1 | L27: 1 | N27: 1 | O27: 1 | W27: =H27+K27+N27+Q27 -> 3 | X27: =I27+L27+O27+R27 -> 3
B29: Faturamento | D29: Emissão de NF de troca em garantia (NF-e) | F29: Diario | H29: 1 | I29: 1 | K29: 1 | L29: 1 | N29: 1 | O29: 1 | W29: =H29+K29+N29+Q29+T29 -> 3 | X29: =I29+L29+O29+R29 -> 3
H30: 1 | I30: 1 | K30: 1 | L30: 1 | N30: 1 | O30: 1 | W30: =H30+K30+N30+Q30 -> 3 | X30: =I30+L30+O30+R30 -> 3
B32: Faturamento | D32: Emissão de NF de industrialização (NF-e) | F32: Diario | H32: 1 | I32: 1 | K32: 1 | L32: 1 | N32: 1 | O32: 1 | W32: =H32+K32+N32+Q32+T32 -> 3 | X32: =I32+L32+O32+R32 -> 3
H33: 1 | I33: 1 | K33: 1 | L33: 1 | N33: 1 | O33: 1 | W33: =H33+K33+N33+Q33 -> 3 | X33: =I33+L33+O33+R33 -> 3
B35: Faturamento | D35: Emissão de NF de serviço (NFS-e) | F35: Diario | H35: 1 | I35: 1 | K35: 1 | L35: 1 | N35: 1 | O35: 1 | W35: =H35+K35+N35+Q35+T35 -> 3 | X35: =I35+L35+O35+R35 -> 3
H36: 1 | I36: 1 | K36: 1 | N36: 1 | O36: 1 | W36: =H36+K36+N36+Q36 -> 3 | X36: =I36+L36+O36+R36 -> 2
B38: Faturamento | D38: Emissão de NF de débito (ND) | F38: Diario | H38: 1 | I38: 1 | K38: 1 | L38: 1 | N38: 1 | O38: 1 | W38: =H38+K38+N38+Q38+T38 -> 3 | X38: =I38+L38+O38+R38 -> 3
H39: 1 | I39: 1 | K39: 1 | N39: 1 | O39: 1 | W39: =H39+K39+N39+Q39 -> 3 | X39: =I39+L39+O39+R39 -> 2
B41: Faturamento | D41: Emissão de NF complementar de ICMS (NF-e) | F41: Diario | H41: 1 | I41: 1 | K41: 1 | L41: 1 | N41: 1 | O41: 1 | W41: =H41+K41+N41+Q41+T41 -> 3 | X41: =I41+L41+O41+R41 -> 3
H42: 1 | I42: 1 | K42: 1 | L42: 1 | N42: 1 | O42: 1 | W42: =H42+K42+N42+Q42 -> 3 | X42: =I42+L42+O42+R42 -> 3
B44: Faturamento | D44: Emissão e/ou lançamento de NF de devolução de venda | F44: Diario | H44: 1 | I44: 1 | K44: 1 | L44: 1 | N44: 1 | O44: 1 | W44: =H44+K44+N44+Q44+T44 -> 3 | X44: =I44+L44+O44+R44 -> 3
H45: 1 | I45: 1 | K45: 1 | L45: 1 | N45: 1 | O45: 1 | W45: =H45+K45+N45+Q45 -> 3 | X45: =I45+L45+O45+R45 -> 3
B47: Faturamento | D47: Emissão e/ou lançamento de NF de retorno de comodato | F47: Diario | H47: 1 | I47: 1 | K47: 1 | L47: 1 | N47: 1 | O47: 1 | W47: =H47+K47+N47+Q47+T47 -> 3 | X47: =I47+L47+O47+R47 -> 3
H48: 1 | I48: 1 | K48: 1 | L48: 1 | N48: 1 | O48: 1 | W48: =H48+K48+N48+Q48 -> 3 | X48: =I48+L48+O48+R48 -> 3
B50: Faturamento | D50: Emissão e/ou lançamento de NF de retorno de demonstração | F50: Diario | H50: 1 | I50: 1 | K50: 1 | L50: 1 | N50: 1 | O50: 1 | W50: =H50+K50+N50+Q50+T50 -> 3 | X50: =I50+L50+O50+R50 -> 3
H51: 1 | I51: 1 | K51: 1 | L51: 1 | N51: 1 | O51: 1 | W51: =H51+K51+N51+Q51 -> 3 | X51: =I51+L51+O51+R51 -> 3
B53: Faturamento | D53: Emissão e/ou lançamento de NF de retorno de industrialização | F53: Diario | H53: 1 | I53: 1 | K53: 1 | L53: 1 | N53: 1 | O53: 1 | W53: =H53+K53+N53+Q53+T53 -> 3 | X53: =I53+L53+O53+R53 -> 3
H54: 1 | I54: 1 | K54: 1 | L54: 1 | N54: 1 | O54: 1 | W54: =H54+K54+N54+Q54 -> 3 | X54: =I54+L54+O54+R54 -> 3
B56: Faturamento | D56: Emissão e/ou lançamento de NF de troca em garantia | F56: Diario | H56: 1 | I56: 1 | K56: 1 | L56: 1 | N56: 1 | O56: 1 | W56: =H56+K56+N56+Q56+T56 -> 3 | X56: =I56+L56+O56+R56 -> 3
H57: 1 | I57: 1 | K57: 1 | L57: 1 | N57: 1 | O57: 1 | W57: =H57+K57+N57+Q57 -> 3 | X57: =I57+L57+O57+R57 -> 3
B59: Faturamento | D59: Análise e/ou criação de cadastros de clientes e fornecedores no sistema SAP | F59: Diario | H59: 1 | I59: 1 | K59: 1 | L59: 1 | N59: 1 | O59: 1 | W59: =H59+K59+N59+Q59+T59 -> 3 | X59: =I59+L59+O59+R59 -> 3
H60: 1 | I60: 1 | K60: 1 | L60: 1 | N60: 1 | O60: 1 | W60: =H60+K60+N60+Q60 -> 3 | X60: =I60+L60+O60+R60 -> 3
B62: Faturamento | D62: Análise de possível emissão de guia DIFAL (diferencial de alíquotas) | F62: Diario | H62: 1 | I62: 1 | K62: 1 | L62: 1 | N62: 1 | O62: 1 | W62: =H62+K62+N62+Q62+T62 -> 3 | X62: =I62+L62+O62+R62 -> 3
H63: 1 | I63: 1 | K63: 1 | L63: 1 | N63: 1 | O63: 1 | W63: =H63+K63+N63+Q63 -> 3 | X63: =I63+L63+O63+R63 -> 3
B65: Faturamento | D65: Confirmação de pagamento dos pedidos de venda com acesso ao banco Itaú | F65: Diario | H65: 1 | I65: 1 | N65: 1 | O65: 1 | W65: =H65+K65+N65+Q65+T65 -> 2 | X65: =I65+L65+O65+R65 -> 2
H66: 1 | I66: 1 | N66: 1 | O66: 1 | W66: =H66+K66+N66+Q66 -> 2 | X66: =I66+L66+O66+R66 -> 2
B68: Faturamento | D68: Emissão de fatura de adiantamento no pedido de venda | F68: Diario | H68: 1 | I68: 1 | N68: 1 | O68: 1 | W68: =H68+K68+N68+Q68+T68 -> 2 | X68: =I68+L68+O68+R68 -> 2
H69: 1 | I69: 1 | N69: 1 | O69: 1 | W69: =H69+K69+N69+Q69 -> 2 | X69: =I69+L69+O69+R69 -> 2
B71: Faturamento | D71: Controle das mensalidades de locação na planilha Excel junto com o sistema SAP | F71: Diario | H71: 1 | I71: 1 | K71: 1 | L71: 1 | N71: 1 | O71: 1 | W71: =H71+K71+N71+Q71+T71 -> 3 | X71: =I71+L71+O71+R71 -> 3
H72: 1 | I72: 1 | K72: 1 | L72: 1 | N72: 1 | O72: 1 | W72: =H72+K72+N72+Q72 -> 3 | X72: =I72+L72+O72+R72 -> 3
B74: Faturamento | D74: Envio manual via e-mail das notas de débito e boletos para o respectivos clientes | F74: Diario | H74: 1 | I74: 1 | K74: 1 | L74: 1 | N74: 1 | O74: 1 | W74: =H74+K74+N74+Q74+T74 -> 3 | X74: =I74+L74+O74+R74 -> 3
H75: 1 | I75: 1 | K75: 1 | L75: 1 | N75: 1 | O75: 1 | W75: =H75+K75+N75+Q75 -> 3 | X75: =I75+L75+O75+R75 -> 3
B77: Faturamento | D77: Análise e controle das mensalidades de manuntenção de equipamentos, para a posterior emissão de NFS-e | F77: Diario | H77: 1 | I77: 1 | N77: 1 | O77: 1 | W77: =H77+K77+N77+Q77+T77 -> 2 | X77: =I77+L77+O77+R77 -> 2
H78: 1 | I78: 1 | N78: 1 | O78: 1 | W78: =H78+K78+N78+Q78 -> 2 | X78: =I78+L78+O78+R78 -> 2
B80: Faturamento | D80: Análise de novos contratos de locação novos / Planilhamento / cadastro no SAP, emissão das notas de débito (ND) | F80: Diario | H80: 1 | I80: 1 | N80: 1 | O80: 1 | W80: =H80+K80+N80+Q80+T80 -> 2 | X80: =I80+L80+O80+R80 -> 2
H81: 1 | I81: 1 | N81: 1 | O81: 1 | W81: =H81+K81+N81+Q81 -> 2 | X81: =I81+L81+O81+R81 -> 2
B83: Faturamento | D83: Análise de contratos de locação em andamento | F83: Diario | H83: 1 | I83: 1 | N83: 1 | O83: 1 | W83: =H83+K83+N83+Q83+T83 -> 2 | X83: =I83+L83+O83+R83 -> 2
H84: 1 | I84: 1 | N84: 1 | O84: 1 | W84: =H84+K84+N84+Q84 -> 2 | X84: =I84+L84+O84+R84 -> 2
B86: Faturamento | D86: Análise de possíveis reajuste contratuais nas parcelas dos contratos de locação/manuntenção | F86: Diario | H86: 1 | I86: 1 | N86: 1 | O86: 1 | W86: =H86+K86+N86+Q86+T86 -> 2 | X86: =I86+L86+O86+R86 -> 2
H87: 1 | I87: 1 | N87: 1 | O87: 1 | W87: =H87+K87+N87+Q87 -> 2 | X87: =I87+L87+O87+R87 -> 2
B89: Faturamento | D89: Controle de retorno de comodato da Geneslab / emissão NF de venda | F89: Diario | H89: 1 | I89: 1 | N89: 1 | O89: 1 | W89: =H89+K89+N89+Q89+T89 -> 2 | X89: =I89+L89+O89+R89 -> 2
H90: 1 | I90: 1 | N90: 1 | O90: 1 | W90: =H90+K90+N90+Q90 -> 2 | X90: =I90+L90+O90+R90 -> 2
B92: Faturamento | D92: Suporte e Orientações aos setores (help desk, comercial, adequação, almoxarifado) | F92: Diario | H92: 1 | I92: 1 | K92: 1 | L92: 1 | N92: 1 | O92: 1 | W92: =H92+K92+N92+Q92+T92 -> 3 | X92: =I92+L92+O92+R92 -> 3
H93: 1 | I93: 1 | K93: 1 | L93: 1 | N93: 1 | O93: 1 | W93: =H93+K93+N93+Q93 -> 3 | X93: =I93+L93+O93+R93 -> 3
B95: Faturamento | D95: Resolução de problemas e/ou dúvidas de clientes, via e-mail, telefone, whatsapp | F95: Diario | H95: 1 | I95: 1 | K95: 1 | L95: 1 | N95: 1 | O95: 1 | W95: =H95+K95+N95+Q95+T95 -> 3 | X95: =I95+L95+O95+R95 -> 3
H96: 1 | I96: 1 | K96: 1 | L96: 1 | N96: 1 | O96: 1 | W96: =H96+K96+N96+Q96 -> 3 | X96: =I96+L96+O96+R96 -> 3
B98: Faturamento | D98: Análise de impostos e tributações das operações em geral | F98: Diario | H98: 1 | I98: 1 | K98: 1 | L98: 1 | N98: 1 | O98: 1 | W98: =H98+K98+N98+Q98+T98 -> 3 | X98: =I98+L98+O98+R98 -> 3
H99: 1 | I99: 1 | K99: 1 | L99: 1 | N99: 1 | O99: 1 | W99: =H99+K99+N99+Q99 -> 3 | X99: =I99+L99+O99+R99 -> 3
B101: Recebimento | D101: Lançamento de notas com pedido de compra | F101: Diario | K101: 1 | L101: 1 | N101: 1 | O101: 1 | Q101: 1 | R101: 1 | T101: 1 | U101: 1 | W101: =H101+K101+N101+Q101+T101 -> 4 | X101: =I101+L101+O101+R101 -> 3
K102: 1 | N102: 1 | O102: 1 | Q102: 1 | R102: 1 | T102: 1 | U102: 1 | W102: =H102+K102+N102+Q102 -> 3 | X102: =I102+L102+O102+R102 -> 2
B104: Recebimento | D104: Lançamento de notas recorrentes | F104: Diario | K104: 1 | N104: 1 | O104: 1 | Q104: 1 | R104: 1 | T104: 1 | U104: 1 | W104: =H104+K104+N104+Q104+T104 -> 4 | X104: =I104+L104+O104+R104 -> 2
N105: 1 | O105: 1 | Q105: 1 | R105: 1 | T105: 1 | U105: 1 | W105: =H105+K105+N105+Q105 -> 2 | X105: =I105+L105+O105+R105 -> 2
B107: Recebimento | D107: Lançamentos de guias e impostos (LCM) | F107: Diario | K107: 1 | N107: 1 | O107: 1 | Q107: 1 | R107: 1 | T107: 1 | U107: 1 | W107: =H107+K107+N107+Q107+T107 -> 4 | X107: =I107+L107+O107+R107 -> 2
Q108: 1 | R108: 1 | T108: 1 | U108: 1 | W108: =H108+K108+N108+Q108 -> 1 | X108: =I108+L108+O108+R108 -> 1
B110: Recebimento | D110: Lançamento da folha de pagamento | F110: Mensal | K110: 1 | N110: 1 | Q110: 1 | R110: 1 | T110: 1 | U110: 1 | W110: =H110+K110+N110+Q110+T110 -> 4 | X110: =I110+L110+O110+R110 -> 1
Q111: 1 | R111: 1 | T111: 1 | U111: 1 | W111: =H111+K111+N111+Q111 -> 1 | X111: =I111+L111+O111+R111 -> 1
B113: Recebimento | D113: Controle de notas de entrada | F113: Diario | K113: 1 | N113: 1 | O113: 1 | Q113: 1 | R113: 1 | T113: 1 | U113: 1 | W113: =H113+K113+N113+Q113+T113 -> 4 | X113: =I113+L113+O113+R113 -> 2
N114: 1 | O114: 1 | Q114: 1 | R114: 1 | T114: 1 | U114: 1 | W114: =H114+K114+N114+Q114 -> 2 | X114: =I114+L114+O114+R114 -> 2
B116: Recebimento | D116: Lançamento de fatura de cartão de crédito | F116: Mensal | K116: 1 | N116: 1 | Q116: 1 | R116: 1 | T116: 1 | U116: 1 | W116: =H116+K116+N116+Q116+T116 -> 4 | X116: =I116+L116+O116+R116 -> 1
Q117: 1 | R117: 1 | T117: 1 | U117: 1 | W117: =H117+K117+N117+Q117 -> 1 | X117: =I117+L117+O117+R117 -> 1
B119: Recebimento | D119: Abertura de pedidos recorrentes | F119: Diario | N119: 1 | O119: 1 | Q119: 1 | R119: 1 | T119: 1 | U119: 1 | W119: =H119+K119+N119+Q119+T119 -> 3 | X119: =I119+L119+O119+R119 -> 2
N120: 1 | O120: 1 | Q120: 1 | R120: 1 | T120: 1 | U120: 1 | W120: =H120+K120+N120+Q120 -> 2 | X120: =I120+L120+O120+R120 -> 2
B122: Recebimento | D122: Fatura de adiantamento para fornecedor | F122: Diario | N122: 1 | O122: 1 | Q122: 1 | R122: 1 | T122: 1 | U122: 1 | W122: =H122+K122+N122+Q122+T122 -> 3 | X122: =I122+L122+O122+R122 -> 2
N123: 1 | O123: 1 | Q123: 1 | R123: 1 | T123: 1 | U123: 1 | W123: =H123+K123+N123+Q123 -> 2 | X123: =I123+L123+O123+R123 -> 2
B125: Recebimento | D125: Importar arquivos XML de saídas para o Arquivei | F125: Diario | N125: 1 | O125: 1 | Q125: 1 | R125: 1 | T125: 1 | U125: 1 | W125: =H125+K125+N125+Q125+T125 -> 3 | X125: =I125+L125+O125+R125 -> 2
N126: 1 | O126: 1 | Q126: 1 | R126: 1 | T126: 1 | U126: 1 | W126: =H126+K126+N126+Q126 -> 2 | X126: =I126+L126+O126+R126 -> 2
B128: Recebimento | D128: Envio de documentos à contabilidade externa | F128: Mensal | N128: 1 | Q128: 1 | R128: 1 | T128: 1 | U128: 1 | W128: =H128+K128+N128+Q128+T128 -> 3 | X128: =I128+L128+O128+R128 -> 1
Q129: 1 | R129: 1 | T129: 1 | U129: 1 | W129: =H129+K129+N129+Q129 -> 1 | X129: =I129+L129+O129+R129 -> 1
B131: Recebimento | D131: Efetivar lançamentos de impostos em débito automático | F131: Mensal | N131: 1 | Q131: 1 | R131: 1 | T131: 1 | U131: 1 | W131: =H131+K131+N131+Q131+T131 -> 3 | X131: =I131+L131+O131+R131 -> 1
Q132: 1 | R132: 1 | T132: 1 | U132: 1 | W132: =H132+K132+N132+Q132 -> 1 | X132: =I132+L132+O132+R132 -> 1
B134: Recebimento | D134: Lançamento de Cte | F134: Diario | N134: 1 | O134: 1 | Q134: 1 | R134: 1 | T134: 1 | U134: 1 | W134: =H134+K134+N134+Q134+T134 -> 3 | X134: =I134+L134+O134+R134 -> 2
N135: 1 | O135: 1 | Q135: 1 | R135: 1 | T135: 1 | U135: 1 | W135: =H135+K135+N135+Q135 -> 2 | X135: =I135+L135+O135+R135 -> 2
B137: Recebimento | D137: Lançamento de multas de trânsito | F137: Diario | N137: 1 | O137: 1 | Q137: 1 | R137: 1 | T137: 1 | U137: 1 | W137: =H137+K137+N137+Q137+T137 -> 3 | X137: =I137+L137+O137+R137 -> 2
Q138: 1 | R138: 1 | T138: 1 | U138: 1 | W138: =H138+K138+N138+Q138 -> 1 | X138: =I138+L138+O138+R138 -> 1
B140: Recebimento | D140: Lançamentos de Importação Simpificada (Courrier) | F140: Diario | N140: 1 | O140: 1 | W140: =H140+K140+N140+Q140+T140 -> 1 | X140: =I140+L140+O140+R140 -> 1
W141: =H141+K141+N141+Q141 -> 0 | X141: =I141+L141+O141+R141 -> 0
B143: Recebimento | D143: Emissão de nota fiscal de Importação Simpificada (Courrier) | F143: Diario | K143: 1 | L143: 1 | N143: 1 | O143: 1 | Q143: 1 | R143: 1 | T143: 1 | U143: 1 | W143: =H143+K143+N143+Q143+T143 -> 4 | X143: =I143+L143+O143+R143 -> 3
K144: 1 | N144: 1 | W144: =H144+K144+N144+Q144 -> 2 | X144: =I144+L144+O144+R144 -> 0
F146: Diario | W146: =H146+K146+N146+Q146+T146 -> 0 | X146: =I146+L146+O146+R146 -> 0
W147: =H147+K147+N147+Q147 -> 0 | X147: =I147+L147+O147+R147 -> 0
F149: Diario | W149: =H149+K149+N149+Q149+T149 -> 0 | X149: =I149+L149+O149+R149 -> 0
W150: =H150+K150+N150+Q150 -> 0 | X150: =I150+L150+O150+R150 -> 0
...

Sheet Outubro 2025
B2: Setorização | D2: Tarefas | F2: Periodicidade | H2: Luis | K2: Alexandre | N2: Lucas | Q2: Pamella | T2: Loraine
H3: Gerente | K3: Supervisor
D5: Classificação do Colaborador | H5: =H11+H83+H86+H89+H92+H95+H98+H200+H203+H206+H14+H17+H20+H23+H26+H29+H32+H35+H41+H38+H44+H47+H50+H53+H56+H59+H62+H65+H68+H71+H74+H77+H80+H101+H104+H107+H110+H113+H116+H119+H122+H125+H128+H131+H134+H137+H140+H143+H146+H149+H152+H155+H158+H161+H164+H167+H170+H173+H176+H179+H182+H185+H188+H191+H194+H197+H209+H212+H215+H218+H221+H224+H227+H230+H233+H236+H239+H242+H245+H248+H251+H254+H257+H260+H263+H266+H269+H272 -> 36 | I5: =I11+I83+I86+I89+I92+I95+I98+I200+I203+I206+I14+I17+I20+I23+I26+I29+I32+I35+I41+I38+I44+I47+I50+I53+I56+I59+I62+I65+I68+I71+I74+I77+I80+I101+I104+I107+I110+I113+I116+I119+I122+I125+I128+I131+I134+I137+I140+I143+I146+I149+I152+I155+I158+I161+I164+I167+I170+I173+I176+I179+I182+I185+I188+I191+I194+I197+I209+I212+I215+I218+I221+I224+I227+I230+I233+I236+I239+I242+I245+I248+I251+I254+I257+I260+I263+I266+I269+I272 -> 36 | K5: =K11+K83+K86+K89+K92+K95+K98+K200+K203+K206+K14+K17+K20+K23+K26+K29+K32+K35+K41+K38+K44+K47+K50+K53+K56+K59+K62+K65+K68+K71+K74+K77+K80+K101+K104+K107+K110+K113+K116+K119+K122+K125+K128+K131+K134+K137+K140+K143+K146+K149+K152+K155+K158+K161+K164+K167+K170+K173+K176+K179+K182+K185+K188+K191+K194+K197+K209+K212+K215+K218+K221+K224+K227+K230+K233+K236+K239+K242+K245+K248+K251+K254+K257+K260+K263+K266+K269+K272 -> 46 | L5: =L11+L83+L86+L89+L92+L95+L98+L200+L203+L206+L14+L17+L20+L23+L26+L29+L32+L35+L41+L38+L44+L47+L50+L53+L56+L59+L62+L65+L68+L71+L74+L77+L80+L101+L104+L107+L110+L113+L116+L119+L122+L125+L128+L131+L134+L137+L140+L143+L146+L149+L152+L155+L158+L161+L164+L167+L170+L173+L176+L179+L182+L185+L188+L191+L194+L197+L209+L212+L215+L218+L221+L224+L227+L230+L233+L236+L239+L242+L245+L248+L251+L254+L257+L260+L263+L266+L269+L272 -> 46 | N5: =N11+N83+N86+N89+N92+N95+N98+N200+N203+N206+N14+N17+N20+N23+N26+N29+N32+N35+N41+N38+N44+N47+N50+N53+N56+N59+N62+N65+N68+N71+N74+N77+N80+N101+N104+N107+N110+N113+N116+N119+N122+N125+N128+N131+N134+N137+N140+N143+N146+N149+N152+N155+N158+N161+N164+N167+N170+N173+N176+N179+N182+N185+N188+N191+N194+N197+N209+N212+N215+N218+N221+N224+N227+N230+N233+N236+N239+N242+N245+N248+N251+N254+N257+N260+N263+N266+N269+N272 -> 51 | O5: =O11+O83+O86+O89+O92+O95+O98+O200+O203+O206+O14+O17+O20+O23+O26+O29+O32+O35+O41+O38+O44+O47+O50+O53+O56+O59+O62+O65+O68+O71+O74+O77+O80+O101+O104+O107+O110+O113+O116+O119+O122+O125+O128+O131+O134+O137+O140+O143+O146+O149+O152+O155+O158+O161+O164+O167+O170+O173+O176+O179+O182+O185+O188+O191+O194+O197+O209+O212+O215+O218+O221+O224+O227+O230+O233+O236+O239+O242+O245+O248+O251+O254+O257+O260+O263+O266+O269+O272 -> 42 | Q5: =Q11+Q83+Q86+Q89+Q92+Q95+Q98+Q200+Q203+Q206+Q14+Q17+Q20+Q23+Q26+Q29+Q32+Q35+Q41+Q38+Q44+Q47+Q50+Q53+Q56+Q59+Q62+Q65+Q68+Q71+Q74+Q77+Q80+Q101+Q104+Q107+Q110+Q113+Q116+Q119+Q122+Q125+Q128+Q131+Q134+Q137+Q140+Q143+Q146+Q149+Q152+Q155+Q158+Q161+Q164+Q167+Q170+Q173+Q176+Q179+Q182+Q185+Q188+Q191+Q194+Q197+Q209+Q212+Q215+Q218+Q221+Q224+Q227+Q230+Q233+Q236+Q239+Q242+Q245+Q248+Q251+Q254+Q257+Q260+Q263+Q266+Q269+Q272 -> 14 | R5: =R11+R83+R86+R89+R92+R95+R98+R200+R203+R206+R14+R17+R20+R23+R26+R29+R32+R35+R41+R38+R44+R47+R50+R53+R56+R59+R62+R65+R68+R71+R74+R77+R80+R101+R104+R107+R110+R113+R116+R119+R122+R125+R128+R131+R134+R137+R140+R143+R146+R149+R152+R155+R158+R161+R164+R167+R170+R173+R176+R179+R182+R185+R188+R191+R194+R197+R209+R212+R215+R218+R221+R224+R227+R230+R233+R236+R239+R242+R245+R248+R251+R254+R257+R260+R263+R266+R269+R272 -> 14 | T5: =T11+T83+T86+T89+T92+T95+T98+T200+T203+T206+T14+T17+T20+T23+T26+T29+T32+T35+T41+T38+T44+T47+T50+T53+T56+T59+T62+T65+T68+T71+T74+T77+T80+T101+T104+T107+T110+T113+T116+T119+T122+T125+T128+T131+T134+T137+T140+T143+T146+T149+T152+T155+T158+T161+T164+T167+T170+T173+T176+T179+T182+T185+T188+T191+T194+T197+T209+T212+T215+T218+T221+T224+T227+T230+T233+T236+T239+T242+T245+T248+T251+T254+T257+T260+T263+T266+T269+T272 -> 0 | U5: =U11+U83+U86+U89+U92+U95+U98+U200+U203+U206+U14+U17+U20+U23+U26+U29+U32+U35+U41+U38+U44+U47+U50+U53+U56+U59+U62+U65+U68+U71+U74+U77+U80+U101+U104+U107+U110+U113+U116+U119+U122+U125+U128+U131+U134+U137+U140+U143+U146+U149+U152+U155+U158+U161+U164+U167+U170+U173+U176+U179+U182+U185+U188+U191+U194+U197+U209+U212+U215+U218+U221+U224+U227+U230+U233+U236+U239+U242+U245+U248+U251+U254+U257+U260+U263+U266+U269+U272 -> 0
H6: =H12+H84+H87+H90+H93+H96+H99+H201+H204+H207+H15+H18+H21+H24+H27+H30+H33+H36+H42+H39+H45+H48+H51+H54+H57+H60+H63+H66+H69+H72+H75+H78+H81+H102+H105+H108+H111+H114+H117+H120+H123+H126+H129+H132+H135+H138+H141+H144+H147+H150+H153+H156+H159+H162+H165+H168+H171+H174+H177+H180+H183+H186+H189+H192+H195+H198+H210+H213+H216+H219+H222+H225+H228+H231+H234+H237+H240+H243+H246+H249+H252+H255+H258+H261+H264+H267+H270+H273 -> 36 | I6: =I12+I84+I87+I90+I93+I96+I99+I201+I204+I207+I15+I18+I21+I24+I27+I30+I33+I36+I42+I39+I45+I48+I51+I54+I57+I60+I63+I66+I69+I72+I75+I78+I81+I102+I105+I108+I111+I114+I117+I120+I123+I126+I129+I132+I135+I138+I141+I144+I147+I150+I153+I156+I159+I162+I165+I168+I171+I174+I177+I180+I183+I186+I189+I192+I195+I198+I210+I213+I216+I219+I222+I225+I228+I231+I234+I237+I240+I243+I246+I249+I252+I255+I258+I261+I264+I267+I270+I273 -> 36 | K6: =K12+K84+K87+K90+K93+K96+K99+K201+K204+K207+K15+K18+K21+K24+K27+K30+K33+K36+K42+K39+K45+K48+K51+K54+K57+K60+K63+K66+K69+K72+K75+K78+K81+K102+K105+K108+K111+K114+K117+K120+K123+K126+K129+K132+K135+K138+K141+K144+K147+K150+K153+K156+K159+K162+K165+K168+K171+K174+K177+K180+K183+K186+K189+K192+K195+K198+K210+K213+K216+K219+K222+K225+K228+K231+K234+K237+K240+K243+K246+K249+K252+K255+K258+K261+K264+K267+K270+K273 -> 43 | L6: =L12+L84+L87+L90+L93+L96+L99+L201+L204+L207+L15+L18+L21+L24+L27+L30+L33+L36+L42+L39+L45+L48+L51+L54+L57+L60+L63+L66+L69+L72+L75+L78+L81+L102+L105+L108+L111+L114+L117+L120+L123+L126+L129+L132+L135+L138+L141+L144+L147+L150+L153+L156+L159+L162+L165+L168+L171+L174+L177+L180+L183+L186+L189+L192+L195+L198+L210+L213+L216+L219+L222+L225+L228+L231+L234+L237+L240+L243+L246+L249+L252+L255+L258+L261+L264+L267+L270+L273 -> 40 | N6: =N12+N84+N87+N90+N93+N96+N99+N201+N204+N207+N15+N18+N21+N24+N27+N30+N33+N36+N42+N39+N45+N48+N51+N54+N57+N60+N63+N66+N69+N72+N75+N78+N81+N102+N105+N108+N111+N114+N117+N120+N123+N126+N129+N132+N135+N138+N141+N144+N147+N150+N153+N156+N159+N162+N165+N168+N171+N174+N177+N180+N183+N186+N189+N192+N195+N198+N210+N213+N216+N219+N222+N225+N228+N231+N234+N237+N240+N243+N246+N249+N252+N255+N258+N261+N264+N267+N270+N273 -> 39 | O6: =O12+O84+O87+O90+O93+O96+O99+O201+O204+O207+O15+O18+O21+O24+O27+O30+O33+O36+O42+O39+O45+O48+O51+O54+O57+O60+O63+O66+O69+O72+O75+O78+O81+O102+O105+O108+O111+O114+O117+O120+O123+O126+O129+O132+O135+O138+O141+O144+O147+O150+O153+O156+O159+O162+O165+O168+O171+O174+O177+O180+O183+O186+O189+O192+O195+O198+O210+O213+O216+O219+O222+O225+O228+O231+O234+O237+O240+O243+O246+O249+O252+O255+O258+O261+O264+O267+O270+O273 -> 38 | Q6: =Q12+Q84+Q87+Q90+Q93+Q96+Q99+Q201+Q204+Q207+Q15+Q18+Q21+Q24+Q27+Q30+Q33+Q36+Q42+Q39+Q45+Q48+Q51+Q54+Q57+Q60+Q63+Q66+Q69+Q72+Q75+Q78+Q81+Q102+Q105+Q108+Q111+Q114+Q117+Q120+Q123+Q126+Q129+Q132+Q135+Q138+Q141+Q144+Q147+Q150+Q153+Q156+Q159+Q162+Q165+Q168+Q171+Q174+Q177+Q180+Q183+Q186+Q189+Q192+Q195+Q198+Q210+Q213+Q216+Q219+Q222+Q225+Q228+Q231+Q234+Q237+Q240+Q243+Q246+Q249+Q252+Q255+Q258+Q261+Q264+Q267+Q270+Q273 -> 13 | R6: =R12+R84+R87+R90+R93+R96+R99+R201+R204+R207+R15+R18+R21+R24+R27+R30+R33+R36+R42+R39+R45+R48+R51+R54+R57+R60+R63+R66+R69+R72+R75+R78+R81+R102+R105+R108+R111+R114+R117+R120+R123+R126+R129+R132+R135+R138+R141+R144+R147+R150+R153+R156+R159+R162+R165+R168+R171+R174+R177+R180+R183+R186+R189+R192+R195+R198+R210+R213+R216+R219+R222+R225+R228+R231+R234+R237+R240+R243+R246+R249+R252+R255+R258+R261+R264+R267+R270+R273 -> 13 | T6: =T12+T84+T87+T90+T93+T96+T99+T201+T204+T207+T15+T18+T21+T24+T27+T30+T33+T36+T42+T39+T45+T48+T51+T54+T57+T60+T63+T66+T69+T72+T75+T78+T81+T102+T105+T108+T111+T114+T117+T120+T123+T126+T129+T132+T135+T138+T141+T144+T147+T150+T153+T156+T159+T162+T165+T168+T171+T174+T177+T180+T183+T186+T189+T192+T195+T198+T210+T213+T216+T219+T222+T225+T228+T231+T234+T237+T240+T243+T246+T249+T252+T255+T258+T261+T264+T267+T270+T273 -> 0 | U6: =U12+U84+U87+U90+U93+U96+U99+U201+U204+U207+U15+U18+U21+U24+U27+U30+U33+U36+U42+U39+U45+U48+U51+U54+U57+U60+U63+U66+U69+U72+U75+U78+U81+U102+U105+U108+U111+U114+U117+U120+U123+U126+U129+U132+U135+U138+U141+U144+U147+U150+U153+U156+U159+U162+U165+U168+U171+U174+U177+U180+U183+U186+U189+U192+U195+U198+U210+U213+U216+U219+U222+U225+U228+U231+U234+U237+U240+U243+U246+U249+U252+U255+U258+U261+U264+U267+U270+U273 -> 0
D8: ----------------------------------------------------------------------------------------------------------------------------------------------------------------------> | H8: =H5+I5+H6+I6 -> 144 | I8: Pontos | K8: =K5+L5+K6+L6 -> 175 | L8: Pontos | N8: =N5+O5+N6+O6 -> 170 | O8: Pontos | Q8: =Q5+R5+Q6+R6 -> 54 | R8: Pontos | T8: =T5+U5+T6+U6 -> 0 | U8: Pontos
W9: Semáforo | Z9: Legenda:
B11: Faturamento | D11: Emissão de NF de venda (NF-e) | F11: Diario | H11: 1 | I11: 1 | K11: 1 | L11: 1 | N11: 1 | O11: 1 | W11: =H11+K11+N11+Q11+T11 -> 3 | X11: =I11+L11+O11+R11+U11 -> 3 | AA11: Aprendendo | AB11: 1
H12: 1 | I12: 1 | K12: 1 | L12: 1 | N12: 1 | O12: 1 | W12: =H12+K12+N12+Q12+T12 -> 3 | X12: =I12+L12+O12+R12+U12 -> 3
B14: Faturamento | D14: Emissão de NF de exportação (NF-e) | F14: Diario | H14: 1 | I14: 1 | K14: 1 | L14: 1 | N14: 1 | O14: 1 | W14: =H14+K14+N14+Q14+T14 -> 3 | X14: =I14+L14+O14+R14+U14 -> 3 | Z14: Consegue fazer | AA14: com ajuda | AB14: 1
H15: 1 | I15: 1 | K15: 1 | L15: 1 | N15: 1 | O15: 1 | W15: =H15+K15+N15+Q15+T15 -> 3 | X15: =I15+L15+O15+R15+U15 -> 3 | AB15: 1
B17: Faturamento | D17: Emissão de NF de importação (NF-e) | F17: Diario | H17: 1 | I17: 1 | K17: 1 | L17: 1 | N17: 1 | O17: 1 | W17: =H17+K17+N17+Q17+T17 -> 3 | X17: =I17+L17+O17+R17+U17 -> 3 | Z17: Consegue fazer | AA17: sem ajuda | AB17: 1 | AC17: 1
H18: 1 | I18: 1 | K18: 1 | L18: 1 | N18: 1 | O18: 1 | W18: =H18+K18+N18+Q18+T18 -> 3 | X18: =I18+L18+O18+R18+U18 -> 3 | Z18: (Sei fazer, mas não sei porque faço) | AB18: 1
B20: Faturamento | D20: Emissão de NF de comodato (NF-e) | F20: Diario | H20: 1 | I20: 1 | K20: 1 | L20: 1 | N20: 1 | O20: 1 | W20: =H20+K20+N20+Q20+T20 -> 3 | X20: =I20+L20+O20+R20+U20 -> 3 | Z20: Consegue fazer | AA20: e ensinar | AB20: 1 | AC20: 1
H21: 1 | I21: 1 | K21: 1 | L21: 1 | N21: 1 | O21: 1 | W21: =H21+K21+N21+Q21+T21 -> 3 | X21: =I21+L21+O21+R21+U21 -> 3 | Z21: (Sei fazer, e sei porque faço) | AB21: 1 | AC21: 1
B23: Faturamento | D23: Emissão de NF de bonificação ou brinde (NF-e) | F23: Diario | H23: 1 | I23: 1 | K23: 1 | L23: 1 | N23: 1 | O23: 1 | W23: =H23+K23+N23+Q23+T23 -> 3 | X23: =I23+L23+O23+R23+U23 -> 3
H24: 1 | I24: 1 | K24: 1 | L24: 1 | N24: 1 | O24: 1 | W24: =H24+K24+N24+Q24+T24 -> 3 | X24: =I24+L24+O24+R24+U24 -> 3
B26: Faturamento | D26: Emissão de NF de demonstração (NF-e) | F26: Diario | H26: 1 | I26: 1 | K26: 1 | L26: 1 | N26: 1 | O26: 1 | W26: =H26+K26+N26+Q26+T26 -> 3 | X26: =I26+L26+O26+R26+U26 -> 3
H27: 1 | I27: 1 | K27: 1 | L27: 1 | N27: 1 | O27: 1 | W27: =H27+K27+N27+Q27+T27 -> 3 | X27: =I27+L27+O27+R27+U27 -> 3
B29: Faturamento | D29: Emissão de NF de troca em garantia (NF-e) | F29: Diario | H29: 1 | I29: 1 | K29: 1 | L29: 1 | N29: 1 | O29: 1 | W29: =H29+K29+N29+Q29+T29 -> 3 | X29: =I29+L29+O29+R29+U29 -> 3
H30: 1 | I30: 1 | K30: 1 | L30: 1 | N30: 1 | O30: 1 | W30: =H30+K30+N30+Q30+T30 -> 3 | X30: =I30+L30+O30+R30+U30 -> 3
B32: Faturamento | D32: Emissão de NF de industrialização (NF-e) | F32: Diario | H32: 1 | I32: 1 | K32: 1 | L32: 1 | N32: 1 | O32: 1 | W32: =H32+K32+N32+Q32+T32 -> 3 | X32: =I32+L32+O32+R32+U32 -> 3
H33: 1 | I33: 1 | K33: 1 | L33: 1 | N33: 1 | O33: 1 | W33: =H33+K33+N33+Q33+T33 -> 3 | X33: =I33+L33+O33+R33+U33 -> 3
B35: Faturamento | D35: Emissão de NF de serviço (NFS-e) | F35: Diario | H35: 1 | I35: 1 | K35: 1 | L35: 1 | N35: 1 | O35: 1 | W35: =H35+K35+N35+Q35+T35 -> 3 | X35: =I35+L35+O35+R35+U35 -> 3
H36: 1 | I36: 1 | K36: 1 | N36: 1 | O36: 1 | W36: =H36+K36+N36+Q36+T36 -> 3 | X36: =I36+L36+O36+R36+U36 -> 2
B38: Faturamento | D38: Emissão de NF de débito (ND) | F38: Diario | H38: 1 | I38: 1 | K38: 1 | L38: 1 | N38: 1 | O38: 1 | W38: =H38+K38+N38+Q38+T38 -> 3 | X38: =I38+L38+O38+R38+U38 -> 3
H39: 1 | I39: 1 | K39: 1 | N39: 1 | O39: 1 | W39: =H39+K39+N39+Q39+T39 -> 3 | X39: =I39+L39+O39+R39+U39 -> 2
B41: Faturamento | D41: Emissão de NF complementar de ICMS (NF-e) | F41: Diario | H41: 1 | I41: 1 | K41: 1 | L41: 1 | N41: 1 | O41: 1 | W41: =H41+K41+N41+Q41+T41 -> 3 | X41: =I41+L41+O41+R41+U41 -> 3
H42: 1 | I42: 1 | K42: 1 | L42: 1 | N42: 1 | O42: 1 | W42: =H42+K42+N42+Q42+T42 -> 3 | X42: =I42+L42+O42+R42+U42 -> 3
B44: Faturamento | D44: Emissão e/ou lançamento de NF de devolução de venda | F44: Diario | H44: 1 | I44: 1 | K44: 1 | L44: 1 | N44: 1 | O44: 1 | W44: =H44+K44+N44+Q44+T44 -> 3 | X44: =I44+L44+O44+R44+U44 -> 3
H45: 1 | I45: 1 | K45: 1 | L45: 1 | N45: 1 | O45: 1 | W45: =H45+K45+N45+Q45+T45 -> 3 | X45: =I45+L45+O45+R45+U45 -> 3
B47: Faturamento | D47: Emissão e/ou lançamento de NF de retorno de comodato | F47: Diario | H47: 1 | I47: 1 | K47: 1 | L47: 1 | N47: 1 | O47: 1 | W47: =H47+K47+N47+Q47+T47 -> 3 | X47: =I47+L47+O47+R47+U47 -> 3
H48: 1 | I48: 1 | K48: 1 | L48: 1 | N48: 1 | O48: 1 | W48: =H48+K48+N48+Q48+T48 -> 3 | X48: =I48+L48+O48+R48+U48 -> 3
B50: Faturamento | D50: Emissão e/ou lançamento de NF de retorno de demonstração | F50: Diario | H50: 1 | I50: 1 | K50: 1 | L50: 1 | N50: 1 | O50: 1 | W50: =H50+K50+N50+Q50+T50 -> 3 | X50: =I50+L50+O50+R50+U50 -> 3
H51: 1 | I51: 1 | K51: 1 | L51: 1 | N51: 1 | O51: 1 | W51: =H51+K51+N51+Q51+T51 -> 3 | X51: =I51+L51+O51+R51+U51 -> 3
B53: Faturamento | D53: Emissão e/ou lançamento de NF de retorno de industrialização | F53: Diario | H53: 1 | I53: 1 | K53: 1 | L53: 1 | N53: 1 | O53: 1 | W53: =H53+K53+N53+Q53+T53 -> 3 | X53: =I53+L53+O53+R53+U53 -> 3
H54: 1 | I54: 1 | K54: 1 | L54: 1 | N54: 1 | O54: 1 | W54: =H54+K54+N54+Q54+T54 -> 3 | X54: =I54+L54+O54+R54+U54 -> 3
B56: Faturamento | D56: Emissão e/ou lançamento de NF de troca em garantia | F56: Diario | H56: 1 | I56: 1 | K56: 1 | L56: 1 | N56: 1 | O56: 1 | W56: =H56+K56+N56+Q56+T56 -> 3 | X56: =I56+L56+O56+R56+U56 -> 3
H57: 1 | I57: 1 | K57: 1 | L57: 1 | N57: 1 | O57: 1 | W57: =H57+K57+N57+Q57+T57 -> 3 | X57: =I57+L57+O57+R57+U57 -> 3
B59: Faturamento | D59: Análise e/ou criação de cadastros de clientes e fornecedores no sistema SAP | F59: Diario | H59: 1 | I59: 1 | K59: 1 | L59: 1 | N59: 1 | O59: 1 | W59: =H59+K59+N59+Q59+T59 -> 3 | X59: =I59+L59+O59+R59+U59 -> 3
H60: 1 | I60: 1 | K60: 1 | L60: 1 | N60: 1 | O60: 1 | W60: =H60+K60+N60+Q60+T60 -> 3 | X60: =I60+L60+O60+R60+U60 -> 3
B62: Faturamento | D62: Análise de possível emissão de guia DIFAL (diferencial de alíquotas) | F62: Diario | H62: 1 | I62: 1 | K62: 1 | L62: 1 | N62: 1 | O62: 1 | W62: =H62+K62+N62+Q62+T62 -> 3 | X62: =I62+L62+O62+R62+U62 -> 3
H63: 1 | I63: 1 | K63: 1 | L63: 1 | N63: 1 | O63: 1 | W63: =H63+K63+N63+Q63+T63 -> 3 | X63: =I63+L63+O63+R63+U63 -> 3
B65: Faturamento | D65: Confirmação de pagamento dos pedidos de venda com acesso ao banco Itaú | F65: Diario | H65: 1 | I65: 1 | N65: 1 | O65: 1 | W65: =H65+K65+N65+Q65+T65 -> 2 | X65: =I65+L65+O65+R65+U65 -> 2
H66: 1 | I66: 1 | N66: 1 | O66: 1 | W66: =H66+K66+N66+Q66+T66 -> 2 | X66: =I66+L66+O66+R66+U66 -> 2
B68: Faturamento | D68: Emissão de fatura de adiantamento no pedido de venda | F68: Diario | H68: 1 | I68: 1 | N68: 1 | O68: 1 | W68: =H68+K68+N68+Q68+T68 -> 2 | X68: =I68+L68+O68+R68+U68 -> 2
H69: 1 | I69: 1 | N69: 1 | O69: 1 | W69: =H69+K69+N69+Q69+T69 -> 2 | X69: =I69+L69+O69+R69+U69 -> 2
B71: Faturamento | D71: Controle das mensalidades de locação na planilha Excel junto com o sistema SAP | F71: Diario | H71: 1 | I71: 1 | K71: 1 | L71: 1 | N71: 1 | O71: 1 | W71: =H71+K71+N71+Q71+T71 -> 3 | X71: =I71+L71+O71+R71+U71 -> 3
H72: 1 | I72: 1 | K72: 1 | L72: 1 | N72: 1 | O72: 1 | W72: =H72+K72+N72+Q72+T72 -> 3 | X72: =I72+L72+O72+R72+U72 -> 3
B74: Faturamento | D74: Envio manual via e-mail das notas de débito e boletos para o respectivos clientes | F74: Diario | H74: 1 | I74: 1 | K74: 1 | L74: 1 | N74: 1 | O74: 1 | W74: =H74+K74+N74+Q74+T74 -> 3 | X74: =I74+L74+O74+R74+U74 -> 3
H75: 1 | I75: 1 | K75: 1 | L75: 1 | N75: 1 | O75: 1 | W75: =H75+K75+N75+Q75+T75 -> 3 | X75: =I75+L75+O75+R75+U75 -> 3
B77: Faturamento | D77: Análise e controle das mensalidades de manuntenção de equipamentos, para a posterior emissão de NFS-e | F77: Diario | H77: 1 | I77: 1 | N77: 1 | O77: 1 | W77: =H77+K77+N77+Q77+T77 -> 2 | X77: =I77+L77+O77+R77+U77 -> 2
H78: 1 | I78: 1 | N78: 1 | O78: 1 | W78: =H78+K78+N78+Q78+T78 -> 2 | X78: =I78+L78+O78+R78+U78 -> 2
B80: Faturamento | D80: Análise de novos contratos de locação novos / Planilhamento / cadastro no SAP, emissão das notas de débito (ND) | F80: Diario | H80: 1 | I80: 1 | K80: 1 | L80: 1 | N80: 1 | O80: 1 | W80: =H80+K80+N80+Q80+T80 -> 3 | X80: =I80+L80+O80+R80+U80 -> 3
H81: 1 | I81: 1 | N81: 1 | O81: 1 | W81: =H81+K81+N81+Q81+T81 -> 2 | X81: =I81+L81+O81+R81+U81 -> 2
B83: Faturamento | D83: Análise de contratos de locação em andamento | F83: Diario | H83: 1 | I83: 1 | K83: 1 | L83: 1 | N83: 1 | O83: 1 | W83: =H83+K83+N83+Q83+T83 -> 3 | X83: =I83+L83+O83+R83+U83 -> 3
H84: 1 | I84: 1 | N84: 1 | O84: 1 | W84: =H84+K84+N84+Q84+T84 -> 2 | X84: =I84+L84+O84+R84+U84 -> 2
B86: Faturamento | D86: Análise de possíveis reajuste contratuais nas parcelas dos contratos de locação/manuntenção | F86: Diario | H86: 1 | I86: 1 | N86: 1 | O86: 1 | W86: =H86+K86+N86+Q86+T86 -> 2 | X86: =I86+L86+O86+R86+U86 -> 2
H87: 1 | I87: 1 | N87: 1 | O87: 1 | W87: =H87+K87+N87+Q87+T87 -> 2 | X87: =I87+L87+O87+R87+U87 -> 2
B89: Faturamento | D89: Controle de retorno de comodato da Geneslab / emissão NF de venda | F89: Diario | H89: 1 | I89: 1 | N89: 1 | O89: 1 | W89: =H89+K89+N89+Q89+T89 -> 2 | X89: =I89+L89+O89+R89+U89 -> 2
H90: 1 | I90: 1 | N90: 1 | O90: 1 | W90: =H90+K90+N90+Q90+T90 -> 2 | X90: =I90+L90+O90+R90+U90 -> 2
B92: Faturamento | D92: Suporte e Orientações aos setores (help desk, comercial, adequação, almoxarifado) | F92: Diario | H92: 1 | I92: 1 | K92: 1 | L92: 1 | N92: 1 | O92: 1 | W92: =H92+K92+N92+Q92+T92 -> 3 | X92: =I92+L92+O92+R92+U92 -> 3
H93: 1 | I93: 1 | K93: 1 | L93: 1 | N93: 1 | O93: 1 | W93: =H93+K93+N93+Q93+T93 -> 3 | X93: =I93+L93+O93+R93+U93 -> 3
B95: Faturamento | D95: Resolução de problemas e/ou dúvidas de clientes, via e-mail, telefone, whatsapp | F95: Diario | H95: 1 | I95: 1 | K95: 1 | L95: 1 | N95: 1 | O95: 1 | W95: =H95+K95+N95+Q95+T95 -> 3 | X95: =I95+L95+O95+R95+U95 -> 3
H96: 1 | I96: 1 | K96: 1 | L96: 1 | N96: 1 | O96: 1 | W96: =H96+K96+N96+Q96+T96 -> 3 | X96: =I96+L96+O96+R96+U96 -> 3
B98: Faturamento | D98: Análise de impostos e tributações das operações em geral | F98: Diario | H98: 1 | I98: 1 | K98: 1 | L98: 1 | N98: 1 | O98: 1 | W98: =H98+K98+N98+Q98+T98 -> 3 | X98: =I98+L98+O98+R98+U98 -> 3
H99: 1 | I99: 1 | K99: 1 | L99: 1 | N99: 1 | O99: 1 | W99: =H99+K99+N99+Q99+T99 -> 3 | X99: =I99+L99+O99+R99+U99 -> 3
B101: Recebimento | D101: Lançamento de notas com pedido de compra | F101: Diario | K101: 1 | L101: 1 | N101: 1 | O101: 1 | Q101: 1 | R101: 1 | W101: =H101+K101+N101+Q101+T101 -> 3 | X101: =I101+L101+O101+R101+U101 -> 3
K102: 1 | L102: 1 | N102: 1 | O102: 1 | Q102: 1 | R102: 1 | W102: =H102+K102+N102+Q102+T102 -> 3 | X102: =I102+L102+O102+R102+U102 -> 3
B104: Recebimento | D104: Lançamento de notas recorrentes | F104: Diario | K104: 1 | L104: 1 | N104: 1 | O104: 1 | Q104: 1 | R104: 1 | W104: =H104+K104+N104+Q104+T104 -> 3 | X104: =I104+L104+O104+R104+U104 -> 3
K105: 1 | L105: 1 | N105: 1 | O105: 1 | Q105: 1 | R105: 1 | W105: =H105+K105+N105+Q105+T105 -> 3 | X105: =I105+L105+O105+R105+U105 -> 3
B107: Recebimento | D107: Lançamentos de guias e impostos (LCM) | F107: Diario | K107: 1 | L107: 1 | N107: 1 | O107: 1 | Q107: 1 | R107: 1 | W107: =H107+K107+N107+Q107+T107 -> 3 | X107: =I107+L107+O107+R107+U107 -> 3
K108: 1 | L108: 1 | Q108: 1 | R108: 1 | W108: =H108+K108+N108+Q108+T108 -> 2 | X108: =I108+L108+O108+R108+U108 -> 2
B110: Recebimento | D110: Lançamento da folha de pagamento | F110: Mensal | K110: 1 | L110: 1 | N110: 1 | Q110: 1 | R110: 1 | W110: =H110+K110+N110+Q110+T110 -> 3 | X110: =I110+L110+O110+R110+U110 -> 2
K111: 1 | L111: 1 | Q111: 1 | R111: 1 | W111: =H111+K111+N111+Q111+T111 -> 2 | X111: =I111+L111+O111+R111+U111 -> 2
B113: Recebimento | D113: Controle de notas de entrada | F113: Diario | K113: 1 | L113: 1 | N113: 1 | O113: 1 | Q113: 1 | R113: 1 | W113: =H113+K113+N113+Q113+T113 -> 3 | X113: =I113+L113+O113+R113+U113 -> 3
K114: 1 | L114: 1 | N114: 1 | O114: 1 | Q114: 1 | R114: 1 | W114: =H114+K114+N114+Q114+T114 -> 3 | X114: =I114+L114+O114+R114+U114 -> 3
B116: Recebimento | D116: Lançamento de fatura de cartão de crédito | F116: Mensal | K116: 1 | L116: 1 | N116: 1 | Q116: 1 | R116: 1 | W116: =H116+K116+N116+Q116+T116 -> 3 | X116: =I116+L116+O116+R116+U116 -> 2
K117: 1 | L117: 1 | Q117: 1 | R117: 1 | W117: =H117+K117+N117+Q117+T117 -> 2 | X117: =I117+L117+O117+R117+U117 -> 2
B119: Recebimento | D119: Abertura de pedidos recorrentes | F119: Diario | K119: 1 | L119: 1 | N119: 1 | O119: 1 | Q119: 1 | R119: 1 | W119: =H119+K119+N119+Q119+T119 -> 3 | X119: =I119+L119+O119+R119+U119 -> 3
K120: 1 | L120: 1 | N120: 1 | O120: 1 | Q120: 1 | R120: 1 | W120: =H120+K120+N120+Q120+T120 -> 3 | X120: =I120+L120+O120+R120+U120 -> 3
B122: Recebimento | D122: Fatura de adiantamento para fornecedor | F122: Diario | K122: 1 | L122: 1 | N122: 1 | O122: 1 | Q122: 1 | R122: 1 | W122: =H122+K122+N122+Q122+T122 -> 3 | X122: =I122+L122+O122+R122+U122 -> 3
K123: 1 | L123: 1 | N123: 1 | O123: 1 | Q123: 1 | R123: 1 | W123: =H123+K123+N123+Q123+T123 -> 3 | X123: =I123+L123+O123+R123+U123 -> 3
B125: Recebimento | D125: Importar arquivos XML de saídas para o Arquivei | F125: Diario | N125: 1 | O125: 1 | Q125: 1 | R125: 1 | W125: =H125+K125+N125+Q125+T125 -> 2 | X125: =I125+L125+O125+R125+U125 -> 2
N126: 1 | O126: 1 | Q126: 1 | R126: 1 | W126: =H126+K126+N126+Q126+T126 -> 2 | X126: =I126+L126+O126+R126+U126 -> 2
B128: Recebimento | D128: Envio de documentos à contabilidade externa | F128: Mensal | K128: 1 | L128: 1 | N128: 1 | Q128: 1 | R128: 1 | W128: =H128+K128+N128+Q128+T128 -> 3 | X128: =I128+L128+O128+R128+U128 -> 2
Q129: 1 | R129: 1 | W129: =H129+K129+N129+Q129+T129 -> 1 | X129: =I129+L129+O129+R129+U129 -> 1
B131: Recebimento | D131: Efetivar lançamentos de impostos em débito automático | F131: Mensal | N131: 1 | Q131: 1 | R131: 1 | W131: =H131+K131+N131+Q131+T131 -> 2 | X131: =I131+L131+O131+R131+U131 -> 1
Q132: 1 | R132: 1 | W132: =H132+K132+N132+Q132+T132 -> 1 | X132: =I132+L132+O132+R132+U132 -> 1
B134: Recebimento | D134: Lançamento de Cte | F134: Diario | N134: 1 | O134: 1 | Q134: 1 | R134: 1 | W134: =H134+K134+N134+Q134+T134 -> 2 | X134: =I134+L134+O134+R134+U134 -> 2
N135: 1 | O135: 1 | Q135: 1 | R135: 1 | W135: =H135+K135+N135+Q135+T135 -> 2 | X135: =I135+L135+O135+R135+U135 -> 2
B137: Recebimento | D137: Lançamento de multas de trânsito | F137: Diario | N137: 1 | O137: 1 | Q137: 1 | R137: 1 | W137: =H137+K137+N137+Q137+T137 -> 2 | X137: =I137+L137+O137+R137+U137 -> 2
Q138: 1 | R138: 1 | W138: =H138+K138+N138+Q138+T138 -> 1 | X138: =I138+L138+O138+R138+U138 -> 1
B140: Recebimento | D140: Lançamentos de Importação Simpificada (Courrier) | F140: Diario | N140: 1 | O140: 1 | W140: =H140+K140+N140+Q140+T140 -> 1 | X140: =I140+L140+O140+R140+U140 -> 1
W141: =H141+K141+N141+Q141+T141 -> 0 | X141: =I141+L141+O141+R141+U141 -> 0
B143: Recebimento | D143: Emissão de nota fiscal de Importação Simpificada (Courrier) | F143: Diario | K143: 1 | L143: 1 | N143: 1 | O143: 1 | Q143: 1 | R143: 1 | W143: =H143+K143+N143+Q143+T143 -> 3 | X143: =I143+L143+O143+R143+U143 -> 3
K144: 1 | N144: 1 | W144: =H144+K144+N144+Q144+T144 -> 2 | X144: =I144+L144+O144+R144+U144 -> 0
D146: ______________________________________________________________________________________________ | F146: ________ | W146: =H146+K146+N146+Q146+T146 -> 0 | X146: =I146+L146+O146+R146+U146 -> 0
W147: =H147+K147+N147+Q147+T147 -> 0 | X147: =I147+L147+O147+R147+U147 -> 0
D149: ______________________________________________________________________________________________ | F149: ________ | W149: =H149+K149+N149+Q149+T149 -> 0 | X149: =I149+L149+O149+R149+U149 -> 0
W150: =H150+K150+N150+Q150+T150 -> 0 | X150: =I150+L150+O150+R150+U150 -> 0
...

Sheet Dezembro 2025
B2: Setorização | D2: Tarefas | F2: Periodicidade | H2: Luis | K2: Alexandre | N2: Pamella | Q2: Loraine | T2: Maykon
H3: Gerente | K3: Supervisor
D5: Classificação do Colaborador | H5: =H11+H83+H86+H89+H92+H95+H98+H200+H203+H206+H14+H17+H20+H23+H26+H29+H32+H35+H41+H38+H44+H47+H50+H53+H56+H59+H62+H65+H68+H71+H74+H77+H80+H101+H104+H107+H110+H113+H116+H119+H122+H125+H128+H131+H134+H137+H140+H143+H146+H149+H152+H155+H158+H161+H164+H167+H170+H173+H176+H179+H182+H185+H188+H191+H194+H197+H209+H212+H215+H218+H221+H224+H227+H230+H233+H236+H239+H242+H245+H248+H251+H254+H257+H260+H263+H266+H269+H272 -> 36 | I5: =I11+I83+I86+I89+I92+I95+I98+I200+I203+I206+I14+I17+I20+I23+I26+I29+I32+I35+I41+I38+I44+I47+I50+I53+I56+I59+I62+I65+I68+I71+I74+I77+I80+I101+I104+I107+I110+I113+I116+I119+I122+I125+I128+I131+I134+I137+I140+I143+I146+I149+I152+I155+I158+I161+I164+I167+I170+I173+I176+I179+I182+I185+I188+I191+I194+I197+I209+I212+I215+I218+I221+I224+I227+I230+I233+I236+I239+I242+I245+I248+I251+I254+I257+I260+I263+I266+I269+I272 -> 36 | K5: =K11+K83+K86+K89+K92+K95+K98+K200+K203+K206+K14+K17+K20+K23+K26+K29+K32+K35+K41+K38+K44+K47+K50+K53+K56+K59+K62+K65+K68+K71+K74+K77+K80+K101+K104+K107+K110+K113+K116+K119+K122+K125+K128+K131+K134+K137+K140+K143+K146+K149+K152+K155+K158+K161+K164+K167+K170+K173+K176+K179+K182+K185+K188+K191+K194+K197+K209+K212+K215+K218+K221+K224+K227+K230+K233+K236+K239+K242+K245+K248+K251+K254+K257+K260+K263+K266+K269+K272 -> 46 | L5: =L11+L83+L86+L89+L92+L95+L98+L200+L203+L206+L14+L17+L20+L23+L26+L29+L32+L35+L41+L38+L44+L47+L50+L53+L56+L59+L62+L65+L68+L71+L74+L77+L80+L101+L104+L107+L110+L113+L116+L119+L122+L125+L128+L131+L134+L137+L140+L143+L146+L149+L152+L155+L158+L161+L164+L167+L170+L173+L176+L179+L182+L185+L188+L191+L194+L197+L209+L212+L215+L218+L221+L224+L227+L230+L233+L236+L239+L242+L245+L248+L251+L254+L257+L260+L263+L266+L269+L272 -> 46 | N5: =N11+N83+N86+N89+N92+N95+N98+N200+N203+N206+N14+N17+N20+N23+N26+N29+N32+N35+N41+N38+N44+N47+N50+N53+N56+N59+N62+N65+N68+N71+N74+N77+N80+N101+N104+N107+N110+N113+N116+N119+N122+N125+N128+N131+N134+N137+N140+N143+N146+N149+N152+N155+N158+N161+N164+N167+N170+N173+N176+N179+N182+N185+N188+N191+N194+N197+N209+N212+N215+N218+N221+N224+N227+N230+N233+N236+N239+N242+N245+N248+N251+N254+N257+N260+N263+N266+N269+N272 -> 14 | O5: =O11+O83+O86+O89+O92+O95+O98+O200+O203+O206+O14+O17+O20+O23+O26+O29+O32+O35+O41+O38+O44+O47+O50+O53+O56+O59+O62+O65+O68+O71+O74+O77+O80+O101+O104+O107+O110+O113+O116+O119+O122+O125+O128+O131+O134+O137+O140+O143+O146+O149+O152+O155+O158+O161+O164+O167+O170+O173+O176+O179+O182+O185+O188+O191+O194+O197+O209+O212+O215+O218+O221+O224+O227+O230+O233+O236+O239+O242+O245+O248+O251+O254+O257+O260+O263+O266+O269+O272 -> 14 | Q5: =Q11+Q83+Q86+Q89+Q92+Q95+Q98+Q200+Q203+Q206+Q14+Q17+Q20+Q23+Q26+Q29+Q32+Q35+Q41+Q38+Q44+Q47+Q50+Q53+Q56+Q59+Q62+Q65+Q68+Q71+Q74+Q77+Q80+Q101+Q104+Q107+Q110+Q113+Q116+Q119+Q122+Q125+Q128+Q131+Q134+Q137+Q140+Q143+Q146+Q149+Q152+Q155+Q158+Q161+Q164+Q167+Q170+Q173+Q176+Q179+Q182+Q185+Q188+Q191+Q194+Q197+Q209+Q212+Q215+Q218+Q221+Q224+Q227+Q230+Q233+Q236+Q239+Q242+Q245+Q248+Q251+Q254+Q257+Q260+Q263+Q266+Q269+Q272 -> 0 | R5: =R11+R83+R86+R89+R92+R95+R98+R200+R203+R206+R14+R17+R20+R23+R26+R29+R32+R35+R41+R38+R44+R47+R50+R53+R56+R59+R62+R65+R68+R71+R74+R77+R80+R101+R104+R107+R110+R113+R116+R119+R122+R125+R128+R131+R134+R137+R140+R143+R146+R149+R152+R155+R158+R161+R164+R167+R170+R173+R176+R179+R182+R185+R188+R191+R194+R197+R209+R212+R215+R218+R221+R224+R227+R230+R233+R236+R239+R242+R245+R248+R251+R254+R257+R260+R263+R266+R269+R272 -> 0 | T5: =T11+T83+T86+T89+T92+T95+T98+T200+T203+T206+T14+T17+T20+T23+T26+T29+T32+T35+T41+T38+T44+T47+T50+T53+T56+T59+T62+T65+T68+T71+T74+T77+T80+T101+T104+T107+T110+T113+T116+T119+T122+T125+T128+T131+T134+T137+T140+T143+T146+T149+T152+T155+T158+T161+T164+T167+T170+T173+T176+T179+T182+T185+T188+T191+T194+T197+T209+T212+T215+T218+T221+T224+T227+T230+T233+T236+T239+T242+T245+T248+T251+T254+T257+T260+T263+T266+T269+T272 -> 0 | U5: =U11+U83+U86+U89+U92+U95+U98+U200+U203+U206+U14+U17+U20+U23+U26+U29+U32+U35+U41+U38+U44+U47+U50+U53+U56+U59+U62+U65+U68+U71+U74+U77+U80+U101+U104+U107+U110+U113+U116+U119+U122+U125+U128+U131+U134+U137+U140+U143+U146+U149+U152+U155+U158+U161+U164+U167+U170+U173+U176+U179+U182+U185+U188+U191+U194+U197+U209+U212+U215+U218+U221+U224+U227+U230+U233+U236+U239+U242+U245+U248+U251+U254+U257+U260+U263+U266+U269+U272 -> 0 | W5: =W11+W83+W86+W89+W92+W95+W98+W200+W203+W206+W14+W17+W20+W23+W26+W29+W32+W35+W41+W38+W44+W47+W50+W53+W56+W59+W62+W65+W68+W71+W74+W77+W80+W101+W104+W107+W110+W113+W116+W119+W122+W125+W128+W131+W134+W137+W140+W143+W146+W149+W152+W155+W158+W161+W164+W167+W170+W173+W176+W179+W182+W185+W188+W191+W194+W197+W209+W212+W215+W218+W221+W224+W227+W230+W233+W236+W239+W242+W245+W248+W251+W254+W257+W260+W263+W266+W269+W272 -> 0 | X5: =X11+X83+X86+X89+X92+X95+X98+X200+X203+X206+X14+X17+X20+X23+X26+X29+X32+X35+X41+X38+X44+X47+X50+X53+X56+X59+X62+X65+X68+X71+X74+X77+X80+X101+X104+X107+X110+X113+X116+X119+X122+X125+X128+X131+X134+X137+X140+X143+X146+X149+X152+X155+X158+X161+X164+X167+X170+X173+X176+X179+X182+X185+X188+X191+X194+X197+X209+X212+X215+X218+X221+X224+X227+X230+X233+X236+X239+X242+X245+X248+X251+X254+X257+X260+X263+X266+X269+X272 -> 0
H6: =H12+H84+H87+H90+H93+H96+H99+H201+H204+H207+H15+H18+H21+H24+H27+H30+H33+H36+H42+H39+H45+H48+H51+H54+H57+H60+H63+H66+H69+H72+H75+H78+H81+H102+H105+H108+H111+H114+H117+H120+H123+H126+H129+H132+H135+H138+H141+H144+H147+H150+H153+H156+H159+H162+H165+H168+H171+H174+H177+H180+H183+H186+H189+H192+H195+H198+H210+H213+H216+H219+H222+H225+H228+H231+H234+H237+H240+H243+H246+H249+H252+H255+H258+H261+H264+H267+H270+H273 -> 36 | I6: =I12+I84+I87+I90+I93+I96+I99+I201+I204+I207+I15+I18+I21+I24+I27+I30+I33+I36+I42+I39+I45+I48+I51+I54+I57+I60+I63+I66+I69+I72+I75+I78+I81+I102+I105+I108+I111+I114+I117+I120+I123+I126+I129+I132+I135+I138+I141+I144+I147+I150+I153+I156+I159+I162+I165+I168+I171+I174+I177+I180+I183+I186+I189+I192+I195+I198+I210+I213+I216+I219+I222+I225+I228+I231+I234+I237+I240+I243+I246+I249+I252+I255+I258+I261+I264+I267+I270+I273 -> 36 | K6: =K12+K84+K87+K90+K93+K96+K99+K201+K204+K207+K15+K18+K21+K24+K27+K30+K33+K36+K42+K39+K45+K48+K51+K54+K57+K60+K63+K66+K69+K72+K75+K78+K81+K102+K105+K108+K111+K114+K117+K120+K123+K126+K129+K132+K135+K138+K141+K144+K147+K150+K153+K156+K159+K162+K165+K168+K171+K174+K177+K180+K183+K186+K189+K192+K195+K198+K210+K213+K216+K219+K222+K225+K228+K231+K234+K237+K240+K243+K246+K249+K252+K255+K258+K261+K264+K267+K270+K273 -> 43 | L6: =L12+L84+L87+L90+L93+L96+L99+L201+L204+L207+L15+L18+L21+L24+L27+L30+L33+L36+L42+L39+L45+L48+L51+L54+L57+L60+L63+L66+L69+L72+L75+L78+L81+L102+L105+L108+L111+L114+L117+L120+L123+L126+L129+L132+L135+L138+L141+L144+L147+L150+L153+L156+L159+L162+L165+L168+L171+L174+L177+L180+L183+L186+L189+L192+L195+L198+L210+L213+L216+L219+L222+L225+L228+L231+L234+L237+L240+L243+L246+L249+L252+L255+L258+L261+L264+L267+L270+L273 -> 40 | N6: =N12+N84+N87+N90+N93+N96+N99+N201+N204+N207+N15+N18+N21+N24+N27+N30+N33+N36+N42+N39+N45+N48+N51+N54+N57+N60+N63+N66+N69+N72+N75+N78+N81+N102+N105+N108+N111+N114+N117+N120+N123+N126+N129+N132+N135+N138+N141+N144+N147+N150+N153+N156+N159+N162+N165+N168+N171+N174+N177+N180+N183+N186+N189+N192+N195+N198+N210+N213+N216+N219+N222+N225+N228+N231+N234+N237+N240+N243+N246+N249+N252+N255+N258+N261+N264+N267+N270+N273 -> 13 | O6: =O12+O84+O87+O90+O93+O96+O99+O201+O204+O207+O15+O18+O21+O24+O27+O30+O33+O36+O42+O39+O45+O48+O51+O54+O57+O60+O63+O66+O69+O72+O75+O78+O81+O102+O105+O108+O111+O114+O117+O120+O123+O126+O129+O132+O135+O138+O141+O144+O147+O150+O153+O156+O159+O162+O165+O168+O171+O174+O177+O180+O183+O186+O189+O192+O195+O198+O210+O213+O216+O219+O222+O225+O228+O231+O234+O237+O240+O243+O246+O249+O252+O255+O258+O261+O264+O267+O270+O273 -> 13 | Q6: =Q12+Q84+Q87+Q90+Q93+Q96+Q99+Q201+Q204+Q207+Q15+Q18+Q21+Q24+Q27+Q30+Q33+Q36+Q42+Q39+Q45+Q48+Q51+Q54+Q57+Q60+Q63+Q66+Q69+Q72+Q75+Q78+Q81+Q102+Q105+Q108+Q111+Q114+Q117+Q120+Q123+Q126+Q129+Q132+Q135+Q138+Q141+Q144+Q147+Q150+Q153+Q156+Q159+Q162+Q165+Q168+Q171+Q174+Q177+Q180+Q183+Q186+Q189+Q192+Q195+Q198+Q210+Q213+Q216+Q219+Q222+Q225+Q228+Q231+Q234+Q237+Q240+Q243+Q246+Q249+Q252+Q255+Q258+Q261+Q264+Q267+Q270+Q273 -> 0 | R6: =R12+R84+R87+R90+R93+R96+R99+R201+R204+R207+R15+R18+R21+R24+R27+R30+R33+R36+R42+R39+R45+R48+R51+R54+R57+R60+R63+R66+R69+R72+R75+R78+R81+R102+R105+R108+R111+R114+R117+R120+R123+R126+R129+R132+R135+R138+R141+R144+R147+R150+R153+R156+R159+R162+R165+R168+R171+R174+R177+R180+R183+R186+R189+R192+R195+R198+R210+R213+R216+R219+R222+R225+R228+R231+R234+R237+R240+R243+R246+R249+R252+R255+R258+R261+R264+R267+R270+R273 -> 0 | T6: =T12+T84+T87+T90+T93+T96+T99+T201+T204+T207+T15+T18+T21+T24+T27+T30+T33+T36+T42+T39+T45+T48+T51+T54+T57+T60+T63+T66+T69+T72+T75+T78+T81+T102+T105+T108+T111+T114+T117+T120+T123+T126+T129+T132+T135+T138+T141+T144+T147+T150+T153+T156+T159+T162+T165+T168+T171+T174+T177+T180+T183+T186+T189+T192+T195+T198+T210+T213+T216+T219+T222+T225+T228+T231+T234+T237+T240+T243+T246+T249+T252+T255+T258+T261+T264+T267+T270+T273 -> 0 | U6: =U12+U84+U87+U90+U93+U96+U99+U201+U204+U207+U15+U18+U21+U24+U27+U30+U33+U36+U42+U39+U45+U48+U51+U54+U57+U60+U63+U66+U69+U72+U75+U78+U81+U102+U105+U108+U111+U114+U117+U120+U123+U126+U129+U132+U135+U138+U141+U144+U147+U150+U153+U156+U159+U162+U165+U168+U171+U174+U177+U180+U183+U186+U189+U192+U195+U198+U210+U213+U216+U219+U222+U225+U228+U231+U234+U237+U240+U243+U246+U249+U252+U255+U258+U261+U264+U267+U270+U273 -> 0 | W6: =W12+W84+W87+W90+W93+W96+W99+W201+W204+W207+W15+W18+W21+W24+W27+W30+W33+W36+W42+W39+W45+W48+W51+W54+W57+W60+W63+W66+W69+W72+W75+W78+W81+W102+W105+W108+W111+W114+W117+W120+W123+W126+W129+W132+W135+W138+W141+W144+W147+W150+W153+W156+W159+W162+W165+W168+W171+W174+W177+W180+W183+W186+W189+W192+W195+W198+W210+W213+W216+W219+W222+W225+W228+W231+W234+W237+W240+W243+W246+W249+W252+W255+W258+W261+W264+W267+W270+W273 -> 0 | X6: =X12+X84+X87+X90+X93+X96+X99+X201+X204+X207+X15+X18+X21+X24+X27+X30+X33+X36+X42+X39+X45+X48+X51+X54+X57+X60+X63+X66+X69+X72+X75+X78+X81+X102+X105+X108+X111+X114+X117+X120+X123+X126+X129+X132+X135+X138+X141+X144+X147+X150+X153+X156+X159+X162+X165+X168+X171+X174+X177+X180+X183+X186+X189+X192+X195+X198+X210+X213+X216+X219+X222+X225+X228+X231+X234+X237+X240+X243+X246+X249+X252+X255+X258+X261+X264+X267+X270+X273 -> 0
D8: ----------------------------------------------------------------------------------------------------------------------------------------------------------------------> | H8: =H5+I5+H6+I6 -> 144 | I8: Pontos | K8: =K5+L5+K6+L6 -> 175 | L8: Pontos | N8: =N5+O5+N6+O6 -> 54 | O8: Pontos | Q8: =Q5+R5+Q6+R6 -> 0 | R8: Pontos | T8: =T5+U5+T6+U6 -> 0 | U8: Pontos | W8: =W5+X5+W6+X6 -> 0 | X8: Pontos
Z9: Semáforo | AC9: Legenda:
B11: Faturamento | D11: Emissão de NF de venda (NF-e) | F11: Diario | H11: 1 | I11: 1 | K11: 1 | L11: 1 | Z11: =H11+K11+N11+Q11+T11+W11 -> 2 | AA11: =I11+L11+O11+R11+U11+X11 -> 2 | AD11: Aprendendo | AE11: 1
H12: 1 | I12: 1 | K12: 1 | L12: 1 | Z12: =H12+K12+N12+Q12+T12+W12 -> 2 | AA12: =I12+L12+O12+R12+U12+X12 -> 2
B14: Faturamento | D14: Emissão de NF de exportação (NF-e) | F14: Diario | H14: 1 | I14: 1 | K14: 1 | L14: 1 | Z14: =H14+K14+N14+Q14+T14+W14 -> 2 | AA14: =I14+L14+O14+R14+U14+X14 -> 2 | AC14: Consegue fazer | AD14: com ajuda | AE14: 1
H15: 1 | I15: 1 | K15: 1 | L15: 1 | Z15: =H15+K15+N15+Q15+T15+W15 -> 2 | AA15: =I15+L15+O15+R15+U15+X15 -> 2 | AE15: 1
B17: Faturamento | D17: Emissão de NF de importação (NF-e) | F17: Diario | H17: 1 | I17: 1 | K17: 1 | L17: 1 | Z17: =H17+K17+N17+Q17+T17+W17 -> 2 | AA17: =I17+L17+O17+R17+U17+X17 -> 2 | AC17: Consegue fazer | AD17: sem ajuda | AE17: 1 | AF17: 1
H18: 1 | I18: 1 | K18: 1 | L18: 1 | Z18: =H18+K18+N18+Q18+T18+W18 -> 2 | AA18: =I18+L18+O18+R18+U18+X18 -> 2 | AC18: (Sei fazer, mas não sei porque faço) | AE18: 1
B20: Faturamento | D20: Emissão de NF de comodato (NF-e) | F20: Diario | H20: 1 | I20: 1 | K20: 1 | L20: 1 | Z20: =H20+K20+N20+Q20+T20+W20 -> 2 | AA20: =I20+L20+O20+R20+U20+X20 -> 2 | AC20: Consegue fazer | AD20: e ensinar | AE20: 1 | AF20: 1
H21: 1 | I21: 1 | K21: 1 | L21: 1 | Z21: =H21+K21+N21+Q21+T21+W21 -> 2 | AA21: =I21+L21+O21+R21+U21+X21 -> 2 | AC21: (Sei fazer, e sei porque faço) | AE21: 1 | AF21: 1
B23: Faturamento | D23: Emissão de NF de bonificação ou brinde (NF-e) | F23: Diario | H23: 1 | I23: 1 | K23: 1 | L23: 1 | Z23: =H23+K23+N23+Q23+T23+W23 -> 2 | AA23: =I23+L23+O23+R23+U23+X23 -> 2
H24: 1 | I24: 1 | K24: 1 | L24: 1 | Z24: =H24+K24+N24+Q24+T24+W24 -> 2 | AA24: =I24+L24+O24+R24+U24+X24 -> 2
B26: Faturamento | D26: Emissão de NF de demonstração (NF-e) | F26: Diario | H26: 1 | I26: 1 | K26: 1 | L26: 1 | Z26: =H26+K26+N26+Q26+T26+W26 -> 2 | AA26: =I26+L26+O26+R26+U26+X26 -> 2
H27: 1 | I27: 1 | K27: 1 | L27: 1 | Z27: =H27+K27+N27+Q27+T27+W27 -> 2 | AA27: =I27+L27+O27+R27+U27+X27 -> 2
B29: Faturamento | D29: Emissão de NF de troca em garantia (NF-e) | F29: Diario | H29: 1 | I29: 1 | K29: 1 | L29: 1 | Z29: =H29+K29+N29+Q29+T29+W29 -> 2 | AA29: =I29+L29+O29+R29+U29+X29 -> 2
H30: 1 | I30: 1 | K30: 1 | L30: 1 | Z30: =H30+K30+N30+Q30+T30+W30 -> 2 | AA30: =I30+L30+O30+R30+U30+X30 -> 2
B32: Faturamento | D32: Emissão de NF de industrialização (NF-e) | F32: Diario | H32: 1 | I32: 1 | K32: 1 | L32: 1 | Z32: =H32+K32+N32+Q32+T32+W32 -> 2 | AA32: =I32+L32+O32+R32+U32+X32 -> 2
H33: 1 | I33: 1 | K33: 1 | L33: 1 | Z33: =H33+K33+N33+Q33+T33+W33 -> 2 | AA33: =I33+L33+O33+R33+U33+X33 -> 2
B35: Faturamento | D35: Emissão de NF de serviço (NFS-e) | F35: Diario | H35: 1 | I35: 1 | K35: 1 | L35: 1 | Z35: =H35+K35+N35+Q35+T35+W35 -> 2 | AA35: =I35+L35+O35+R35+U35+X35 -> 2
H36: 1 | I36: 1 | K36: 1 | Z36: =H36+K36+N36+Q36+T36+W36 -> 2 | AA36: =I36+L36+O36+R36+U36+X36 -> 1
B38: Faturamento | D38: Emissão de NF de débito (ND) | F38: Diario | H38: 1 | I38: 1 | K38: 1 | L38: 1 | Z38: =H38+K38+N38+Q38+T38+W38 -> 2 | AA38: =I38+L38+O38+R38+U38+X38 -> 2
H39: 1 | I39: 1 | K39: 1 | Z39: =H39+K39+N39+Q39+T39+W39 -> 2 | AA39: =I39+L39+O39+R39+U39+X39 -> 1
B41: Faturamento | D41: Emissão de NF complementar de ICMS (NF-e) | F41: Diario | H41: 1 | I41: 1 | K41: 1 | L41: 1 | Z41: =H41+K41+N41+Q41+T41+W41 -> 2 | AA41: =I41+L41+O41+R41+U41+X41 -> 2
H42: 1 | I42: 1 | K42: 1 | L42: 1 | Z42: =H42+K42+N42+Q42+T42+W42 -> 2 | AA42: =I42+L42+O42+R42+U42+X42 -> 2
B44: Faturamento | D44: Emissão e/ou lançamento de NF de devolução de venda | F44: Diario | H44: 1 | I44: 1 | K44: 1 | L44: 1 | Z44: =H44+K44+N44+Q44+T44+W44 -> 2 | AA44: =I44+L44+O44+R44+U44+X44 -> 2
H45: 1 | I45: 1 | K45: 1 | L45: 1 | Z45: =H45+K45+N45+Q45+T45+W45 -> 2 | AA45: =I45+L45+O45+R45+U45+X45 -> 2
B47: Faturamento | D47: Emissão e/ou lançamento de NF de retorno de comodato | F47: Diario | H47: 1 | I47: 1 | K47: 1 | L47: 1 | Z47: =H47+K47+N47+Q47+T47+W47 -> 2 | AA47: =I47+L47+O47+R47+U47+X47 -> 2
H48: 1 | I48: 1 | K48: 1 | L48: 1 | Z48: =H48+K48+N48+Q48+T48+W48 -> 2 | AA48: =I48+L48+O48+R48+U48+X48 -> 2
B50: Faturamento | D50: Emissão e/ou lançamento de NF de retorno de demonstração | F50: Diario | H50: 1 | I50: 1 | K50: 1 | L50: 1 | Z50: =H50+K50+N50+Q50+T50+W50 -> 2 | AA50: =I50+L50+O50+R50+U50+X50 -> 2
H51: 1 | I51: 1 | K51: 1 | L51: 1 | Z51: =H51+K51+N51+Q51+T51+W51 -> 2 | AA51: =I51+L51+O51+R51+U51+X51 -> 2
B53: Faturamento | D53: Emissão e/ou lançamento de NF de retorno de industrialização | F53: Diario | H53: 1 | I53: 1 | K53: 1 | L53: 1 | Z53: =H53+K53+N53+Q53+T53+W53 -> 2 | AA53: =I53+L53+O53+R53+U53+X53 -> 2
H54: 1 | I54: 1 | K54: 1 | L54: 1 | Z54: =H54+K54+N54+Q54+T54+W54 -> 2 | AA54: =I54+L54+O54+R54+U54+X54 -> 2
B56: Faturamento | D56: Emissão e/ou lançamento de NF de troca em garantia | F56: Diario | H56: 1 | I56: 1 | K56: 1 | L56: 1 | Z56: =H56+K56+N56+Q56+T56+W56 -> 2 | AA56: =I56+L56+O56+R56+U56+X56 -> 2
H57: 1 | I57: 1 | K57: 1 | L57: 1 | Z57: =H57+K57+N57+Q57+T57+W57 -> 2 | AA57: =I57+L57+O57+R57+U57+X57 -> 2
B59: Faturamento | D59: Análise e/ou criação de cadastros de clientes e fornecedores no sistema SAP | F59: Diario | H59: 1 | I59: 1 | K59: 1 | L59: 1 | Z59: =H59+K59+N59+Q59+T59+W59 -> 2 | AA59: =I59+L59+O59+R59+U59+X59 -> 2
H60: 1 | I60: 1 | K60: 1 | L60: 1 | Z60: =H60+K60+N60+Q60+T60+W60 -> 2 | AA60: =I60+L60+O60+R60+U60+X60 -> 2
B62: Faturamento | D62: Análise de possível emissão de guia DIFAL (diferencial de alíquotas) | F62: Diario | H62: 1 | I62: 1 | K62: 1 | L62: 1 | Z62: =H62+K62+N62+Q62+T62+W62 -> 2 | AA62: =I62+L62+O62+R62+U62+X62 -> 2
H63: 1 | I63: 1 | K63: 1 | L63: 1 | Z63: =H63+K63+N63+Q63+T63+W63 -> 2 | AA63: =I63+L63+O63+R63+U63+X63 -> 2
B65: Faturamento | D65: Confirmação de pagamento dos pedidos de venda com acesso ao banco Itaú | F65: Diario | H65: 1 | I65: 1 | Z65: =H65+K65+N65+Q65+T65+W65 -> 1 | AA65: =I65+L65+O65+R65+U65+X65 -> 1
H66: 1 | I66: 1 | Z66: =H66+K66+N66+Q66+T66+W66 -> 1 | AA66: =I66+L66+O66+R66+U66+X66 -> 1
B68: Faturamento | D68: Emissão de fatura de adiantamento no pedido de venda | F68: Diario | H68: 1 | I68: 1 | Z68: =H68+K68+N68+Q68+T68+W68 -> 1 | AA68: =I68+L68+O68+R68+U68+X68 -> 1
H69: 1 | I69: 1 | Z69: =H69+K69+N69+Q69+T69+W69 -> 1 | AA69: =I69+L69+O69+R69+U69+X69 -> 1
B71: Faturamento | D71: Controle das mensalidades de locação na planilha Excel junto com o sistema SAP | F71: Diario | H71: 1 | I71: 1 | K71: 1 | L71: 1 | Z71: =H71+K71+N71+Q71+T71+W71 -> 2 | AA71: =I71+L71+O71+R71+U71+X71 -> 2
H72: 1 | I72: 1 | K72: 1 | L72: 1 | Z72: =H72+K72+N72+Q72+T72+W72 -> 2 | AA72: =I72+L72+O72+R72+U72+X72 -> 2
B74: Faturamento | D74: Envio manual via e-mail das notas de débito e boletos para o respectivos clientes | F74: Diario | H74: 1 | I74: 1 | K74: 1 | L74: 1 | Z74: =H74+K74+N74+Q74+T74+W74 -> 2 | AA74: =I74+L74+O74+R74+U74+X74 -> 2
H75: 1 | I75: 1 | K75: 1 | L75: 1 | Z75: =H75+K75+N75+Q75+T75+W75 -> 2 | AA75: =I75+L75+O75+R75+U75+X75 -> 2
B77: Faturamento | D77: Análise e controle das mensalidades de manuntenção de equipamentos, para a posterior emissão de NFS-e | F77: Diario | H77: 1 | I77: 1 | Z77: =H77+K77+N77+Q77+T77+W77 -> 1 | AA77: =I77+L77+O77+R77+U77+X77 -> 1
H78: 1 | I78: 1 | Z78: =H78+K78+N78+Q78+T78+W78 -> 1 | AA78: =I78+L78+O78+R78+U78+X78 -> 1
B80: Faturamento | D80: Análise de novos contratos de locação novos / Planilhamento / cadastro no SAP, emissão das notas de débito (ND) | F80: Diario | H80: 1 | I80: 1 | K80: 1 | L80: 1 | Z80: =H80+K80+N80+Q80+T80+W80 -> 2 | AA80: =I80+L80+O80+R80+U80+X80 -> 2
H81: 1 | I81: 1 | Z81: =H81+K81+N81+Q81+T81+W81 -> 1 | AA81: =I81+L81+O81+R81+U81+X81 -> 1
B83: Faturamento | D83: Análise de contratos de locação em andamento | F83: Diario | H83: 1 | I83: 1 | K83: 1 | L83: 1 | Z83: =H83+K83+N83+Q83+T83+W83 -> 2 | AA83: =I83+L83+O83+R83+U83+X83 -> 2
H84: 1 | I84: 1 | Z84: =H84+K84+N84+Q84+T84+W84 -> 1 | AA84: =I84+L84+O84+R84+U84+X84 -> 1
B86: Faturamento | D86: Análise de possíveis reajuste contratuais nas parcelas dos contratos de locação/manuntenção | F86: Diario | H86: 1 | I86: 1 | Z86: =H86+K86+N86+Q86+T86+W86 -> 1 | AA86: =I86+L86+O86+R86+U86+X86 -> 1
H87: 1 | I87: 1 | Z87: =H87+K87+N87+Q87+T87+W87 -> 1 | AA87: =I87+L87+O87+R87+U87+X87 -> 1
B89: Faturamento | D89: Controle de retorno de comodato da Geneslab / emissão NF de venda | F89: Diario | H89: 1 | I89: 1 | Z89: =H89+K89+N89+Q89+T89+W89 -> 1 | AA89: =I89+L89+O89+R89+U89+X89 -> 1
H90: 1 | I90: 1 | Z90: =H90+K90+N90+Q90+T90+W90 -> 1 | AA90: =I90+L90+O90+R90+U90+X90 -> 1
B92: Faturamento | D92: Suporte e Orientações aos setores (help desk, comercial, adequação, almoxarifado) | F92: Diario | H92: 1 | I92: 1 | K92: 1 | L92: 1 | Z92: =H92+K92+N92+Q92+T92+W92 -> 2 | AA92: =I92+L92+O92+R92+U92+X92 -> 2
H93: 1 | I93: 1 | K93: 1 | L93: 1 | Z93: =H93+K93+N93+Q93+T93+W93 -> 2 | AA93: =I93+L93+O93+R93+U93+X93 -> 2
B95: Faturamento | D95: Resolução de problemas e/ou dúvidas de clientes, via e-mail, telefone, whatsapp | F95: Diario | H95: 1 | I95: 1 | K95: 1 | L95: 1 | Z95: =H95+K95+N95+Q95+T95+W95 -> 2 | AA95: =I95+L95+O95+R95+U95+X95 -> 2
H96: 1 | I96: 1 | K96: 1 | L96: 1 | Z96: =H96+K96+N96+Q96+T96+W96 -> 2 | AA96: =I96+L96+O96+R96+U96+X96 -> 2
B98: Faturamento | D98: Análise de impostos e tributações das operações em geral | F98: Diario | H98: 1 | I98: 1 | K98: 1 | L98: 1 | Z98: =H98+K98+N98+Q98+T98+W98 -> 2 | AA98: =I98+L98+O98+R98+U98+X98 -> 2
H99: 1 | I99: 1 | K99: 1 | L99: 1 | Z99: =H99+K99+N99+Q99+T99+W99 -> 2 | AA99: =I99+L99+O99+R99+U99+X99 -> 2
B101: Recebimento | D101: Lançamento de notas com pedido de compra | F101: Diario | K101: 1 | L101: 1 | N101: 1 | O101: 1 | Z101: =H101+K101+N101+Q101+T101+W101 -> 2 | AA101: =I101+L101+O101+R101+U101+X101 -> 2
K102: 1 | L102: 1 | N102: 1 | O102: 1 | Z102: =H102+K102+N102+Q102+T102+W102 -> 2 | AA102: =I102+L102+O102+R102+U102+X102 -> 2
B104: Recebimento | D104: Lançamento de notas recorrentes | F104: Diario | K104: 1 | L104: 1 | N104: 1 | O104: 1 | Z104: =H104+K104+N104+Q104+T104+W104 -> 2 | AA104: =I104+L104+O104+R104+U104+X104 -> 2
K105: 1 | L105: 1 | N105: 1 | O105: 1 | Z105: =H105+K105+N105+Q105+T105+W105 -> 2 | AA105: =I105+L105+O105+R105+U105+X105 -> 2
B107: Recebimento | D107: Lançamentos de guias e impostos (LCM) | F107: Diario | K107: 1 | L107: 1 | N107: 1 | O107: 1 | Z107: =H107+K107+N107+Q107+T107+W107 -> 2 | AA107: =I107+L107+O107+R107+U107+X107 -> 2
K108: 1 | L108: 1 | N108: 1 | O108: 1 | Z108: =H108+K108+N108+Q108+T108+W108 -> 2 | AA108: =I108+L108+O108+R108+U108+X108 -> 2
B110: Recebimento | D110: Lançamento da folha de pagamento | F110: Mensal | K110: 1 | L110: 1 | N110: 1 | O110: 1 | Z110: =H110+K110+N110+Q110+T110+W110 -> 2 | AA110: =I110+L110+O110+R110+U110+X110 -> 2
K111: 1 | L111: 1 | N111: 1 | O111: 1 | Z111: =H111+K111+N111+Q111+T111+W111 -> 2 | AA111: =I111+L111+O111+R111+U111+X111 -> 2
B113: Recebimento | D113: Controle de notas de entrada | F113: Diario | K113: 1 | L113: 1 | N113: 1 | O113: 1 | Z113: =H113+K113+N113+Q113+T113+W113 -> 2 | AA113: =I113+L113+O113+R113+U113+X113 -> 2
K114: 1 | L114: 1 | N114: 1 | O114: 1 | Z114: =H114+K114+N114+Q114+T114+W114 -> 2 | AA114: =I114+L114+O114+R114+U114+X114 -> 2
B116: Recebimento | D116: Lançamento de fatura de cartão de crédito | F116: Mensal | K116: 1 | L116: 1 | N116: 1 | O116: 1 | Z116: =H116+K116+N116+Q116+T116+W116 -> 2 | AA116: =I116+L116+O116+R116+U116+X116 -> 2
K117: 1 | L117: 1 | N117: 1 | O117: 1 | Z117: =H117+K117+N117+Q117+T117+W117 -> 2 | AA117: =I117+L117+O117+R117+U117+X117 -> 2
B119: Recebimento | D119: Abertura de pedidos recorrentes | F119: Diario | K119: 1 | L119: 1 | N119: 1 | O119: 1 | Z119: =H119+K119+N119+Q119+T119+W119 -> 2 | AA119: =I119+L119+O119+R119+U119+X119 -> 2
K120: 1 | L120: 1 | N120: 1 | O120: 1 | Z120: =H120+K120+N120+Q120+T120+W120 -> 2 | AA120: =I120+L120+O120+R120+U120+X120 -> 2
B122: Recebimento | D122: Fatura de adiantamento para fornecedor | F122: Diario | K122: 1 | L122: 1 | N122: 1 | O122: 1 | Z122: =H122+K122+N122+Q122+T122+W122 -> 2 | AA122: =I122+L122+O122+R122+U122+X122 -> 2
K123: 1 | L123: 1 | N123: 1 | O123: 1 | Z123: =H123+K123+N123+Q123+T123+W123 -> 2 | AA123: =I123+L123+O123+R123+U123+X123 -> 2
B125: Recebimento | D125: Importar arquivos XML de saídas para o Arquivei | F125: Diario | N125: 1 | O125: 1 | Z125: =H125+K125+N125+Q125+T125+W125 -> 1 | AA125: =I125+L125+O125+R125+U125+X125 -> 1
N126: 1 | O126: 1 | Z126: =H126+K126+N126+Q126+T126+W126 -> 1 | AA126: =I126+L126+O126+R126+U126+X126 -> 1
B128: Recebimento | D128: Envio de documentos à contabilidade externa | F128: Mensal | K128: 1 | L128: 1 | N128: 1 | O128: 1 | Z128: =H128+K128+N128+Q128+T128+W128 -> 2 | AA128: =I128+L128+O128+R128+U128+X128 -> 2
N129: 1 | O129: 1 | Z129: =H129+K129+N129+Q129+T129+W129 -> 1 | AA129: =I129+L129+O129+R129+U129+X129 -> 1
B131: Recebimento | D131: Efetivar lançamentos de impostos em débito automático | F131: Mensal | N131: 1 | O131: 1 | Z131: =H131+K131+N131+Q131+T131+W131 -> 1 | AA131: =I131+L131+O131+R131+U131+X131 -> 1
N132: 1 | O132: 1 | Z132: =H132+K132+N132+Q132+T132+W132 -> 1 | AA132: =I132+L132+O132+R132+U132+X132 -> 1
B134: Recebimento | D134: Lançamento de Cte | F134: Diario | N134: 1 | O134: 1 | Z134: =H134+K134+N134+Q134+T134+W134 -> 1 | AA134: =I134+L134+O134+R134+U134+X134 -> 1
N135: 1 | O135: 1 | Z135: =H135+K135+N135+Q135+T135+W135 -> 1 | AA135: =I135+L135+O135+R135+U135+X135 -> 1
B137: Recebimento | D137: Lançamento de multas de trânsito | F137: Diario | N137: 1 | O137: 1 | Z137: =H137+K137+N137+Q137+T137+W137 -> 1 | AA137: =I137+L137+O137+R137+U137+X137 -> 1
N138: 1 | O138: 1 | Z138: =H138+K138+N138+Q138+T138+W138 -> 1 | AA138: =I138+L138+O138+R138+U138+X138 -> 1
B140: Recebimento | D140: Lançamentos de Importação Simpificada (Courrier) | F140: Diario | Z140: =H140+K140+N140+Q140+T140+W140 -> 0 | AA140: =I140+L140+O140+R140+U140+X140 -> 0
Z141: =H141+K141+N141+Q141+T141+W141 -> 0 | AA141: =I141+L141+O141+R141+U141+X141 -> 0
B143: Recebimento | D143: Emissão de nota fiscal de Importação Simpificada (Courrier) | F143: Diario | K143: 1 | L143: 1 | N143: 1 | O143: 1 | Z143: =H143+K143+N143+Q143+T143+W143 -> 2 | AA143: =I143+L143+O143+R143+U143+X143 -> 2
K144: 1 | Z144: =H144+K144+N144+Q144+T144+W144 -> 1 | AA144: =I144+L144+O144+R144+U144+X144 -> 0
D146: ______________________________________________________________________________________________ | F146: ________ | Z146: =H146+K146+N146+Q146+T146+W146 -> 0 | AA146: =I146+L146+O146+R146+U146+X146 -> 0
Z147: =H147+K147+N147+Q147+T147+W147 -> 0 | AA147: =I147+L147+O147+R147+U147+X147 -> 0
D149: ______________________________________________________________________________________________ | F149: ________ | Z149: =H149+K149+N149+Q149+T149+W149 -> 0 | AA149: =I149+L149+O149+R149+U149+X149 -> 0
Z150: =H150+K150+N150+Q150+T150+W150 -> 0 | AA150: =I150+L150+O150+R150+U150+X150 -> 0
...

Sheet Fevereiro 2026
B2: Setorização | D2: Tarefas | F2: Periodicidade | H2: Luis | K2: Alexandre | N2: Pamella | Q2: Loraine | T2: Maykon | W2: Bruno
H3: Gerente | K3: Supervisor
D5: Classificação do Colaborador | H5: =H11+H83+H86+H89+H92+H95+H98+H200+H203+H206+H14+H17+H20+H23+H26+H29+H32+H35+H41+H38+H44+H47+H50+H53+H56+H59+H62+H65+H68+H71+H74+H77+H80+H101+H104+H107+H110+H113+H116+H119+H122+H125+H128+H131+H134+H137+H140+H143+H146+H149+H152+H155+H158+H161+H164+H167+H170+H173+H176+H179+H182+H185+H188+H191+H194+H197+H209+H212+H215+H218+H221+H224+H227+H230+H233+H236+H239+H242+H245+H248+H251+H254+H257+H260+H263+H266+H269+H272 -> 36 | I5: =I11+I83+I86+I89+I92+I95+I98+I200+I203+I206+I14+I17+I20+I23+I26+I29+I32+I35+I41+I38+I44+I47+I50+I53+I56+I59+I62+I65+I68+I71+I74+I77+I80+I101+I104+I107+I110+I113+I116+I119+I122+I125+I128+I131+I134+I137+I140+I143+I146+I149+I152+I155+I158+I161+I164+I167+I170+I173+I176+I179+I182+I185+I188+I191+I194+I197+I209+I212+I215+I218+I221+I224+I227+I230+I233+I236+I239+I242+I245+I248+I251+I254+I257+I260+I263+I266+I269+I272 -> 36 | K5: =K11+K83+K86+K89+K92+K95+K98+K200+K203+K206+K14+K17+K20+K23+K26+K29+K32+K35+K41+K38+K44+K47+K50+K53+K56+K59+K62+K65+K68+K71+K74+K77+K80+K101+K104+K107+K110+K113+K116+K119+K122+K125+K128+K131+K134+K137+K140+K143+K146+K149+K152+K155+K158+K161+K164+K167+K170+K173+K176+K179+K182+K185+K188+K191+K194+K197+K209+K212+K215+K218+K221+K224+K227+K230+K233+K236+K239+K242+K245+K248+K251+K254+K257+K260+K263+K266+K269+K272 -> 46 | L5: =L11+L83+L86+L89+L92+L95+L98+L200+L203+L206+L14+L17+L20+L23+L26+L29+L32+L35+L41+L38+L44+L47+L50+L53+L56+L59+L62+L65+L68+L71+L74+L77+L80+L101+L104+L107+L110+L113+L116+L119+L122+L125+L128+L131+L134+L137+L140+L143+L146+L149+L152+L155+L158+L161+L164+L167+L170+L173+L176+L179+L182+L185+L188+L191+L194+L197+L209+L212+L215+L218+L221+L224+L227+L230+L233+L236+L239+L242+L245+L248+L251+L254+L257+L260+L263+L266+L269+L272 -> 46 | N5: =N11+N83+N86+N89+N92+N95+N98+N200+N203+N206+N14+N17+N20+N23+N26+N29+N32+N35+N41+N38+N44+N47+N50+N53+N56+N59+N62+N65+N68+N71+N74+N77+N80+N101+N104+N107+N110+N113+N116+N119+N122+N125+N128+N131+N134+N137+N140+N143+N146+N149+N152+N155+N158+N161+N164+N167+N170+N173+N176+N179+N182+N185+N188+N191+N194+N197+N209+N212+N215+N218+N221+N224+N227+N230+N233+N236+N239+N242+N245+N248+N251+N254+N257+N260+N263+N266+N269+N272 -> 45 | O5: =O11+O83+O86+O89+O92+O95+O98+O200+O203+O206+O14+O17+O20+O23+O26+O29+O32+O35+O41+O38+O44+O47+O50+O53+O56+O59+O62+O65+O68+O71+O74+O77+O80+O101+O104+O107+O110+O113+O116+O119+O122+O125+O128+O131+O134+O137+O140+O143+O146+O149+O152+O155+O158+O161+O164+O167+O170+O173+O176+O179+O182+O185+O188+O191+O194+O197+O209+O212+O215+O218+O221+O224+O227+O230+O233+O236+O239+O242+O245+O248+O251+O254+O257+O260+O263+O266+O269+O272 -> 45 | Q5: =Q11+Q83+Q86+Q89+Q92+Q95+Q98+Q200+Q203+Q206+Q14+Q17+Q20+Q23+Q26+Q29+Q32+Q35+Q41+Q38+Q44+Q47+Q50+Q53+Q56+Q59+Q62+Q65+Q68+Q71+Q74+Q77+Q80+Q101+Q104+Q107+Q110+Q113+Q116+Q119+Q122+Q125+Q128+Q131+Q134+Q137+Q140+Q143+Q146+Q149+Q152+Q155+Q158+Q161+Q164+Q167+Q170+Q173+Q176+Q179+Q182+Q185+Q188+Q191+Q194+Q197+Q209+Q212+Q215+Q218+Q221+Q224+Q227+Q230+Q233+Q236+Q239+Q242+Q245+Q248+Q251+Q254+Q257+Q260+Q263+Q266+Q269+Q272 -> 14 | R5: =R11+R83+R86+R89+R92+R95+R98+R200+R203+R206+R14+R17+R20+R23+R26+R29+R32+R35+R41+R38+R44+R47+R50+R53+R56+R59+R62+R65+R68+R71+R74+R77+R80+R101+R104+R107+R110+R113+R116+R119+R122+R125+R128+R131+R134+R137+R140+R143+R146+R149+R152+R155+R158+R161+R164+R167+R170+R173+R176+R179+R182+R185+R188+R191+R194+R197+R209+R212+R215+R218+R221+R224+R227+R230+R233+R236+R239+R242+R245+R248+R251+R254+R257+R260+R263+R266+R269+R272 -> 14 | T5: =T11+T83+T86+T89+T92+T95+T98+T200+T203+T206+T14+T17+T20+T23+T26+T29+T32+T35+T41+T38+T44+T47+T50+T53+T56+T59+T62+T65+T68+T71+T74+T77+T80+T101+T104+T107+T110+T113+T116+T119+T122+T125+T128+T131+T134+T137+T140+T143+T146+T149+T152+T155+T158+T161+T164+T167+T170+T173+T176+T179+T182+T185+T188+T191+T194+T197+T209+T212+T215+T218+T221+T224+T227+T230+T233+T236+T239+T242+T245+T248+T251+T254+T257+T260+T263+T266+T269+T272 -> 0 | U5: =U11+U83+U86+U89+U92+U95+U98+U200+U203+U206+U14+U17+U20+U23+U26+U29+U32+U35+U41+U38+U44+U47+U50+U53+U56+U59+U62+U65+U68+U71+U74+U77+U80+U101+U104+U107+U110+U113+U116+U119+U122+U125+U128+U131+U134+U137+U140+U143+U146+U149+U152+U155+U158+U161+U164+U167+U170+U173+U176+U179+U182+U185+U188+U191+U194+U197+U209+U212+U215+U218+U221+U224+U227+U230+U233+U236+U239+U242+U245+U248+U251+U254+U257+U260+U263+U266+U269+U272 -> 0 | W5: =W11+W83+W86+W89+W92+W95+W98+W200+W203+W206+W14+W17+W20+W23+W26+W29+W32+W35+W41+W38+W44+W47+W50+W53+W56+W59+W62+W65+W68+W71+W74+W77+W80+W101+W104+W107+W110+W113+W116+W119+W122+W125+W128+W131+W134+W137+W140+W143+W146+W149+W152+W155+W158+W161+W164+W167+W170+W173+W176+W179+W182+W185+W188+W191+W194+W197+W209+W212+W215+W218+W221+W224+W227+W230+W233+W236+W239+W242+W245+W248+W251+W254+W257+W260+W263+W266+W269+W272 -> 0 | X5: =X11+X83+X86+X89+X92+X95+X98+X200+X203+X206+X14+X17+X20+X23+X26+X29+X32+X35+X41+X38+X44+X47+X50+X53+X56+X59+X62+X65+X68+X71+X74+X77+X80+X101+X104+X107+X110+X113+X116+X119+X122+X125+X128+X131+X134+X137+X140+X143+X146+X149+X152+X155+X158+X161+X164+X167+X170+X173+X176+X179+X182+X185+X188+X191+X194+X197+X209+X212+X215+X218+X221+X224+X227+X230+X233+X236+X239+X242+X245+X248+X251+X254+X257+X260+X263+X266+X269+X272 -> 0
H6: =H12+H84+H87+H90+H93+H96+H99+H201+H204+H207+H15+H18+H21+H24+H27+H30+H33+H36+H42+H39+H45+H48+H51+H54+H57+H60+H63+H66+H69+H72+H75+H78+H81+H102+H105+H108+H111+H114+H117+H120+H123+H126+H129+H132+H135+H138+H141+H144+H147+H150+H153+H156+H159+H162+H165+H168+H171+H174+H177+H180+H183+H186+H189+H192+H195+H198+H210+H213+H216+H219+H222+H225+H228+H231+H234+H237+H240+H243+H246+H249+H252+H255+H258+H261+H264+H267+H270+H273 -> 36 | I6: =I12+I84+I87+I90+I93+I96+I99+I201+I204+I207+I15+I18+I21+I24+I27+I30+I33+I36+I42+I39+I45+I48+I51+I54+I57+I60+I63+I66+I69+I72+I75+I78+I81+I102+I105+I108+I111+I114+I117+I120+I123+I126+I129+I132+I135+I138+I141+I144+I147+I150+I153+I156+I159+I162+I165+I168+I171+I174+I177+I180+I183+I186+I189+I192+I195+I198+I210+I213+I216+I219+I222+I225+I228+I231+I234+I237+I240+I243+I246+I249+I252+I255+I258+I261+I264+I267+I270+I273 -> 36 | K6: =K12+K84+K87+K90+K93+K96+K99+K201+K204+K207+K15+K18+K21+K24+K27+K30+K33+K36+K42+K39+K45+K48+K51+K54+K57+K60+K63+K66+K69+K72+K75+K78+K81+K102+K105+K108+K111+K114+K117+K120+K123+K126+K129+K132+K135+K138+K141+K144+K147+K150+K153+K156+K159+K162+K165+K168+K171+K174+K177+K180+K183+K186+K189+K192+K195+K198+K210+K213+K216+K219+K222+K225+K228+K231+K234+K237+K240+K243+K246+K249+K252+K255+K258+K261+K264+K267+K270+K273 -> 43 | L6: =L12+L84+L87+L90+L93+L96+L99+L201+L204+L207+L15+L18+L21+L24+L27+L30+L33+L36+L42+L39+L45+L48+L51+L54+L57+L60+L63+L66+L69+L72+L75+L78+L81+L102+L105+L108+L111+L114+L117+L120+L123+L126+L129+L132+L135+L138+L141+L144+L147+L150+L153+L156+L159+L162+L165+L168+L171+L174+L177+L180+L183+L186+L189+L192+L195+L198+L210+L213+L216+L219+L222+L225+L228+L231+L234+L237+L240+L243+L246+L249+L252+L255+L258+L261+L264+L267+L270+L273 -> 40 | N6: =N12+N84+N87+N90+N93+N96+N99+N201+N204+N207+N15+N18+N21+N24+N27+N30+N33+N36+N42+N39+N45+N48+N51+N54+N57+N60+N63+N66+N69+N72+N75+N78+N81+N102+N105+N108+N111+N114+N117+N120+N123+N126+N129+N132+N135+N138+N141+N144+N147+N150+N153+N156+N159+N162+N165+N168+N171+N174+N177+N180+N183+N186+N189+N192+N195+N198+N210+N213+N216+N219+N222+N225+N228+N231+N234+N237+N240+N243+N246+N249+N252+N255+N258+N261+N264+N267+N270+N273 -> 40 | O6: =O12+O84+O87+O90+O93+O96+O99+O201+O204+O207+O15+O18+O21+O24+O27+O30+O33+O36+O42+O39+O45+O48+O51+O54+O57+O60+O63+O66+O69+O72+O75+O78+O81+O102+O105+O108+O111+O114+O117+O120+O123+O126+O129+O132+O135+O138+O141+O144+O147+O150+O153+O156+O159+O162+O165+O168+O171+O174+O177+O180+O183+O186+O189+O192+O195+O198+O210+O213+O216+O219+O222+O225+O228+O231+O234+O237+O240+O243+O246+O249+O252+O255+O258+O261+O264+O267+O270+O273 -> 39 | Q6: =Q12+Q84+Q87+Q90+Q93+Q96+Q99+Q201+Q204+Q207+Q15+Q18+Q21+Q24+Q27+Q30+Q33+Q36+Q42+Q39+Q45+Q48+Q51+Q54+Q57+Q60+Q63+Q66+Q69+Q72+Q75+Q78+Q81+Q102+Q105+Q108+Q111+Q114+Q117+Q120+Q123+Q126+Q129+Q132+Q135+Q138+Q141+Q144+Q147+Q150+Q153+Q156+Q159+Q162+Q165+Q168+Q171+Q174+Q177+Q180+Q183+Q186+Q189+Q192+Q195+Q198+Q210+Q213+Q216+Q219+Q222+Q225+Q228+Q231+Q234+Q237+Q240+Q243+Q246+Q249+Q252+Q255+Q258+Q261+Q264+Q267+Q270+Q273 -> 14 | R6: =R12+R84+R87+R90+R93+R96+R99+R201+R204+R207+R15+R18+R21+R24+R27+R30+R33+R36+R42+R39+R45+R48+R51+R54+R57+R60+R63+R66+R69+R72+R75+R78+R81+R102+R105+R108+R111+R114+R117+R120+R123+R126+R129+R132+R135+R138+R141+R144+R147+R150+R153+R156+R159+R162+R165+R168+R171+R174+R177+R180+R183+R186+R189+R192+R195+R198+R210+R213+R216+R219+R222+R225+R228+R231+R234+R237+R240+R243+R246+R249+R252+R255+R258+R261+R264+R267+R270+R273 -> 11 | T6: =T12+T84+T87+T90+T93+T96+T99+T201+T204+T207+T15+T18+T21+T24+T27+T30+T33+T36+T42+T39+T45+T48+T51+T54+T57+T60+T63+T66+T69+T72+T75+T78+T81+T102+T105+T108+T111+T114+T117+T120+T123+T126+T129+T132+T135+T138+T141+T144+T147+T150+T153+T156+T159+T162+T165+T168+T171+T174+T177+T180+T183+T186+T189+T192+T195+T198+T210+T213+T216+T219+T222+T225+T228+T231+T234+T237+T240+T243+T246+T249+T252+T255+T258+T261+T264+T267+T270+T273 -> 0 | U6: =U12+U84+U87+U90+U93+U96+U99+U201+U204+U207+U15+U18+U21+U24+U27+U30+U33+U36+U42+U39+U45+U48+U51+U54+U57+U60+U63+U66+U69+U72+U75+U78+U81+U102+U105+U108+U111+U114+U117+U120+U123+U126+U129+U132+U135+U138+U141+U144+U147+U150+U153+U156+U159+U162+U165+U168+U171+U174+U177+U180+U183+U186+U189+U192+U195+U198+U210+U213+U216+U219+U222+U225+U228+U231+U234+U237+U240+U243+U246+U249+U252+U255+U258+U261+U264+U267+U270+U273 -> 0 | W6: =W12+W84+W87+W90+W93+W96+W99+W201+W204+W207+W15+W18+W21+W24+W27+W30+W33+W36+W42+W39+W45+W48+W51+W54+W57+W60+W63+W66+W69+W72+W75+W78+W81+W102+W105+W108+W111+W114+W117+W120+W123+W126+W129+W132+W135+W138+W141+W144+W147+W150+W153+W156+W159+W162+W165+W168+W171+W174+W177+W180+W183+W186+W189+W192+W195+W198+W210+W213+W216+W219+W222+W225+W228+W231+W234+W237+W240+W243+W246+W249+W252+W255+W258+W261+W264+W267+W270+W273 -> 0 | X6: =X12+X84+X87+X90+X93+X96+X99+X201+X204+X207+X15+X18+X21+X24+X27+X30+X33+X36+X42+X39+X45+X48+X51+X54+X57+X60+X63+X66+X69+X72+X75+X78+X81+X102+X105+X108+X111+X114+X117+X120+X123+X126+X129+X132+X135+X138+X141+X144+X147+X150+X153+X156+X159+X162+X165+X168+X171+X174+X177+X180+X183+X186+X189+X192+X195+X198+X210+X213+X216+X219+X222+X225+X228+X231+X234+X237+X240+X243+X246+X249+X252+X255+X258+X261+X264+X267+X270+X273 -> 0
D8: ----------------------------------------------------------------------------------------------------------------------------------------------------------------------> | H8: =H5+I5+H6+I6 -> 144 | I8: Pontos | K8: =K5+L5+K6+L6 -> 175 | L8: Pontos | N8: =N5+O5+N6+O6 -> 169 | O8: Pontos | Q8: =Q5+R5+Q6+R6 -> 53 | R8: Pontos | T8: =T5+U5+T6+U6 -> 0 | U8: Pontos | W8: =W5+X5+W6+X6 -> 0 | X8: Pontos
Z9: Semáforo | AC9: Legenda:
B11: Faturamento | D11: Emissão de NF de venda (NF-e) | F11: Diario | H11: 1 | I11: 1 | K11: 1 | L11: 1 | N11: 1 | O11: 1 | Q11: 1 | R11: 1 | Z11: =H11+K11+N11+Q11+T11+W11 -> 4 | AA11: =I11+L11+O11+R11+U11+X11 -> 4 | AD11: Aprendendo | AE11: 1
H12: 1 | I12: 1 | K12: 1 | L12: 1 | N12: 1 | O12: 1 | Q12: 1 | R12: 1 | Z12: =H12+K12+N12+Q12+T12+W12 -> 4 | AA12: =I12+L12+O12+R12+U12+X12 -> 4
B14: Faturamento | D14: Emissão de NF de exportação (NF-e) | F14: Diario | H14: 1 | I14: 1 | K14: 1 | L14: 1 | N14: 1 | O14: 1 | Z14: =H14+K14+N14+Q14+T14+W14 -> 3 | AA14: =I14+L14+O14+R14+U14+X14 -> 3 | AC14: Consegue fazer | AD14: com ajuda | AE14: 1
H15: 1 | I15: 1 | K15: 1 | L15: 1 | N15: 1 | O15: 1 | Z15: =H15+K15+N15+Q15+T15+W15 -> 3 | AA15: =I15+L15+O15+R15+U15+X15 -> 3 | AE15: 1
B17: Faturamento | D17: Emissão de NF de importação (NF-e) | F17: Diario | H17: 1 | I17: 1 | K17: 1 | L17: 1 | N17: 1 | O17: 1 | Z17: =H17+K17+N17+Q17+T17+W17 -> 3 | AA17: =I17+L17+O17+R17+U17+X17 -> 3 | AC17: Consegue fazer | AD17: sem ajuda | AE17: 1 | AF17: 1
H18: 1 | I18: 1 | K18: 1 | L18: 1 | N18: 1 | O18: 1 | Z18: =H18+K18+N18+Q18+T18+W18 -> 3 | AA18: =I18+L18+O18+R18+U18+X18 -> 3 | AC18: (Sei fazer, mas não sei porque faço) | AE18: 1
B20: Faturamento | D20: Emissão de NF de comodato (NF-e) | F20: Diario | H20: 1 | I20: 1 | K20: 1 | L20: 1 | N20: 1 | O20: 1 | Q20: 1 | R20: 1 | Z20: =H20+K20+N20+Q20+T20+W20 -> 4 | AA20: =I20+L20+O20+R20+U20+X20 -> 4 | AC20: Consegue fazer | AD20: e ensinar | AE20: 1 | AF20: 1
H21: 1 | I21: 1 | K21: 1 | L21: 1 | N21: 1 | O21: 1 | Q21: 1 | R21: 1 | Z21: =H21+K21+N21+Q21+T21+W21 -> 4 | AA21: =I21+L21+O21+R21+U21+X21 -> 4 | AC21: (Sei fazer, e sei porque faço) | AE21: 1 | AF21: 1
B23: Faturamento | D23: Emissão de NF de bonificação ou brinde (NF-e) | F23: Diario | H23: 1 | I23: 1 | K23: 1 | L23: 1 | N23: 1 | O23: 1 | Q23: 1 | R23: 1 | Z23: =H23+K23+N23+Q23+T23+W23 -> 4 | AA23: =I23+L23+O23+R23+U23+X23 -> 4
H24: 1 | I24: 1 | K24: 1 | L24: 1 | N24: 1 | O24: 1 | Q24: 1 | R24: 1 | Z24: =H24+K24+N24+Q24+T24+W24 -> 4 | AA24: =I24+L24+O24+R24+U24+X24 -> 4
B26: Faturamento | D26: Emissão de NF de demonstração (NF-e) | F26: Diario | H26: 1 | I26: 1 | K26: 1 | L26: 1 | N26: 1 | O26: 1 | Q26: 1 | R26: 1 | Z26: =H26+K26+N26+Q26+T26+W26 -> 4 | AA26: =I26+L26+O26+R26+U26+X26 -> 4
H27: 1 | I27: 1 | K27: 1 | L27: 1 | N27: 1 | O27: 1 | Q27: 1 | R27: 1 | Z27: =H27+K27+N27+Q27+T27+W27 -> 4 | AA27: =I27+L27+O27+R27+U27+X27 -> 4
B29: Faturamento | D29: Emissão de NF de troca em garantia (NF-e) | F29: Diario | H29: 1 | I29: 1 | K29: 1 | L29: 1 | N29: 1 | O29: 1 | Q29: 1 | R29: 1 | Z29: =H29+K29+N29+Q29+T29+W29 -> 4 | AA29: =I29+L29+O29+R29+U29+X29 -> 4
H30: 1 | I30: 1 | K30: 1 | L30: 1 | N30: 1 | O30: 1 | Q30: 1 | R30: 1 | Z30: =H30+K30+N30+Q30+T30+W30 -> 4 | AA30: =I30+L30+O30+R30+U30+X30 -> 4
B32: Faturamento | D32: Emissão de NF de industrialização (NF-e) | F32: Diario | H32: 1 | I32: 1 | K32: 1 | L32: 1 | N32: 1 | O32: 1 | Z32: =H32+K32+N32+Q32+T32+W32 -> 3 | AA32: =I32+L32+O32+R32+U32+X32 -> 3
H33: 1 | I33: 1 | K33: 1 | L33: 1 | N33: 1 | O33: 1 | Z33: =H33+K33+N33+Q33+T33+W33 -> 3 | AA33: =I33+L33+O33+R33+U33+X33 -> 3
B35: Faturamento | D35: Emissão de NF de serviço (NFS-e) | F35: Diario | H35: 1 | I35: 1 | K35: 1 | L35: 1 | N35: 1 | O35: 1 | Z35: =H35+K35+N35+Q35+T35+W35 -> 3 | AA35: =I35+L35+O35+R35+U35+X35 -> 3
H36: 1 | I36: 1 | K36: 1 | N36: 1 | O36: 1 | Z36: =H36+K36+N36+Q36+T36+W36 -> 3 | AA36: =I36+L36+O36+R36+U36+X36 -> 2
B38: Faturamento | D38: Emissão de NF de débito (ND) | F38: Diario | H38: 1 | I38: 1 | K38: 1 | L38: 1 | N38: 1 | O38: 1 | Z38: =H38+K38+N38+Q38+T38+W38 -> 3 | AA38: =I38+L38+O38+R38+U38+X38 -> 3
H39: 1 | I39: 1 | K39: 1 | N39: 1 | O39: 1 | Z39: =H39+K39+N39+Q39+T39+W39 -> 3 | AA39: =I39+L39+O39+R39+U39+X39 -> 2
B41: Faturamento | D41: Emissão de NF complementar de ICMS (NF-e) | F41: Diario | H41: 1 | I41: 1 | K41: 1 | L41: 1 | N41: 1 | O41: 1 | Z41: =H41+K41+N41+Q41+T41+W41 -> 3 | AA41: =I41+L41+O41+R41+U41+X41 -> 3
H42: 1 | I42: 1 | K42: 1 | L42: 1 | Z42: =H42+K42+N42+Q42+T42+W42 -> 2 | AA42: =I42+L42+O42+R42+U42+X42 -> 2
B44: Faturamento | D44: Emissão e/ou lançamento de NF de devolução de venda | F44: Diario | H44: 1 | I44: 1 | K44: 1 | L44: 1 | N44: 1 | O44: 1 | Q44: 1 | R44: 1 | Z44: =H44+K44+N44+Q44+T44+W44 -> 4 | AA44: =I44+L44+O44+R44+U44+X44 -> 4
H45: 1 | I45: 1 | K45: 1 | L45: 1 | N45: 1 | O45: 1 | Q45: 1 | R45: 1 | Z45: =H45+K45+N45+Q45+T45+W45 -> 4 | AA45: =I45+L45+O45+R45+U45+X45 -> 4
B47: Faturamento | D47: Emissão e/ou lançamento de NF de retorno de comodato | F47: Diario | H47: 1 | I47: 1 | K47: 1 | L47: 1 | N47: 1 | O47: 1 | Q47: 1 | R47: 1 | Z47: =H47+K47+N47+Q47+T47+W47 -> 4 | AA47: =I47+L47+O47+R47+U47+X47 -> 4
H48: 1 | I48: 1 | K48: 1 | L48: 1 | N48: 1 | O48: 1 | Q48: 1 | R48: 1 | Z48: =H48+K48+N48+Q48+T48+W48 -> 4 | AA48: =I48+L48+O48+R48+U48+X48 -> 4
B50: Faturamento | D50: Emissão e/ou lançamento de NF de retorno de demonstração | F50: Diario | H50: 1 | I50: 1 | K50: 1 | L50: 1 | N50: 1 | O50: 1 | Q50: 1 | R50: 1 | Z50: =H50+K50+N50+Q50+T50+W50 -> 4 | AA50: =I50+L50+O50+R50+U50+X50 -> 4
H51: 1 | I51: 1 | K51: 1 | L51: 1 | N51: 1 | O51: 1 | Q51: 1 | R51: 1 | Z51: =H51+K51+N51+Q51+T51+W51 -> 4 | AA51: =I51+L51+O51+R51+U51+X51 -> 4
B53: Faturamento | D53: Emissão e/ou lançamento de NF de retorno de industrialização | F53: Diario | H53: 1 | I53: 1 | K53: 1 | L53: 1 | N53: 1 | O53: 1 | Z53: =H53+K53+N53+Q53+T53+W53 -> 3 | AA53: =I53+L53+O53+R53+U53+X53 -> 3
H54: 1 | I54: 1 | K54: 1 | L54: 1 | N54: 1 | O54: 1 | Z54: =H54+K54+N54+Q54+T54+W54 -> 3 | AA54: =I54+L54+O54+R54+U54+X54 -> 3
B56: Faturamento | D56: Emissão e/ou lançamento de NF de troca em garantia | F56: Diario | H56: 1 | I56: 1 | K56: 1 | L56: 1 | N56: 1 | O56: 1 | Q56: 1 | R56: 1 | Z56: =H56+K56+N56+Q56+T56+W56 -> 4 | AA56: =I56+L56+O56+R56+U56+X56 -> 4
H57: 1 | I57: 1 | K57: 1 | L57: 1 | N57: 1 | O57: 1 | Q57: 1 | R57: 1 | Z57: =H57+K57+N57+Q57+T57+W57 -> 4 | AA57: =I57+L57+O57+R57+U57+X57 -> 4
B59: Faturamento | D59: Análise e/ou criação de cadastros de clientes e fornecedores no sistema SAP | F59: Diario | H59: 1 | I59: 1 | K59: 1 | L59: 1 | N59: 1 | O59: 1 | Q59: 1 | R59: 1 | Z59: =H59+K59+N59+Q59+T59+W59 -> 4 | AA59: =I59+L59+O59+R59+U59+X59 -> 4
H60: 1 | I60: 1 | K60: 1 | L60: 1 | N60: 1 | O60: 1 | Q60: 1 | R60: 1 | Z60: =H60+K60+N60+Q60+T60+W60 -> 4 | AA60: =I60+L60+O60+R60+U60+X60 -> 4
B62: Faturamento | D62: Análise de possível emissão de guia DIFAL (diferencial de alíquotas) | F62: Diario | H62: 1 | I62: 1 | K62: 1 | L62: 1 | N62: 1 | O62: 1 | Z62: =H62+K62+N62+Q62+T62+W62 -> 3 | AA62: =I62+L62+O62+R62+U62+X62 -> 3
H63: 1 | I63: 1 | K63: 1 | L63: 1 | Z63: =H63+K63+N63+Q63+T63+W63 -> 2 | AA63: =I63+L63+O63+R63+U63+X63 -> 2
B65: Faturamento | D65: Confirmação de pagamento dos pedidos de venda com acesso ao banco Itaú | F65: Diario | H65: 1 | I65: 1 | Z65: =H65+K65+N65+Q65+T65+W65 -> 1 | AA65: =I65+L65+O65+R65+U65+X65 -> 1
H66: 1 | I66: 1 | Z66: =H66+K66+N66+Q66+T66+W66 -> 1 | AA66: =I66+L66+O66+R66+U66+X66 -> 1
B68: Faturamento | D68: Emissão de fatura de adiantamento no pedido de venda | F68: Diario | H68: 1 | I68: 1 | N68: 1 | O68: 1 | Z68: =H68+K68+N68+Q68+T68+W68 -> 2 | AA68: =I68+L68+O68+R68+U68+X68 -> 2
H69: 1 | I69: 1 | N69: 1 | O69: 1 | Z69: =H69+K69+N69+Q69+T69+W69 -> 2 | AA69: =I69+L69+O69+R69+U69+X69 -> 2
B71: Faturamento | D71: Controle das mensalidades de locação na planilha Excel junto com o sistema SAP | F71: Diario | H71: 1 | I71: 1 | K71: 1 | L71: 1 | N71: 1 | O71: 1 | Z71: =H71+K71+N71+Q71+T71+W71 -> 3 | AA71: =I71+L71+O71+R71+U71+X71 -> 3
H72: 1 | I72: 1 | K72: 1 | L72: 1 | N72: 1 | O72: 1 | Z72: =H72+K72+N72+Q72+T72+W72 -> 3 | AA72: =I72+L72+O72+R72+U72+X72 -> 3
B74: Faturamento | D74: Envio manual via e-mail das notas de débito e boletos para o respectivos clientes | F74: Diario | H74: 1 | I74: 1 | K74: 1 | L74: 1 | N74: 1 | O74: 1 | Q74: 1 | R74: 1 | Z74: =H74+K74+N74+Q74+T74+W74 -> 4 | AA74: =I74+L74+O74+R74+U74+X74 -> 4
H75: 1 | I75: 1 | K75: 1 | L75: 1 | N75: 1 | O75: 1 | Q75: 1 | R75: 1 | Z75: =H75+K75+N75+Q75+T75+W75 -> 4 | AA75: =I75+L75+O75+R75+U75+X75 -> 4
B77: Faturamento | D77: Análise e controle das mensalidades de manuntenção de equipamentos, para a posterior emissão de NFS-e | F77: Diario | H77: 1 | I77: 1 | N77: 1 | O77: 1 | Z77: =H77+K77+N77+Q77+T77+W77 -> 2 | AA77: =I77+L77+O77+R77+U77+X77 -> 2
H78: 1 | I78: 1 | N78: 1 | O78: 1 | Z78: =H78+K78+N78+Q78+T78+W78 -> 2 | AA78: =I78+L78+O78+R78+U78+X78 -> 2
B80: Faturamento | D80: Análise de novos contratos de locação novos / Planilhamento / cadastro no SAP, emissão das notas de débito (ND) | F80: Diario | H80: 1 | I80: 1 | K80: 1 | L80: 1 | N80: 1 | O80: 1 | Z80: =H80+K80+N80+Q80+T80+W80 -> 3 | AA80: =I80+L80+O80+R80+U80+X80 -> 3
H81: 1 | I81: 1 | N81: 1 | O81: 1 | Z81: =H81+K81+N81+Q81+T81+W81 -> 2 | AA81: =I81+L81+O81+R81+U81+X81 -> 2
B83: Faturamento | D83: Análise de contratos de locação em andamento | F83: Diario | H83: 1 | I83: 1 | K83: 1 | L83: 1 | N83: 1 | O83: 1 | Z83: =H83+K83+N83+Q83+T83+W83 -> 3 | AA83: =I83+L83+O83+R83+U83+X83 -> 3
H84: 1 | I84: 1 | N84: 1 | O84: 1 | Z84: =H84+K84+N84+Q84+T84+W84 -> 2 | AA84: =I84+L84+O84+R84+U84+X84 -> 2
B86: Faturamento | D86: Análise de possíveis reajuste contratuais nas parcelas dos contratos de locação/manuntenção | F86: Diario | H86: 1 | I86: 1 | N86: 1 | O86: 1 | Z86: =H86+K86+N86+Q86+T86+W86 -> 2 | AA86: =I86+L86+O86+R86+U86+X86 -> 2
H87: 1 | I87: 1 | N87: 1 | O87: 1 | Z87: =H87+K87+N87+Q87+T87+W87 -> 2 | AA87: =I87+L87+O87+R87+U87+X87 -> 2
B89: Faturamento | D89: Controle de retorno de comodato da Geneslab / emissão NF de venda | F89: Diario | H89: 1 | I89: 1 | N89: 1 | O89: 1 | Z89: =H89+K89+N89+Q89+T89+W89 -> 2 | AA89: =I89+L89+O89+R89+U89+X89 -> 2
H90: 1 | I90: 1 | N90: 1 | O90: 1 | Z90: =H90+K90+N90+Q90+T90+W90 -> 2 | AA90: =I90+L90+O90+R90+U90+X90 -> 2
B92: Faturamento | D92: Suporte e Orientações aos setores (help desk, comercial, adequação, almoxarifado) | F92: Diario | H92: 1 | I92: 1 | K92: 1 | L92: 1 | N92: 1 | O92: 1 | Q92: 1 | R92: 1 | Z92: =H92+K92+N92+Q92+T92+W92 -> 4 | AA92: =I92+L92+O92+R92+U92+X92 -> 4
H93: 1 | I93: 1 | K93: 1 | L93: 1 | N93: 1 | O93: 1 | Q93: 1 | Z93: =H93+K93+N93+Q93+T93+W93 -> 4 | AA93: =I93+L93+O93+R93+U93+X93 -> 3
B95: Faturamento | D95: Resolução de problemas e/ou dúvidas de clientes, via e-mail, telefone, whatsapp | F95: Diario | H95: 1 | I95: 1 | K95: 1 | L95: 1 | N95: 1 | O95: 1 | Q95: 1 | R95: 1 | Z95: =H95+K95+N95+Q95+T95+W95 -> 4 | AA95: =I95+L95+O95+R95+U95+X95 -> 4
H96: 1 | I96: 1 | K96: 1 | L96: 1 | N96: 1 | O96: 1 | Q96: 1 | Z96: =H96+K96+N96+Q96+T96+W96 -> 4 | AA96: =I96+L96+O96+R96+U96+X96 -> 3
B98: Faturamento | D98: Análise de impostos e tributações das operações em geral | F98: Diario | H98: 1 | I98: 1 | K98: 1 | L98: 1 | N98: 1 | O98: 1 | Z98: =H98+K98+N98+Q98+T98+W98 -> 3 | AA98: =I98+L98+O98+R98+U98+X98 -> 3
H99: 1 | I99: 1 | K99: 1 | L99: 1 | Z99: =H99+K99+N99+Q99+T99+W99 -> 2 | AA99: =I99+L99+O99+R99+U99+X99 -> 2
B101: Recebimento | D101: Lançamento de notas com pedido de compra | F101: Diario | K101: 1 | L101: 1 | N101: 1 | O101: 1 | Z101: =H101+K101+N101+Q101+T101+W101 -> 2 | AA101: =I101+L101+O101+R101+U101+X101 -> 2
K102: 1 | L102: 1 | N102: 1 | O102: 1 | Z102: =H102+K102+N102+Q102+T102+W102 -> 2 | AA102: =I102+L102+O102+R102+U102+X102 -> 2
B104: Recebimento | D104: Lançamento de notas recorrentes | F104: Diario | K104: 1 | L104: 1 | N104: 1 | O104: 1 | Z104: =H104+K104+N104+Q104+T104+W104 -> 2 | AA104: =I104+L104+O104+R104+U104+X104 -> 2
K105: 1 | L105: 1 | N105: 1 | O105: 1 | Z105: =H105+K105+N105+Q105+T105+W105 -> 2 | AA105: =I105+L105+O105+R105+U105+X105 -> 2
B107: Recebimento | D107: Lançamentos de guias e impostos (LCM) | F107: Diario | K107: 1 | L107: 1 | N107: 1 | O107: 1 | Z107: =H107+K107+N107+Q107+T107+W107 -> 2 | AA107: =I107+L107+O107+R107+U107+X107 -> 2
K108: 1 | L108: 1 | N108: 1 | O108: 1 | Z108: =H108+K108+N108+Q108+T108+W108 -> 2 | AA108: =I108+L108+O108+R108+U108+X108 -> 2
B110: Recebimento | D110: Lançamento da folha de pagamento | F110: Mensal | K110: 1 | L110: 1 | N110: 1 | O110: 1 | Z110: =H110+K110+N110+Q110+T110+W110 -> 2 | AA110: =I110+L110+O110+R110+U110+X110 -> 2
K111: 1 | L111: 1 | N111: 1 | O111: 1 | Z111: =H111+K111+N111+Q111+T111+W111 -> 2 | AA111: =I111+L111+O111+R111+U111+X111 -> 2
B113: Recebimento | D113: Controle de notas de entrada | F113: Diario | K113: 1 | L113: 1 | N113: 1 | O113: 1 | Q113: 1 | R113: 1 | Z113: =H113+K113+N113+Q113+T113+W113 -> 3 | AA113: =I113+L113+O113+R113+U113+X113 -> 3
K114: 1 | L114: 1 | N114: 1 | O114: 1 | Q114: 1 | Z114: =H114+K114+N114+Q114+T114+W114 -> 3 | AA114: =I114+L114+O114+R114+U114+X114 -> 2
B116: Recebimento | D116: Lançamento de fatura de cartão de crédito | F116: Mensal | K116: 1 | L116: 1 | N116: 1 | O116: 1 | Z116: =H116+K116+N116+Q116+T116+W116 -> 2 | AA116: =I116+L116+O116+R116+U116+X116 -> 2
K117: 1 | L117: 1 | N117: 1 | O117: 1 | Z117: =H117+K117+N117+Q117+T117+W117 -> 2 | AA117: =I117+L117+O117+R117+U117+X117 -> 2
B119: Recebimento | D119: Abertura de pedidos recorrentes | F119: Diario | K119: 1 | L119: 1 | N119: 1 | O119: 1 | Z119: =H119+K119+N119+Q119+T119+W119 -> 2 | AA119: =I119+L119+O119+R119+U119+X119 -> 2
K120: 1 | L120: 1 | N120: 1 | O120: 1 | Z120: =H120+K120+N120+Q120+T120+W120 -> 2 | AA120: =I120+L120+O120+R120+U120+X120 -> 2
B122: Recebimento | D122: Fatura de adiantamento para fornecedor | F122: Diario | K122: 1 | L122: 1 | N122: 1 | O122: 1 | Z122: =H122+K122+N122+Q122+T122+W122 -> 2 | AA122: =I122+L122+O122+R122+U122+X122 -> 2
K123: 1 | L123: 1 | N123: 1 | O123: 1 | Z123: =H123+K123+N123+Q123+T123+W123 -> 2 | AA123: =I123+L123+O123+R123+U123+X123 -> 2
B125: Recebimento | D125: Importar arquivos XML de saídas para o Arquivei | F125: Diario | N125: 1 | O125: 1 | Z125: =H125+K125+N125+Q125+T125+W125 -> 1 | AA125: =I125+L125+O125+R125+U125+X125 -> 1
N126: 1 | O126: 1 | Z126: =H126+K126+N126+Q126+T126+W126 -> 1 | AA126: =I126+L126+O126+R126+U126+X126 -> 1
B128: Recebimento | D128: Envio de documentos à contabilidade externa | F128: Mensal | K128: 1 | L128: 1 | N128: 1 | O128: 1 | Z128: =H128+K128+N128+Q128+T128+W128 -> 2 | AA128: =I128+L128+O128+R128+U128+X128 -> 2
N129: 1 | O129: 1 | Z129: =H129+K129+N129+Q129+T129+W129 -> 1 | AA129: =I129+L129+O129+R129+U129+X129 -> 1
B131: Recebimento | D131: Efetivar lançamentos de impostos em débito automático | F131: Mensal | N131: 1 | O131: 1 | Z131: =H131+K131+N131+Q131+T131+W131 -> 1 | AA131: =I131+L131+O131+R131+U131+X131 -> 1
N132: 1 | O132: 1 | Z132: =H132+K132+N132+Q132+T132+W132 -> 1 | AA132: =I132+L132+O132+R132+U132+X132 -> 1
B134: Recebimento | D134: Lançamento de Cte | F134: Diario | N134: 1 | O134: 1 | Z134: =H134+K134+N134+Q134+T134+W134 -> 1 | AA134: =I134+L134+O134+R134+U134+X134 -> 1
N135: 1 | O135: 1 | Z135: =H135+K135+N135+Q135+T135+W135 -> 1 | AA135: =I135+L135+O135+R135+U135+X135 -> 1
B137: Recebimento | D137: Lançamento de multas de trânsito | F137: Diario | N137: 1 | O137: 1 | Z137: =H137+K137+N137+Q137+T137+W137 -> 1 | AA137: =I137+L137+O137+R137+U137+X137 -> 1
N138: 1 | O138: 1 | Z138: =H138+K138+N138+Q138+T138+W138 -> 1 | AA138: =I138+L138+O138+R138+U138+X138 -> 1
B140: Recebimento | D140: Lançamentos de Importação Simpificada (Courrier) | F140: Diario | N140: 1 | O140: 1 | Z140: =H140+K140+N140+Q140+T140+W140 -> 1 | AA140: =I140+L140+O140+R140+U140+X140 -> 1
Z141: =H141+K141+N141+Q141+T141+W141 -> 0 | AA141: =I141+L141+O141+R141+U141+X141 -> 0
B143: Recebimento | D143: Emissão de nota fiscal de Importação Simpificada (Courrier) | F143: Diario | K143: 1 | L143: 1 | N143: 1 | O143: 1 | Z143: =H143+K143+N143+Q143+T143+W143 -> 2 | AA143: =I143+L143+O143+R143+U143+X143 -> 2
K144: 1 | Z144: =H144+K144+N144+Q144+T144+W144 -> 1 | AA144: =I144+L144+O144+R144+U144+X144 -> 0
D146: ______________________________________________________________________________________________ | F146: ________ | Z146: =H146+K146+N146+Q146+T146+W146 -> 0 | AA146: =I146+L146+O146+R146+U146+X146 -> 0
Z147: =H147+K147+N147+Q147+T147+W147 -> 0 | AA147: =I147+L147+O147+R147+U147+X147 -> 0
D149: ______________________________________________________________________________________________ | F149: ________ | Z149: =H149+K149+N149+Q149+T149+W149 -> 0 | AA149: =I149+L149+O149+R149+U149+X149 -> 0
Z150: =H150+K150+N150+Q150+T150+W150 -> 0 | AA150: =I150+L150+O150+R150+U150+X150 -> 0
...

Sheet Março 2026
B2: Setorização | D2: Tarefas | F2: Periodicidade | H2: Luis | K2: Alexandre | N2: Pamella | Q2: Loraine | T2: Maykon | W2: Bruno
H3: Gerente | K3: Supervisor
D5: Classificação do Colaborador | H5: =H11+H83+H86+H89+H92+H95+H98+H200+H203+H206+H14+H17+H20+H23+H26+H29+H32+H35+H41+H38+H44+H47+H50+H53+H56+H59+H62+H65+H68+H71+H74+H77+H80+H101+H104+H107+H110+H113+H116+H119+H122+H125+H128+H131+H134+H137+H140+H143+H146+H149+H152+H155+H158+H161+H164+H167+H170+H173+H176+H179+H182+H185+H188+H191+H194+H197+H209+H212+H215+H218+H221+H224+H227+H230+H233+H236+H239+H242+H245+H248+H251+H254+H257+H260+H263+H266+H269+H272 -> 41 | I5: =I11+I83+I86+I89+I92+I95+I98+I200+I203+I206+I14+I17+I20+I23+I26+I29+I32+I35+I41+I38+I44+I47+I50+I53+I56+I59+I62+I65+I68+I71+I74+I77+I80+I101+I104+I107+I110+I113+I116+I119+I122+I125+I128+I131+I134+I137+I140+I143+I146+I149+I152+I155+I158+I161+I164+I167+I170+I173+I176+I179+I182+I185+I188+I191+I194+I197+I209+I212+I215+I218+I221+I224+I227+I230+I233+I236+I239+I242+I245+I248+I251+I254+I257+I260+I263+I266+I269+I272 -> 41 | K5: =K11+K83+K86+K89+K92+K95+K98+K200+K203+K206+K14+K17+K20+K23+K26+K29+K32+K35+K41+K38+K44+K47+K50+K53+K56+K59+K62+K65+K68+K71+K74+K77+K80+K101+K104+K107+K110+K113+K116+K119+K122+K125+K128+K131+K134+K137+K140+K143+K146+K149+K152+K155+K158+K161+K164+K167+K170+K173+K176+K179+K182+K185+K188+K191+K194+K197+K209+K212+K215+K218+K221+K224+K227+K230+K233+K236+K239+K242+K245+K248+K251+K254+K257+K260+K263+K266+K269+K272 -> 46 | L5: =L11+L83+L86+L89+L92+L95+L98+L200+L203+L206+L14+L17+L20+L23+L26+L29+L32+L35+L41+L38+L44+L47+L50+L53+L56+L59+L62+L65+L68+L71+L74+L77+L80+L101+L104+L107+L110+L113+L116+L119+L122+L125+L128+L131+L134+L137+L140+L143+L146+L149+L152+L155+L158+L161+L164+L167+L170+L173+L176+L179+L182+L185+L188+L191+L194+L197+L209+L212+L215+L218+L221+L224+L227+L230+L233+L236+L239+L242+L245+L248+L251+L254+L257+L260+L263+L266+L269+L272 -> 46 | N5: =N11+N83+N86+N89+N92+N95+N98+N200+N203+N206+N14+N17+N20+N23+N26+N29+N32+N35+N41+N38+N44+N47+N50+N53+N56+N59+N62+N65+N68+N71+N74+N77+N80+N101+N104+N107+N110+N113+N116+N119+N122+N125+N128+N131+N134+N137+N140+N143+N146+N149+N152+N155+N158+N161+N164+N167+N170+N173+N176+N179+N182+N185+N188+N191+N194+N197+N209+N212+N215+N218+N221+N224+N227+N230+N233+N236+N239+N242+N245+N248+N251+N254+N257+N260+N263+N266+N269+N272 -> 45 | O5: =O11+O83+O86+O89+O92+O95+O98+O200+O203+O206+O14+O17+O20+O23+O26+O29+O32+O35+O41+O38+O44+O47+O50+O53+O56+O59+O62+O65+O68+O71+O74+O77+O80+O101+O104+O107+O110+O113+O116+O119+O122+O125+O128+O131+O134+O137+O140+O143+O146+O149+O152+O155+O158+O161+O164+O167+O170+O173+O176+O179+O182+O185+O188+O191+O194+O197+O209+O212+O215+O218+O221+O224+O227+O230+O233+O236+O239+O242+O245+O248+O251+O254+O257+O260+O263+O266+O269+O272 -> 45 | Q5: =Q11+Q83+Q86+Q89+Q92+Q95+Q98+Q200+Q203+Q206+Q14+Q17+Q20+Q23+Q26+Q29+Q32+Q35+Q41+Q38+Q44+Q47+Q50+Q53+Q56+Q59+Q62+Q65+Q68+Q71+Q74+Q77+Q80+Q101+Q104+Q107+Q110+Q113+Q116+Q119+Q122+Q125+Q128+Q131+Q134+Q137+Q140+Q143+Q146+Q149+Q152+Q155+Q158+Q161+Q164+Q167+Q170+Q173+Q176+Q179+Q182+Q185+Q188+Q191+Q194+Q197+Q209+Q212+Q215+Q218+Q221+Q224+Q227+Q230+Q233+Q236+Q239+Q242+Q245+Q248+Q251+Q254+Q257+Q260+Q263+Q266+Q269+Q272 -> 14 | R5: =R11+R83+R86+R89+R92+R95+R98+R200+R203+R206+R14+R17+R20+R23+R26+R29+R32+R35+R41+R38+R44+R47+R50+R53+R56+R59+R62+R65+R68+R71+R74+R77+R80+R101+R104+R107+R110+R113+R116+R119+R122+R125+R128+R131+R134+R137+R140+R143+R146+R149+R152+R155+R158+R161+R164+R167+R170+R173+R176+R179+R182+R185+R188+R191+R194+R197+R209+R212+R215+R218+R221+R224+R227+R230+R233+R236+R239+R242+R245+R248+R251+R254+R257+R260+R263+R266+R269+R272 -> 14 | T5: =T11+T83+T86+T89+T92+T95+T98+T200+T203+T206+T14+T17+T20+T23+T26+T29+T32+T35+T41+T38+T44+T47+T50+T53+T56+T59+T62+T65+T68+T71+T74+T77+T80+T101+T104+T107+T110+T113+T116+T119+T122+T125+T128+T131+T134+T137+T140+T143+T146+T149+T152+T155+T158+T161+T164+T167+T170+T173+T176+T179+T182+T185+T188+T191+T194+T197+T209+T212+T215+T218+T221+T224+T227+T230+T233+T236+T239+T242+T245+T248+T251+T254+T257+T260+T263+T266+T269+T272 -> 0 | U5: =U11+U83+U86+U89+U92+U95+U98+U200+U203+U206+U14+U17+U20+U23+U26+U29+U32+U35+U41+U38+U44+U47+U50+U53+U56+U59+U62+U65+U68+U71+U74+U77+U80+U101+U104+U107+U110+U113+U116+U119+U122+U125+U128+U131+U134+U137+U140+U143+U146+U149+U152+U155+U158+U161+U164+U167+U170+U173+U176+U179+U182+U185+U188+U191+U194+U197+U209+U212+U215+U218+U221+U224+U227+U230+U233+U236+U239+U242+U245+U248+U251+U254+U257+U260+U263+U266+U269+U272 -> 0 | W5: =W11+W83+W86+W89+W92+W95+W98+W200+W203+W206+W14+W17+W20+W23+W26+W29+W32+W35+W41+W38+W44+W47+W50+W53+W56+W59+W62+W65+W68+W71+W74+W77+W80+W101+W104+W107+W110+W113+W116+W119+W122+W125+W128+W131+W134+W137+W140+W143+W146+W149+W152+W155+W158+W161+W164+W167+W170+W173+W176+W179+W182+W185+W188+W191+W194+W197+W209+W212+W215+W218+W221+W224+W227+W230+W233+W236+W239+W242+W245+W248+W251+W254+W257+W260+W263+W266+W269+W272 -> 0 | X5: =X11+X83+X86+X89+X92+X95+X98+X200+X203+X206+X14+X17+X20+X23+X26+X29+X32+X35+X41+X38+X44+X47+X50+X53+X56+X59+X62+X65+X68+X71+X74+X77+X80+X101+X104+X107+X110+X113+X116+X119+X122+X125+X128+X131+X134+X137+X140+X143+X146+X149+X152+X155+X158+X161+X164+X167+X170+X173+X176+X179+X182+X185+X188+X191+X194+X197+X209+X212+X215+X218+X221+X224+X227+X230+X233+X236+X239+X242+X245+X248+X251+X254+X257+X260+X263+X266+X269+X272 -> 0
H6: =H12+H84+H87+H90+H93+H96+H99+H201+H204+H207+H15+H18+H21+H24+H27+H30+H33+H36+H42+H39+H45+H48+H51+H54+H57+H60+H63+H66+H69+H72+H75+H78+H81+H102+H105+H108+H111+H114+H117+H120+H123+H126+H129+H132+H135+H138+H141+H144+H147+H150+H153+H156+H159+H162+H165+H168+H171+H174+H177+H180+H183+H186+H189+H192+H195+H198+H210+H213+H216+H219+H222+H225+H228+H231+H234+H237+H240+H243+H246+H249+H252+H255+H258+H261+H264+H267+H270+H273 -> 41 | I6: =I12+I84+I87+I90+I93+I96+I99+I201+I204+I207+I15+I18+I21+I24+I27+I30+I33+I36+I42+I39+I45+I48+I51+I54+I57+I60+I63+I66+I69+I72+I75+I78+I81+I102+I105+I108+I111+I114+I117+I120+I123+I126+I129+I132+I135+I138+I141+I144+I147+I150+I153+I156+I159+I162+I165+I168+I171+I174+I177+I180+I183+I186+I189+I192+I195+I198+I210+I213+I216+I219+I222+I225+I228+I231+I234+I237+I240+I243+I246+I249+I252+I255+I258+I261+I264+I267+I270+I273 -> 41 | K6: =K12+K84+K87+K90+K93+K96+K99+K201+K204+K207+K15+K18+K21+K24+K27+K30+K33+K36+K42+K39+K45+K48+K51+K54+K57+K60+K63+K66+K69+K72+K75+K78+K81+K102+K105+K108+K111+K114+K117+K120+K123+K126+K129+K132+K135+K138+K141+K144+K147+K150+K153+K156+K159+K162+K165+K168+K171+K174+K177+K180+K183+K186+K189+K192+K195+K198+K210+K213+K216+K219+K222+K225+K228+K231+K234+K237+K240+K243+K246+K249+K252+K255+K258+K261+K264+K267+K270+K273 -> 43 | L6: =L12+L84+L87+L90+L93+L96+L99+L201+L204+L207+L15+L18+L21+L24+L27+L30+L33+L36+L42+L39+L45+L48+L51+L54+L57+L60+L63+L66+L69+L72+L75+L78+L81+L102+L105+L108+L111+L114+L117+L120+L123+L126+L129+L132+L135+L138+L141+L144+L147+L150+L153+L156+L159+L162+L165+L168+L171+L174+L177+L180+L183+L186+L189+L192+L195+L198+L210+L213+L216+L219+L222+L225+L228+L231+L234+L237+L240+L243+L246+L249+L252+L255+L258+L261+L264+L267+L270+L273 -> 40 | N6: =N12+N84+N87+N90+N93+N96+N99+N201+N204+N207+N15+N18+N21+N24+N27+N30+N33+N36+N42+N39+N45+N48+N51+N54+N57+N60+N63+N66+N69+N72+N75+N78+N81+N102+N105+N108+N111+N114+N117+N120+N123+N126+N129+N132+N135+N138+N141+N144+N147+N150+N153+N156+N159+N162+N165+N168+N171+N174+N177+N180+N183+N186+N189+N192+N195+N198+N210+N213+N216+N219+N222+N225+N228+N231+N234+N237+N240+N243+N246+N249+N252+N255+N258+N261+N264+N267+N270+N273 -> 40 | O6: =O12+O84+O87+O90+O93+O96+O99+O201+O204+O207+O15+O18+O21+O24+O27+O30+O33+O36+O42+O39+O45+O48+O51+O54+O57+O60+O63+O66+O69+O72+O75+O78+O81+O102+O105+O108+O111+O114+O117+O120+O123+O126+O129+O132+O135+O138+O141+O144+O147+O150+O153+O156+O159+O162+O165+O168+O171+O174+O177+O180+O183+O186+O189+O192+O195+O198+O210+O213+O216+O219+O222+O225+O228+O231+O234+O237+O240+O243+O246+O249+O252+O255+O258+O261+O264+O267+O270+O273 -> 39 | Q6: =Q12+Q84+Q87+Q90+Q93+Q96+Q99+Q201+Q204+Q207+Q15+Q18+Q21+Q24+Q27+Q30+Q33+Q36+Q42+Q39+Q45+Q48+Q51+Q54+Q57+Q60+Q63+Q66+Q69+Q72+Q75+Q78+Q81+Q102+Q105+Q108+Q111+Q114+Q117+Q120+Q123+Q126+Q129+Q132+Q135+Q138+Q141+Q144+Q147+Q150+Q153+Q156+Q159+Q162+Q165+Q168+Q171+Q174+Q177+Q180+Q183+Q186+Q189+Q192+Q195+Q198+Q210+Q213+Q216+Q219+Q222+Q225+Q228+Q231+Q234+Q237+Q240+Q243+Q246+Q249+Q252+Q255+Q258+Q261+Q264+Q267+Q270+Q273 -> 14 | R6: =R12+R84+R87+R90+R93+R96+R99+R201+R204+R207+R15+R18+R21+R24+R27+R30+R33+R36+R42+R39+R45+R48+R51+R54+R57+R60+R63+R66+R69+R72+R75+R78+R81+R102+R105+R108+R111+R114+R117+R120+R123+R126+R129+R132+R135+R138+R141+R144+R147+R150+R153+R156+R159+R162+R165+R168+R171+R174+R177+R180+R183+R186+R189+R192+R195+R198+R210+R213+R216+R219+R222+R225+R228+R231+R234+R237+R240+R243+R246+R249+R252+R255+R258+R261+R264+R267+R270+R273 -> 11 | T6: =T12+T84+T87+T90+T93+T96+T99+T201+T204+T207+T15+T18+T21+T24+T27+T30+T33+T36+T42+T39+T45+T48+T51+T54+T57+T60+T63+T66+T69+T72+T75+T78+T81+T102+T105+T108+T111+T114+T117+T120+T123+T126+T129+T132+T135+T138+T141+T144+T147+T150+T153+T156+T159+T162+T165+T168+T171+T174+T177+T180+T183+T186+T189+T192+T195+T198+T210+T213+T216+T219+T222+T225+T228+T231+T234+T237+T240+T243+T246+T249+T252+T255+T258+T261+T264+T267+T270+T273 -> 0 | U6: =U12+U84+U87+U90+U93+U96+U99+U201+U204+U207+U15+U18+U21+U24+U27+U30+U33+U36+U42+U39+U45+U48+U51+U54+U57+U60+U63+U66+U69+U72+U75+U78+U81+U102+U105+U108+U111+U114+U117+U120+U123+U126+U129+U132+U135+U138+U141+U144+U147+U150+U153+U156+U159+U162+U165+U168+U171+U174+U177+U180+U183+U186+U189+U192+U195+U198+U210+U213+U216+U219+U222+U225+U228+U231+U234+U237+U240+U243+U246+U249+U252+U255+U258+U261+U264+U267+U270+U273 -> 0 | W6: =W12+W84+W87+W90+W93+W96+W99+W201+W204+W207+W15+W18+W21+W24+W27+W30+W33+W36+W42+W39+W45+W48+W51+W54+W57+W60+W63+W66+W69+W72+W75+W78+W81+W102+W105+W108+W111+W114+W117+W120+W123+W126+W129+W132+W135+W138+W141+W144+W147+W150+W153+W156+W159+W162+W165+W168+W171+W174+W177+W180+W183+W186+W189+W192+W195+W198+W210+W213+W216+W219+W222+W225+W228+W231+W234+W237+W240+W243+W246+W249+W252+W255+W258+W261+W264+W267+W270+W273 -> 0 | X6: =X12+X84+X87+X90+X93+X96+X99+X201+X204+X207+X15+X18+X21+X24+X27+X30+X33+X36+X42+X39+X45+X48+X51+X54+X57+X60+X63+X66+X69+X72+X75+X78+X81+X102+X105+X108+X111+X114+X117+X120+X123+X126+X129+X132+X135+X138+X141+X144+X147+X150+X153+X156+X159+X162+X165+X168+X171+X174+X177+X180+X183+X186+X189+X192+X195+X198+X210+X213+X216+X219+X222+X225+X228+X231+X234+X237+X240+X243+X246+X249+X252+X255+X258+X261+X264+X267+X270+X273 -> 0
D8: ----------------------------------------------------------------------------------------------------------------------------------------------------------------------> | H8: =H5+I5+H6+I6 -> 164 | I8: Pontos | K8: =K5+L5+K6+L6 -> 175 | L8: Pontos | N8: =N5+O5+N6+O6 -> 169 | O8: Pontos | Q8: =Q5+R5+Q6+R6 -> 53 | R8: Pontos | T8: =T5+U5+T6+U6 -> 0 | U8: Pontos | W8: =W5+X5+W6+X6 -> 0 | X8: Pontos
Z9: Semáforo | AC9: Legenda:
B11: Faturamento | D11: Emissão de NF de venda (NF-e) | F11: Diario | H11: 1 | I11: 1 | K11: 1 | L11: 1 | N11: 1 | O11: 1 | Q11: 1 | R11: 1 | Z11: =H11+K11+N11+Q11+T11+W11 -> 4 | AA11: =I11+L11+O11+R11+U11+X11 -> 4 | AD11: Aprendendo | AE11: 1
H12: 1 | I12: 1 | K12: 1 | L12: 1 | N12: 1 | O12: 1 | Q12: 1 | R12: 1 | Z12: =H12+K12+N12+Q12+T12+W12 -> 4 | AA12: =I12+L12+O12+R12+U12+X12 -> 4
B14: Faturamento | D14: Emissão de NF de exportação (NF-e) | F14: Diario | H14: 1 | I14: 1 | K14: 1 | L14: 1 | N14: 1 | O14: 1 | Z14: =H14+K14+N14+Q14+T14+W14 -> 3 | AA14: =I14+L14+O14+R14+U14+X14 -> 3 | AC14: Consegue fazer | AD14: com ajuda | AE14: 1
H15: 1 | I15: 1 | K15: 1 | L15: 1 | N15: 1 | O15: 1 | Z15: =H15+K15+N15+Q15+T15+W15 -> 3 | AA15: =I15+L15+O15+R15+U15+X15 -> 3 | AE15: 1
B17: Faturamento | D17: Emissão de NF de importação (NF-e) | F17: Diario | H17: 1 | I17: 1 | K17: 1 | L17: 1 | N17: 1 | O17: 1 | Z17: =H17+K17+N17+Q17+T17+W17 -> 3 | AA17: =I17+L17+O17+R17+U17+X17 -> 3 | AC17: Consegue fazer | AD17: sem ajuda | AE17: 1 | AF17: 1
H18: 1 | I18: 1 | K18: 1 | L18: 1 | N18: 1 | O18: 1 | Z18: =H18+K18+N18+Q18+T18+W18 -> 3 | AA18: =I18+L18+O18+R18+U18+X18 -> 3 | AC18: (Sei fazer, mas não sei porque faço) | AE18: 1
B20: Faturamento | D20: Emissão de NF de comodato (NF-e) | F20: Diario | H20: 1 | I20: 1 | K20: 1 | L20: 1 | N20: 1 | O20: 1 | Q20: 1 | R20: 1 | Z20: =H20+K20+N20+Q20+T20+W20 -> 4 | AA20: =I20+L20+O20+R20+U20+X20 -> 4 | AC20: Consegue fazer | AD20: e ensinar | AE20: 1 | AF20: 1
H21: 1 | I21: 1 | K21: 1 | L21: 1 | N21: 1 | O21: 1 | Q21: 1 | R21: 1 | Z21: =H21+K21+N21+Q21+T21+W21 -> 4 | AA21: =I21+L21+O21+R21+U21+X21 -> 4 | AC21: (Sei fazer, e sei porque faço) | AE21: 1 | AF21: 1
B23: Faturamento | D23: Emissão de NF de bonificação ou brinde (NF-e) | F23: Diario | H23: 1 | I23: 1 | K23: 1 | L23: 1 | N23: 1 | O23: 1 | Q23: 1 | R23: 1 | Z23: =H23+K23+N23+Q23+T23+W23 -> 4 | AA23: =I23+L23+O23+R23+U23+X23 -> 4
H24: 1 | I24: 1 | K24: 1 | L24: 1 | N24: 1 | O24: 1 | Q24: 1 | R24: 1 | Z24: =H24+K24+N24+Q24+T24+W24 -> 4 | AA24: =I24+L24+O24+R24+U24+X24 -> 4
B26: Faturamento | D26: Emissão de NF de demonstração (NF-e) | F26: Diario | H26: 1 | I26: 1 | K26: 1 | L26: 1 | N26: 1 | O26: 1 | Q26: 1 | R26: 1 | Z26: =H26+K26+N26+Q26+T26+W26 -> 4 | AA26: =I26+L26+O26+R26+U26+X26 -> 4
H27: 1 | I27: 1 | K27: 1 | L27: 1 | N27: 1 | O27: 1 | Q27: 1 | R27: 1 | Z27: =H27+K27+N27+Q27+T27+W27 -> 4 | AA27: =I27+L27+O27+R27+U27+X27 -> 4
B29: Faturamento | D29: Emissão de NF de troca em garantia (NF-e) | F29: Diario | H29: 1 | I29: 1 | K29: 1 | L29: 1 | N29: 1 | O29: 1 | Q29: 1 | R29: 1 | Z29: =H29+K29+N29+Q29+T29+W29 -> 4 | AA29: =I29+L29+O29+R29+U29+X29 -> 4
H30: 1 | I30: 1 | K30: 1 | L30: 1 | N30: 1 | O30: 1 | Q30: 1 | R30: 1 | Z30: =H30+K30+N30+Q30+T30+W30 -> 4 | AA30: =I30+L30+O30+R30+U30+X30 -> 4
B32: Faturamento | D32: Emissão de NF de industrialização (NF-e) | F32: Diario | H32: 1 | I32: 1 | K32: 1 | L32: 1 | N32: 1 | O32: 1 | Z32: =H32+K32+N32+Q32+T32+W32 -> 3 | AA32: =I32+L32+O32+R32+U32+X32 -> 3
H33: 1 | I33: 1 | K33: 1 | L33: 1 | N33: 1 | O33: 1 | Z33: =H33+K33+N33+Q33+T33+W33 -> 3 | AA33: =I33+L33+O33+R33+U33+X33 -> 3
B35: Faturamento | D35: Emissão de NF de serviço (NFS-e) | F35: Diario | H35: 1 | I35: 1 | K35: 1 | L35: 1 | N35: 1 | O35: 1 | Z35: =H35+K35+N35+Q35+T35+W35 -> 3 | AA35: =I35+L35+O35+R35+U35+X35 -> 3
H36: 1 | I36: 1 | K36: 1 | N36: 1 | O36: 1 | Z36: =H36+K36+N36+Q36+T36+W36 -> 3 | AA36: =I36+L36+O36+R36+U36+X36 -> 2
B38: Faturamento | D38: Emissão de NF de débito (ND) | F38: Diario | H38: 1 | I38: 1 | K38: 1 | L38: 1 | N38: 1 | O38: 1 | Z38: =H38+K38+N38+Q38+T38+W38 -> 3 | AA38: =I38+L38+O38+R38+U38+X38 -> 3
H39: 1 | I39: 1 | K39: 1 | N39: 1 | O39: 1 | Z39: =H39+K39+N39+Q39+T39+W39 -> 3 | AA39: =I39+L39+O39+R39+U39+X39 -> 2
B41: Faturamento | D41: Emissão de NF complementar de ICMS (NF-e) | F41: Diario | H41: 1 | I41: 1 | K41: 1 | L41: 1 | N41: 1 | O41: 1 | Z41: =H41+K41+N41+Q41+T41+W41 -> 3 | AA41: =I41+L41+O41+R41+U41+X41 -> 3
H42: 1 | I42: 1 | K42: 1 | L42: 1 | Z42: =H42+K42+N42+Q42+T42+W42 -> 2 | AA42: =I42+L42+O42+R42+U42+X42 -> 2
B44: Faturamento | D44: Emissão e/ou lançamento de NF de devolução de venda | F44: Diario | H44: 1 | I44: 1 | K44: 1 | L44: 1 | N44: 1 | O44: 1 | Q44: 1 | R44: 1 | Z44: =H44+K44+N44+Q44+T44+W44 -> 4 | AA44: =I44+L44+O44+R44+U44+X44 -> 4
H45: 1 | I45: 1 | K45: 1 | L45: 1 | N45: 1 | O45: 1 | Q45: 1 | R45: 1 | Z45: =H45+K45+N45+Q45+T45+W45 -> 4 | AA45: =I45+L45+O45+R45+U45+X45 -> 4
B47: Faturamento | D47: Emissão e/ou lançamento de NF de retorno de comodato | F47: Diario | H47: 1 | I47: 1 | K47: 1 | L47: 1 | N47: 1 | O47: 1 | Q47: 1 | R47: 1 | Z47: =H47+K47+N47+Q47+T47+W47 -> 4 | AA47: =I47+L47+O47+R47+U47+X47 -> 4
H48: 1 | I48: 1 | K48: 1 | L48: 1 | N48: 1 | O48: 1 | Q48: 1 | R48: 1 | Z48: =H48+K48+N48+Q48+T48+W48 -> 4 | AA48: =I48+L48+O48+R48+U48+X48 -> 4
B50: Faturamento | D50: Emissão e/ou lançamento de NF de retorno de demonstração | F50: Diario | H50: 1 | I50: 1 | K50: 1 | L50: 1 | N50: 1 | O50: 1 | Q50: 1 | R50: 1 | Z50: =H50+K50+N50+Q50+T50+W50 -> 4 | AA50: =I50+L50+O50+R50+U50+X50 -> 4
H51: 1 | I51: 1 | K51: 1 | L51: 1 | N51: 1 | O51: 1 | Q51: 1 | R51: 1 | Z51: =H51+K51+N51+Q51+T51+W51 -> 4 | AA51: =I51+L51+O51+R51+U51+X51 -> 4
B53: Faturamento | D53: Emissão e/ou lançamento de NF de retorno de industrialização | F53: Diario | H53: 1 | I53: 1 | K53: 1 | L53: 1 | N53: 1 | O53: 1 | Z53: =H53+K53+N53+Q53+T53+W53 -> 3 | AA53: =I53+L53+O53+R53+U53+X53 -> 3
H54: 1 | I54: 1 | K54: 1 | L54: 1 | N54: 1 | O54: 1 | Z54: =H54+K54+N54+Q54+T54+W54 -> 3 | AA54: =I54+L54+O54+R54+U54+X54 -> 3
B56: Faturamento | D56: Emissão e/ou lançamento de NF de troca em garantia | F56: Diario | H56: 1 | I56: 1 | K56: 1 | L56: 1 | N56: 1 | O56: 1 | Q56: 1 | R56: 1 | Z56: =H56+K56+N56+Q56+T56+W56 -> 4 | AA56: =I56+L56+O56+R56+U56+X56 -> 4
H57: 1 | I57: 1 | K57: 1 | L57: 1 | N57: 1 | O57: 1 | Q57: 1 | R57: 1 | Z57: =H57+K57+N57+Q57+T57+W57 -> 4 | AA57: =I57+L57+O57+R57+U57+X57 -> 4
B59: Faturamento | D59: Análise e/ou criação de cadastros de clientes e fornecedores no sistema SAP | F59: Diario | H59: 1 | I59: 1 | K59: 1 | L59: 1 | N59: 1 | O59: 1 | Q59: 1 | R59: 1 | Z59: =H59+K59+N59+Q59+T59+W59 -> 4 | AA59: =I59+L59+O59+R59+U59+X59 -> 4
H60: 1 | I60: 1 | K60: 1 | L60: 1 | N60: 1 | O60: 1 | Q60: 1 | R60: 1 | Z60: =H60+K60+N60+Q60+T60+W60 -> 4 | AA60: =I60+L60+O60+R60+U60+X60 -> 4
B62: Faturamento | D62: Análise de possível emissão de guia DIFAL (diferencial de alíquotas) | F62: Diario | H62: 1 | I62: 1 | K62: 1 | L62: 1 | N62: 1 | O62: 1 | Z62: =H62+K62+N62+Q62+T62+W62 -> 3 | AA62: =I62+L62+O62+R62+U62+X62 -> 3
H63: 1 | I63: 1 | K63: 1 | L63: 1 | Z63: =H63+K63+N63+Q63+T63+W63 -> 2 | AA63: =I63+L63+O63+R63+U63+X63 -> 2
B65: Faturamento | D65: Confirmação de pagamento dos pedidos de venda com acesso ao banco Itaú | F65: Diario | H65: 1 | I65: 1 | Z65: =H65+K65+N65+Q65+T65+W65 -> 1 | AA65: =I65+L65+O65+R65+U65+X65 -> 1
H66: 1 | I66: 1 | Z66: =H66+K66+N66+Q66+T66+W66 -> 1 | AA66: =I66+L66+O66+R66+U66+X66 -> 1
B68: Faturamento | D68: Emissão de fatura de adiantamento no pedido de venda | F68: Diario | H68: 1 | I68: 1 | N68: 1 | O68: 1 | Z68: =H68+K68+N68+Q68+T68+W68 -> 2 | AA68: =I68+L68+O68+R68+U68+X68 -> 2
H69: 1 | I69: 1 | N69: 1 | O69: 1 | Z69: =H69+K69+N69+Q69+T69+W69 -> 2 | AA69: =I69+L69+O69+R69+U69+X69 -> 2
B71: Faturamento | D71: Controle das mensalidades de locação na planilha Excel junto com o sistema SAP | F71: Diario | H71: 1 | I71: 1 | K71: 1 | L71: 1 | N71: 1 | O71: 1 | Z71: =H71+K71+N71+Q71+T71+W71 -> 3 | AA71: =I71+L71+O71+R71+U71+X71 -> 3
H72: 1 | I72: 1 | K72: 1 | L72: 1 | N72: 1 | O72: 1 | Z72: =H72+K72+N72+Q72+T72+W72 -> 3 | AA72: =I72+L72+O72+R72+U72+X72 -> 3
B74: Faturamento | D74: Envio manual via e-mail das notas de débito e boletos para o respectivos clientes | F74: Diario | H74: 1 | I74: 1 | K74: 1 | L74: 1 | N74: 1 | O74: 1 | Q74: 1 | R74: 1 | Z74: =H74+K74+N74+Q74+T74+W74 -> 4 | AA74: =I74+L74+O74+R74+U74+X74 -> 4
H75: 1 | I75: 1 | K75: 1 | L75: 1 | N75: 1 | O75: 1 | Q75: 1 | R75: 1 | Z75: =H75+K75+N75+Q75+T75+W75 -> 4 | AA75: =I75+L75+O75+R75+U75+X75 -> 4
B77: Faturamento | D77: Análise e controle das mensalidades de manuntenção de equipamentos, para a posterior emissão de NFS-e | F77: Diario | H77: 1 | I77: 1 | N77: 1 | O77: 1 | Z77: =H77+K77+N77+Q77+T77+W77 -> 2 | AA77: =I77+L77+O77+R77+U77+X77 -> 2
H78: 1 | I78: 1 | N78: 1 | O78: 1 | Z78: =H78+K78+N78+Q78+T78+W78 -> 2 | AA78: =I78+L78+O78+R78+U78+X78 -> 2
B80: Faturamento | D80: Análise de novos contratos de locação novos / Planilhamento / cadastro no SAP, emissão das notas de débito (ND) | F80: Diario | H80: 1 | I80: 1 | K80: 1 | L80: 1 | N80: 1 | O80: 1 | Z80: =H80+K80+N80+Q80+T80+W80 -> 3 | AA80: =I80+L80+O80+R80+U80+X80 -> 3
H81: 1 | I81: 1 | N81: 1 | O81: 1 | Z81: =H81+K81+N81+Q81+T81+W81 -> 2 | AA81: =I81+L81+O81+R81+U81+X81 -> 2
B83: Faturamento | D83: Análise de contratos de locação em andamento | F83: Diario | H83: 1 | I83: 1 | K83: 1 | L83: 1 | N83: 1 | O83: 1 | Z83: =H83+K83+N83+Q83+T83+W83 -> 3 | AA83: =I83+L83+O83+R83+U83+X83 -> 3
H84: 1 | I84: 1 | N84: 1 | O84: 1 | Z84: =H84+K84+N84+Q84+T84+W84 -> 2 | AA84: =I84+L84+O84+R84+U84+X84 -> 2
B86: Faturamento | D86: Análise de possíveis reajuste contratuais nas parcelas dos contratos de locação/manuntenção | F86: Diario | H86: 1 | I86: 1 | N86: 1 | O86: 1 | Z86: =H86+K86+N86+Q86+T86+W86 -> 2 | AA86: =I86+L86+O86+R86+U86+X86 -> 2
H87: 1 | I87: 1 | N87: 1 | O87: 1 | Z87: =H87+K87+N87+Q87+T87+W87 -> 2 | AA87: =I87+L87+O87+R87+U87+X87 -> 2
B89: Faturamento | D89: Controle de retorno de comodato da Geneslab / emissão NF de venda | F89: Diario | H89: 1 | I89: 1 | N89: 1 | O89: 1 | Z89: =H89+K89+N89+Q89+T89+W89 -> 2 | AA89: =I89+L89+O89+R89+U89+X89 -> 2
H90: 1 | I90: 1 | N90: 1 | O90: 1 | Z90: =H90+K90+N90+Q90+T90+W90 -> 2 | AA90: =I90+L90+O90+R90+U90+X90 -> 2
B92: Faturamento | D92: Suporte e Orientações aos setores (help desk, comercial, adequação, almoxarifado) | F92: Diario | H92: 1 | I92: 1 | K92: 1 | L92: 1 | N92: 1 | O92: 1 | Q92: 1 | R92: 1 | Z92: =H92+K92+N92+Q92+T92+W92 -> 4 | AA92: =I92+L92+O92+R92+U92+X92 -> 4
H93: 1 | I93: 1 | K93: 1 | L93: 1 | N93: 1 | O93: 1 | Q93: 1 | Z93: =H93+K93+N93+Q93+T93+W93 -> 4 | AA93: =I93+L93+O93+R93+U93+X93 -> 3
B95: Faturamento | D95: Resolução de problemas e/ou dúvidas de clientes, via e-mail, telefone, whatsapp | F95: Diario | H95: 1 | I95: 1 | K95: 1 | L95: 1 | N95: 1 | O95: 1 | Q95: 1 | R95: 1 | Z95: =H95+K95+N95+Q95+T95+W95 -> 4 | AA95: =I95+L95+O95+R95+U95+X95 -> 4
H96: 1 | I96: 1 | K96: 1 | L96: 1 | N96: 1 | O96: 1 | Q96: 1 | Z96: =H96+K96+N96+Q96+T96+W96 -> 4 | AA96: =I96+L96+O96+R96+U96+X96 -> 3
B98: Faturamento | D98: Análise de impostos e tributações das operações em geral | F98: Diario | H98: 1 | I98: 1 | K98: 1 | L98: 1 | N98: 1 | O98: 1 | Z98: =H98+K98+N98+Q98+T98+W98 -> 3 | AA98: =I98+L98+O98+R98+U98+X98 -> 3
H99: 1 | I99: 1 | K99: 1 | L99: 1 | Z99: =H99+K99+N99+Q99+T99+W99 -> 2 | AA99: =I99+L99+O99+R99+U99+X99 -> 2
B101: Recebimento | D101: Lançamento de notas com pedido de compra | F101: Diario | K101: 1 | L101: 1 | N101: 1 | O101: 1 | Z101: =H101+K101+N101+Q101+T101+W101 -> 2 | AA101: =I101+L101+O101+R101+U101+X101 -> 2
K102: 1 | L102: 1 | N102: 1 | O102: 1 | Z102: =H102+K102+N102+Q102+T102+W102 -> 2 | AA102: =I102+L102+O102+R102+U102+X102 -> 2
B104: Recebimento | D104: Lançamento de notas recorrentes | F104: Diario | K104: 1 | L104: 1 | N104: 1 | O104: 1 | Z104: =H104+K104+N104+Q104+T104+W104 -> 2 | AA104: =I104+L104+O104+R104+U104+X104 -> 2
K105: 1 | L105: 1 | N105: 1 | O105: 1 | Z105: =H105+K105+N105+Q105+T105+W105 -> 2 | AA105: =I105+L105+O105+R105+U105+X105 -> 2
B107: Recebimento | D107: Lançamentos de guias e impostos (LCM) | F107: Diario | K107: 1 | L107: 1 | N107: 1 | O107: 1 | Z107: =H107+K107+N107+Q107+T107+W107 -> 2 | AA107: =I107+L107+O107+R107+U107+X107 -> 2
K108: 1 | L108: 1 | N108: 1 | O108: 1 | Z108: =H108+K108+N108+Q108+T108+W108 -> 2 | AA108: =I108+L108+O108+R108+U108+X108 -> 2
B110: Recebimento | D110: Lançamento da folha de pagamento | F110: Mensal | K110: 1 | L110: 1 | N110: 1 | O110: 1 | Z110: =H110+K110+N110+Q110+T110+W110 -> 2 | AA110: =I110+L110+O110+R110+U110+X110 -> 2
K111: 1 | L111: 1 | N111: 1 | O111: 1 | Z111: =H111+K111+N111+Q111+T111+W111 -> 2 | AA111: =I111+L111+O111+R111+U111+X111 -> 2
B113: Recebimento | D113: Controle de notas de entrada | F113: Diario | K113: 1 | L113: 1 | N113: 1 | O113: 1 | Q113: 1 | R113: 1 | Z113: =H113+K113+N113+Q113+T113+W113 -> 3 | AA113: =I113+L113+O113+R113+U113+X113 -> 3
K114: 1 | L114: 1 | N114: 1 | O114: 1 | Q114: 1 | Z114: =H114+K114+N114+Q114+T114+W114 -> 3 | AA114: =I114+L114+O114+R114+U114+X114 -> 2
B116: Recebimento | D116: Lançamento de fatura de cartão de crédito | F116: Mensal | K116: 1 | L116: 1 | N116: 1 | O116: 1 | Z116: =H116+K116+N116+Q116+T116+W116 -> 2 | AA116: =I116+L116+O116+R116+U116+X116 -> 2
K117: 1 | L117: 1 | N117: 1 | O117: 1 | Z117: =H117+K117+N117+Q117+T117+W117 -> 2 | AA117: =I117+L117+O117+R117+U117+X117 -> 2
B119: Recebimento | D119: Abertura de pedidos recorrentes | F119: Diario | K119: 1 | L119: 1 | N119: 1 | O119: 1 | Z119: =H119+K119+N119+Q119+T119+W119 -> 2 | AA119: =I119+L119+O119+R119+U119+X119 -> 2
K120: 1 | L120: 1 | N120: 1 | O120: 1 | Z120: =H120+K120+N120+Q120+T120+W120 -> 2 | AA120: =I120+L120+O120+R120+U120+X120 -> 2
B122: Recebimento | D122: Fatura de adiantamento para fornecedor | F122: Diario | K122: 1 | L122: 1 | N122: 1 | O122: 1 | Z122: =H122+K122+N122+Q122+T122+W122 -> 2 | AA122: =I122+L122+O122+R122+U122+X122 -> 2
K123: 1 | L123: 1 | N123: 1 | O123: 1 | Z123: =H123+K123+N123+Q123+T123+W123 -> 2 | AA123: =I123+L123+O123+R123+U123+X123 -> 2
B125: Recebimento | D125: Importar arquivos XML de saídas para o Arquivei | F125: Diario | N125: 1 | O125: 1 | Z125: =H125+K125+N125+Q125+T125+W125 -> 1 | AA125: =I125+L125+O125+R125+U125+X125 -> 1
N126: 1 | O126: 1 | Z126: =H126+K126+N126+Q126+T126+W126 -> 1 | AA126: =I126+L126+O126+R126+U126+X126 -> 1
B128: Recebimento | D128: Envio de documentos à contabilidade externa | F128: Mensal | K128: 1 | L128: 1 | N128: 1 | O128: 1 | Z128: =H128+K128+N128+Q128+T128+W128 -> 2 | AA128: =I128+L128+O128+R128+U128+X128 -> 2
N129: 1 | O129: 1 | Z129: =H129+K129+N129+Q129+T129+W129 -> 1 | AA129: =I129+L129+O129+R129+U129+X129 -> 1
B131: Recebimento | D131: Efetivar lançamentos de impostos em débito automático | F131: Mensal | N131: 1 | O131: 1 | Z131: =H131+K131+N131+Q131+T131+W131 -> 1 | AA131: =I131+L131+O131+R131+U131+X131 -> 1
N132: 1 | O132: 1 | Z132: =H132+K132+N132+Q132+T132+W132 -> 1 | AA132: =I132+L132+O132+R132+U132+X132 -> 1
B134: Recebimento | D134: Lançamento de Cte | F134: Diario | N134: 1 | O134: 1 | Z134: =H134+K134+N134+Q134+T134+W134 -> 1 | AA134: =I134+L134+O134+R134+U134+X134 -> 1
N135: 1 | O135: 1 | Z135: =H135+K135+N135+Q135+T135+W135 -> 1 | AA135: =I135+L135+O135+R135+U135+X135 -> 1
B137: Recebimento | D137: Lançamento de multas de trânsito | F137: Diario | N137: 1 | O137: 1 | Z137: =H137+K137+N137+Q137+T137+W137 -> 1 | AA137: =I137+L137+O137+R137+U137+X137 -> 1
N138: 1 | O138: 1 | Z138: =H138+K138+N138+Q138+T138+W138 -> 1 | AA138: =I138+L138+O138+R138+U138+X138 -> 1
B140: Recebimento | D140: Lançamentos de Importação Simpificada (Courrier) | F140: Diario | N140: 1 | O140: 1 | Z140: =H140+K140+N140+Q140+T140+W140 -> 1 | AA140: =I140+L140+O140+R140+U140+X140 -> 1
Z141: =H141+K141+N141+Q141+T141+W141 -> 0 | AA141: =I141+L141+O141+R141+U141+X141 -> 0
B143: Recebimento | D143: Emissão de nota fiscal de Importação Simpificada (Courrier) | F143: Diario | K143: 1 | L143: 1 | N143: 1 | O143: 1 | Z143: =H143+K143+N143+Q143+T143+W143 -> 2 | AA143: =I143+L143+O143+R143+U143+X143 -> 2
K144: 1 | Z144: =H144+K144+N144+Q144+T144+W144 -> 1 | AA144: =I144+L144+O144+R144+U144+X144 -> 0
D146: ______________________________________________________________________________________________ | F146: ________ | Z146: =H146+K146+N146+Q146+T146+W146 -> 0 | AA146: =I146+L146+O146+R146+U146+X146 -> 0
Z147: =H147+K147+N147+Q147+T147+W147 -> 0 | AA147: =I147+L147+O147+R147+U147+X147 -> 0
D149: ______________________________________________________________________________________________ | F149: ________ | Z149: =H149+K149+N149+Q149+T149+W149 -> 0 | AA149: =I149+L149+O149+R149+U149+X149 -> 0
Z150: =H150+K150+N150+Q150+T150+W150 -> 0 | AA150: =I150+L150+O150+R150+U150+X150 -> 0
...

Sheet Abril 2026
B2: Setorização | D2: Tarefas | F2: Periodicidade | H2: Luis | K2: Alexandre | N2: Pamella | Q2: Loraine | T2: Maykon | W2: Bruno
H3: Gerente | K3: Supervisor
D5: Classificação do Colaborador | H5: =H11+H83+H86+H89+H92+H95+H98+H200+H203+H206+H14+H17+H20+H23+H26+H29+H32+H35+H41+H38+H44+H47+H50+H53+H56+H59+H62+H65+H68+H71+H74+H77+H80+H101+H104+H107+H110+H113+H116+H119+H122+H125+H128+H131+H134+H137+H140+H143+H146+H149+H152+H155+H158+H161+H164+H167+H170+H173+H176+H179+H182+H185+H188+H191+H194+H197+H209+H212+H215+H218+H221+H224+H227+H230+H233+H236+H239+H242+H245+H248+H251+H254+H257+H260+H263+H266+H269+H272 -> 41 | I5: =I11+I83+I86+I89+I92+I95+I98+I200+I203+I206+I14+I17+I20+I23+I26+I29+I32+I35+I41+I38+I44+I47+I50+I53+I56+I59+I62+I65+I68+I71+I74+I77+I80+I101+I104+I107+I110+I113+I116+I119+I122+I125+I128+I131+I134+I137+I140+I143+I146+I149+I152+I155+I158+I161+I164+I167+I170+I173+I176+I179+I182+I185+I188+I191+I194+I197+I209+I212+I215+I218+I221+I224+I227+I230+I233+I236+I239+I242+I245+I248+I251+I254+I257+I260+I263+I266+I269+I272 -> 41 | K5: =K11+K83+K86+K89+K92+K95+K98+K200+K203+K206+K14+K17+K20+K23+K26+K29+K32+K35+K41+K38+K44+K47+K50+K53+K56+K59+K62+K65+K68+K71+K74+K77+K80+K101+K104+K107+K110+K113+K116+K119+K122+K125+K128+K131+K134+K137+K140+K143+K146+K149+K152+K155+K158+K161+K164+K167+K170+K173+K176+K179+K182+K185+K188+K191+K194+K197+K209+K212+K215+K218+K221+K224+K227+K230+K233+K236+K239+K242+K245+K248+K251+K254+K257+K260+K263+K266+K269+K272 -> 52 | L5: =L11+L83+L86+L89+L92+L95+L98+L200+L203+L206+L14+L17+L20+L23+L26+L29+L32+L35+L41+L38+L44+L47+L50+L53+L56+L59+L62+L65+L68+L71+L74+L77+L80+L101+L104+L107+L110+L113+L116+L119+L122+L125+L128+L131+L134+L137+L140+L143+L146+L149+L152+L155+L158+L161+L164+L167+L170+L173+L176+L179+L182+L185+L188+L191+L194+L197+L209+L212+L215+L218+L221+L224+L227+L230+L233+L236+L239+L242+L245+L248+L251+L254+L257+L260+L263+L266+L269+L272 -> 52 | N5: =N11+N83+N86+N89+N92+N95+N98+N200+N203+N206+N14+N17+N20+N23+N26+N29+N32+N35+N41+N38+N44+N47+N50+N53+N56+N59+N62+N65+N68+N71+N74+N77+N80+N101+N104+N107+N110+N113+N116+N119+N122+N125+N128+N131+N134+N137+N140+N143+N146+N149+N152+N155+N158+N161+N164+N167+N170+N173+N176+N179+N182+N185+N188+N191+N194+N197+N209+N212+N215+N218+N221+N224+N227+N230+N233+N236+N239+N242+N245+N248+N251+N254+N257+N260+N263+N266+N269+N272 -> 53 | O5: =O11+O83+O86+O89+O92+O95+O98+O200+O203+O206+O14+O17+O20+O23+O26+O29+O32+O35+O41+O38+O44+O47+O50+O53+O56+O59+O62+O65+O68+O71+O74+O77+O80+O101+O104+O107+O110+O113+O116+O119+O122+O125+O128+O131+O134+O137+O140+O143+O146+O149+O152+O155+O158+O161+O164+O167+O170+O173+O176+O179+O182+O185+O188+O191+O194+O197+O209+O212+O215+O218+O221+O224+O227+O230+O233+O236+O239+O242+O245+O248+O251+O254+O257+O260+O263+O266+O269+O272 -> 53 | Q5: =Q11+Q83+Q86+Q89+Q92+Q95+Q98+Q200+Q203+Q206+Q14+Q17+Q20+Q23+Q26+Q29+Q32+Q35+Q41+Q38+Q44+Q47+Q50+Q53+Q56+Q59+Q62+Q65+Q68+Q71+Q74+Q77+Q80+Q101+Q104+Q107+Q110+Q113+Q116+Q119+Q122+Q125+Q128+Q131+Q134+Q137+Q140+Q143+Q146+Q149+Q152+Q155+Q158+Q161+Q164+Q167+Q170+Q173+Q176+Q179+Q182+Q185+Q188+Q191+Q194+Q197+Q209+Q212+Q215+Q218+Q221+Q224+Q227+Q230+Q233+Q236+Q239+Q242+Q245+Q248+Q251+Q254+Q257+Q260+Q263+Q266+Q269+Q272 -> 14 | R5: =R11+R83+R86+R89+R92+R95+R98+R200+R203+R206+R14+R17+R20+R23+R26+R29+R32+R35+R41+R38+R44+R47+R50+R53+R56+R59+R62+R65+R68+R71+R74+R77+R80+R101+R104+R107+R110+R113+R116+R119+R122+R125+R128+R131+R134+R137+R140+R143+R146+R149+R152+R155+R158+R161+R164+R167+R170+R173+R176+R179+R182+R185+R188+R191+R194+R197+R209+R212+R215+R218+R221+R224+R227+R230+R233+R236+R239+R242+R245+R248+R251+R254+R257+R260+R263+R266+R269+R272 -> 14 | T5: =T11+T83+T86+T89+T92+T95+T98+T200+T203+T206+T14+T17+T20+T23+T26+T29+T32+T35+T41+T38+T44+T47+T50+T53+T56+T59+T62+T65+T68+T71+T74+T77+T80+T101+T104+T107+T110+T113+T116+T119+T122+T125+T128+T131+T134+T137+T140+T143+T146+T149+T152+T155+T158+T161+T164+T167+T170+T173+T176+T179+T182+T185+T188+T191+T194+T197+T209+T212+T215+T218+T221+T224+T227+T230+T233+T236+T239+T242+T245+T248+T251+T254+T257+T260+T263+T266+T269+T272 -> 0 | U5: =U11+U83+U86+U89+U92+U95+U98+U200+U203+U206+U14+U17+U20+U23+U26+U29+U32+U35+U41+U38+U44+U47+U50+U53+U56+U59+U62+U65+U68+U71+U74+U77+U80+U101+U104+U107+U110+U113+U116+U119+U122+U125+U128+U131+U134+U137+U140+U143+U146+U149+U152+U155+U158+U161+U164+U167+U170+U173+U176+U179+U182+U185+U188+U191+U194+U197+U209+U212+U215+U218+U221+U224+U227+U230+U233+U236+U239+U242+U245+U248+U251+U254+U257+U260+U263+U266+U269+U272 -> 0 | W5: =W11+W83+W86+W89+W92+W95+W98+W200+W203+W206+W14+W17+W20+W23+W26+W29+W32+W35+W41+W38+W44+W47+W50+W53+W56+W59+W62+W65+W68+W71+W74+W77+W80+W101+W104+W107+W110+W113+W116+W119+W122+W125+W128+W131+W134+W137+W140+W143+W146+W149+W152+W155+W158+W161+W164+W167+W170+W173+W176+W179+W182+W185+W188+W191+W194+W197+W209+W212+W215+W218+W221+W224+W227+W230+W233+W236+W239+W242+W245+W248+W251+W254+W257+W260+W263+W266+W269+W272 -> 0 | X5: =X11+X83+X86+X89+X92+X95+X98+X200+X203+X206+X14+X17+X20+X23+X26+X29+X32+X35+X41+X38+X44+X47+X50+X53+X56+X59+X62+X65+X68+X71+X74+X77+X80+X101+X104+X107+X110+X113+X116+X119+X122+X125+X128+X131+X134+X137+X140+X143+X146+X149+X152+X155+X158+X161+X164+X167+X170+X173+X176+X179+X182+X185+X188+X191+X194+X197+X209+X212+X215+X218+X221+X224+X227+X230+X233+X236+X239+X242+X245+X248+X251+X254+X257+X260+X263+X266+X269+X272 -> 0
H6: =H12+H84+H87+H90+H93+H96+H99+H201+H204+H207+H15+H18+H21+H24+H27+H30+H33+H36+H42+H39+H45+H48+H51+H54+H57+H60+H63+H66+H69+H72+H75+H78+H81+H102+H105+H108+H111+H114+H117+H120+H123+H126+H129+H132+H135+H138+H141+H144+H147+H150+H153+H156+H159+H162+H165+H168+H171+H174+H177+H180+H183+H186+H189+H192+H195+H198+H210+H213+H216+H219+H222+H225+H228+H231+H234+H237+H240+H243+H246+H249+H252+H255+H258+H261+H264+H267+H270+H273 -> 41 | I6: =I12+I84+I87+I90+I93+I96+I99+I201+I204+I207+I15+I18+I21+I24+I27+I30+I33+I36+I42+I39+I45+I48+I51+I54+I57+I60+I63+I66+I69+I72+I75+I78+I81+I102+I105+I108+I111+I114+I117+I120+I123+I126+I129+I132+I135+I138+I141+I144+I147+I150+I153+I156+I159+I162+I165+I168+I171+I174+I177+I180+I183+I186+I189+I192+I195+I198+I210+I213+I216+I219+I222+I225+I228+I231+I234+I237+I240+I243+I246+I249+I252+I255+I258+I261+I264+I267+I270+I273 -> 41 | K6: =K12+K84+K87+K90+K93+K96+K99+K201+K204+K207+K15+K18+K21+K24+K27+K30+K33+K36+K42+K39+K45+K48+K51+K54+K57+K60+K63+K66+K69+K72+K75+K78+K81+K102+K105+K108+K111+K114+K117+K120+K123+K126+K129+K132+K135+K138+K141+K144+K147+K150+K153+K156+K159+K162+K165+K168+K171+K174+K177+K180+K183+K186+K189+K192+K195+K198+K210+K213+K216+K219+K222+K225+K228+K231+K234+K237+K240+K243+K246+K249+K252+K255+K258+K261+K264+K267+K270+K273 -> 49 | L6: =L12+L84+L87+L90+L93+L96+L99+L201+L204+L207+L15+L18+L21+L24+L27+L30+L33+L36+L42+L39+L45+L48+L51+L54+L57+L60+L63+L66+L69+L72+L75+L78+L81+L102+L105+L108+L111+L114+L117+L120+L123+L126+L129+L132+L135+L138+L141+L144+L147+L150+L153+L156+L159+L162+L165+L168+L171+L174+L177+L180+L183+L186+L189+L192+L195+L198+L210+L213+L216+L219+L222+L225+L228+L231+L234+L237+L240+L243+L246+L249+L252+L255+L258+L261+L264+L267+L270+L273 -> 46 | N6: =N12+N84+N87+N90+N93+N96+N99+N201+N204+N207+N15+N18+N21+N24+N27+N30+N33+N36+N42+N39+N45+N48+N51+N54+N57+N60+N63+N66+N69+N72+N75+N78+N81+N102+N105+N108+N111+N114+N117+N120+N123+N126+N129+N132+N135+N138+N141+N144+N147+N150+N153+N156+N159+N162+N165+N168+N171+N174+N177+N180+N183+N186+N189+N192+N195+N198+N210+N213+N216+N219+N222+N225+N228+N231+N234+N237+N240+N243+N246+N249+N252+N255+N258+N261+N264+N267+N270+N273 -> 43 | O6: =O12+O84+O87+O90+O93+O96+O99+O201+O204+O207+O15+O18+O21+O24+O27+O30+O33+O36+O42+O39+O45+O48+O51+O54+O57+O60+O63+O66+O69+O72+O75+O78+O81+O102+O105+O108+O111+O114+O117+O120+O123+O126+O129+O132+O135+O138+O141+O144+O147+O150+O153+O156+O159+O162+O165+O168+O171+O174+O177+O180+O183+O186+O189+O192+O195+O198+O210+O213+O216+O219+O222+O225+O228+O231+O234+O237+O240+O243+O246+O249+O252+O255+O258+O261+O264+O267+O270+O273 -> 42 | Q6: =Q12+Q84+Q87+Q90+Q93+Q96+Q99+Q201+Q204+Q207+Q15+Q18+Q21+Q24+Q27+Q30+Q33+Q36+Q42+Q39+Q45+Q48+Q51+Q54+Q57+Q60+Q63+Q66+Q69+Q72+Q75+Q78+Q81+Q102+Q105+Q108+Q111+Q114+Q117+Q120+Q123+Q126+Q129+Q132+Q135+Q138+Q141+Q144+Q147+Q150+Q153+Q156+Q159+Q162+Q165+Q168+Q171+Q174+Q177+Q180+Q183+Q186+Q189+Q192+Q195+Q198+Q210+Q213+Q216+Q219+Q222+Q225+Q228+Q231+Q234+Q237+Q240+Q243+Q246+Q249+Q252+Q255+Q258+Q261+Q264+Q267+Q270+Q273 -> 14 | R6: =R12+R84+R87+R90+R93+R96+R99+R201+R204+R207+R15+R18+R21+R24+R27+R30+R33+R36+R42+R39+R45+R48+R51+R54+R57+R60+R63+R66+R69+R72+R75+R78+R81+R102+R105+R108+R111+R114+R117+R120+R123+R126+R129+R132+R135+R138+R141+R144+R147+R150+R153+R156+R159+R162+R165+R168+R171+R174+R177+R180+R183+R186+R189+R192+R195+R198+R210+R213+R216+R219+R222+R225+R228+R231+R234+R237+R240+R243+R246+R249+R252+R255+R258+R261+R264+R267+R270+R273 -> 11 | T6: =T12+T84+T87+T90+T93+T96+T99+T201+T204+T207+T15+T18+T21+T24+T27+T30+T33+T36+T42+T39+T45+T48+T51+T54+T57+T60+T63+T66+T69+T72+T75+T78+T81+T102+T105+T108+T111+T114+T117+T120+T123+T126+T129+T132+T135+T138+T141+T144+T147+T150+T153+T156+T159+T162+T165+T168+T171+T174+T177+T180+T183+T186+T189+T192+T195+T198+T210+T213+T216+T219+T222+T225+T228+T231+T234+T237+T240+T243+T246+T249+T252+T255+T258+T261+T264+T267+T270+T273 -> 0 | U6: =U12+U84+U87+U90+U93+U96+U99+U201+U204+U207+U15+U18+U21+U24+U27+U30+U33+U36+U42+U39+U45+U48+U51+U54+U57+U60+U63+U66+U69+U72+U75+U78+U81+U102+U105+U108+U111+U114+U117+U120+U123+U126+U129+U132+U135+U138+U141+U144+U147+U150+U153+U156+U159+U162+U165+U168+U171+U174+U177+U180+U183+U186+U189+U192+U195+U198+U210+U213+U216+U219+U222+U225+U228+U231+U234+U237+U240+U243+U246+U249+U252+U255+U258+U261+U264+U267+U270+U273 -> 0 | W6: =W12+W84+W87+W90+W93+W96+W99+W201+W204+W207+W15+W18+W21+W24+W27+W30+W33+W36+W42+W39+W45+W48+W51+W54+W57+W60+W63+W66+W69+W72+W75+W78+W81+W102+W105+W108+W111+W114+W117+W120+W123+W126+W129+W132+W135+W138+W141+W144+W147+W150+W153+W156+W159+W162+W165+W168+W171+W174+W177+W180+W183+W186+W189+W192+W195+W198+W210+W213+W216+W219+W222+W225+W228+W231+W234+W237+W240+W243+W246+W249+W252+W255+W258+W261+W264+W267+W270+W273 -> 0 | X6: =X12+X84+X87+X90+X93+X96+X99+X201+X204+X207+X15+X18+X21+X24+X27+X30+X33+X36+X42+X39+X45+X48+X51+X54+X57+X60+X63+X66+X69+X72+X75+X78+X81+X102+X105+X108+X111+X114+X117+X120+X123+X126+X129+X132+X135+X138+X141+X144+X147+X150+X153+X156+X159+X162+X165+X168+X171+X174+X177+X180+X183+X186+X189+X192+X195+X198+X210+X213+X216+X219+X222+X225+X228+X231+X234+X237+X240+X243+X246+X249+X252+X255+X258+X261+X264+X267+X270+X273 -> 0
D8: ----------------------------------------------------------------------------------------------------------------------------------------------------------------------> | H8: =H5+I5+H6+I6 -> 164 | I8: Pontos | K8: =K5+L5+K6+L6 -> 199 | L8: Pontos | N8: =N5+O5+N6+O6 -> 191 | O8: Pontos | Q8: =Q5+R5+Q6+R6 -> 53 | R8: Pontos | T8: =T5+U5+T6+U6 -> 0 | U8: Pontos | W8: =W5+X5+W6+X6 -> 0 | X8: Pontos
Z9: Semáforo | AC9: Legenda:
B11: Faturamento | D11: Emissão de NF de venda (NF-e) | F11: Diario | H11: 1 | I11: 1 | K11: 1 | L11: 1 | N11: 1 | O11: 1 | Q11: 1 | R11: 1 | Z11: =H11+K11+N11+Q11+T11+W11 -> 4 | AA11: =I11+L11+O11+R11+U11+X11 -> 4 | AD11: Aprendendo | AE11: 1
H12: 1 | I12: 1 | K12: 1 | L12: 1 | N12: 1 | O12: 1 | Q12: 1 | R12: 1 | Z12: =H12+K12+N12+Q12+T12+W12 -> 4 | AA12: =I12+L12+O12+R12+U12+X12 -> 4
B14: Faturamento | D14: Emissão de NF de exportação (NF-e) | F14: Diario | H14: 1 | I14: 1 | K14: 1 | L14: 1 | N14: 1 | O14: 1 | Z14: =H14+K14+N14+Q14+T14+W14 -> 3 | AA14: =I14+L14+O14+R14+U14+X14 -> 3 | AC14: Consegue fazer | AD14: com ajuda | AE14: 1
H15: 1 | I15: 1 | K15: 1 | L15: 1 | N15: 1 | O15: 1 | Z15: =H15+K15+N15+Q15+T15+W15 -> 3 | AA15: =I15+L15+O15+R15+U15+X15 -> 3 | AE15: 1
B17: Faturamento | D17: Emissão de NF de importação (NF-e) | F17: Diario | H17: 1 | I17: 1 | K17: 1 | L17: 1 | N17: 1 | O17: 1 | Z17: =H17+K17+N17+Q17+T17+W17 -> 3 | AA17: =I17+L17+O17+R17+U17+X17 -> 3 | AC17: Consegue fazer | AD17: sem ajuda | AE17: 1 | AF17: 1
H18: 1 | I18: 1 | K18: 1 | L18: 1 | N18: 1 | O18: 1 | Z18: =H18+K18+N18+Q18+T18+W18 -> 3 | AA18: =I18+L18+O18+R18+U18+X18 -> 3 | AC18: (Sei fazer, mas não sei porque faço) | AE18: 1
B20: Faturamento | D20: Emissão de NF de comodato (NF-e) | F20: Diario | H20: 1 | I20: 1 | K20: 1 | L20: 1 | N20: 1 | O20: 1 | Q20: 1 | R20: 1 | Z20: =H20+K20+N20+Q20+T20+W20 -> 4 | AA20: =I20+L20+O20+R20+U20+X20 -> 4 | AC20: Consegue fazer | AD20: e ensinar | AE20: 1 | AF20: 1
H21: 1 | I21: 1 | K21: 1 | L21: 1 | N21: 1 | O21: 1 | Q21: 1 | R21: 1 | Z21: =H21+K21+N21+Q21+T21+W21 -> 4 | AA21: =I21+L21+O21+R21+U21+X21 -> 4 | AC21: (Sei fazer, e sei porque faço) | AE21: 1 | AF21: 1
B23: Faturamento | D23: Emissão de NF de bonificação ou brinde (NF-e) | F23: Diario | H23: 1 | I23: 1 | K23: 1 | L23: 1 | N23: 1 | O23: 1 | Q23: 1 | R23: 1 | Z23: =H23+K23+N23+Q23+T23+W23 -> 4 | AA23: =I23+L23+O23+R23+U23+X23 -> 4
H24: 1 | I24: 1 | K24: 1 | L24: 1 | N24: 1 | O24: 1 | Q24: 1 | R24: 1 | Z24: =H24+K24+N24+Q24+T24+W24 -> 4 | AA24: =I24+L24+O24+R24+U24+X24 -> 4
B26: Faturamento | D26: Emissão de NF de demonstração (NF-e) | F26: Diario | H26: 1 | I26: 1 | K26: 1 | L26: 1 | N26: 1 | O26: 1 | Q26: 1 | R26: 1 | Z26: =H26+K26+N26+Q26+T26+W26 -> 4 | AA26: =I26+L26+O26+R26+U26+X26 -> 4
H27: 1 | I27: 1 | K27: 1 | L27: 1 | N27: 1 | O27: 1 | Q27: 1 | R27: 1 | Z27: =H27+K27+N27+Q27+T27+W27 -> 4 | AA27: =I27+L27+O27+R27+U27+X27 -> 4
B29: Faturamento | D29: Emissão de NF de troca em garantia (NF-e) | F29: Diario | H29: 1 | I29: 1 | K29: 1 | L29: 1 | N29: 1 | O29: 1 | Q29: 1 | R29: 1 | Z29: =H29+K29+N29+Q29+T29+W29 -> 4 | AA29: =I29+L29+O29+R29+U29+X29 -> 4
H30: 1 | I30: 1 | K30: 1 | L30: 1 | N30: 1 | O30: 1 | Q30: 1 | R30: 1 | Z30: =H30+K30+N30+Q30+T30+W30 -> 4 | AA30: =I30+L30+O30+R30+U30+X30 -> 4
B32: Faturamento | D32: Emissão de NF de industrialização (NF-e) | F32: Diario | H32: 1 | I32: 1 | K32: 1 | L32: 1 | N32: 1 | O32: 1 | Z32: =H32+K32+N32+Q32+T32+W32 -> 3 | AA32: =I32+L32+O32+R32+U32+X32 -> 3
H33: 1 | I33: 1 | K33: 1 | L33: 1 | N33: 1 | O33: 1 | Z33: =H33+K33+N33+Q33+T33+W33 -> 3 | AA33: =I33+L33+O33+R33+U33+X33 -> 3
B35: Faturamento | D35: Emissão de NF de serviço (NFS-e) | F35: Diario | H35: 1 | I35: 1 | K35: 1 | L35: 1 | N35: 1 | O35: 1 | Z35: =H35+K35+N35+Q35+T35+W35 -> 3 | AA35: =I35+L35+O35+R35+U35+X35 -> 3
H36: 1 | I36: 1 | K36: 1 | N36: 1 | O36: 1 | Z36: =H36+K36+N36+Q36+T36+W36 -> 3 | AA36: =I36+L36+O36+R36+U36+X36 -> 2
B38: Faturamento | D38: Emissão de NF de débito (ND) | F38: Diario | H38: 1 | I38: 1 | K38: 1 | L38: 1 | N38: 1 | O38: 1 | Z38: =H38+K38+N38+Q38+T38+W38 -> 3 | AA38: =I38+L38+O38+R38+U38+X38 -> 3
H39: 1 | I39: 1 | K39: 1 | N39: 1 | O39: 1 | Z39: =H39+K39+N39+Q39+T39+W39 -> 3 | AA39: =I39+L39+O39+R39+U39+X39 -> 2
B41: Faturamento | D41: Emissão de NF complementar de ICMS (NF-e) | F41: Diario | H41: 1 | I41: 1 | K41: 1 | L41: 1 | N41: 1 | O41: 1 | Z41: =H41+K41+N41+Q41+T41+W41 -> 3 | AA41: =I41+L41+O41+R41+U41+X41 -> 3
H42: 1 | I42: 1 | K42: 1 | L42: 1 | Z42: =H42+K42+N42+Q42+T42+W42 -> 2 | AA42: =I42+L42+O42+R42+U42+X42 -> 2
B44: Faturamento | D44: Emissão e/ou lançamento de NF de devolução de venda | F44: Diario | H44: 1 | I44: 1 | K44: 1 | L44: 1 | N44: 1 | O44: 1 | Q44: 1 | R44: 1 | Z44: =H44+K44+N44+Q44+T44+W44 -> 4 | AA44: =I44+L44+O44+R44+U44+X44 -> 4
H45: 1 | I45: 1 | K45: 1 | L45: 1 | N45: 1 | O45: 1 | Q45: 1 | R45: 1 | Z45: =H45+K45+N45+Q45+T45+W45 -> 4 | AA45: =I45+L45+O45+R45+U45+X45 -> 4
B47: Faturamento | D47: Emissão e/ou lançamento de NF de retorno de comodato | F47: Diario | H47: 1 | I47: 1 | K47: 1 | L47: 1 | N47: 1 | O47: 1 | Q47: 1 | R47: 1 | Z47: =H47+K47+N47+Q47+T47+W47 -> 4 | AA47: =I47+L47+O47+R47+U47+X47 -> 4
H48: 1 | I48: 1 | K48: 1 | L48: 1 | N48: 1 | O48: 1 | Q48: 1 | R48: 1 | Z48: =H48+K48+N48+Q48+T48+W48 -> 4 | AA48: =I48+L48+O48+R48+U48+X48 -> 4
B50: Faturamento | D50: Emissão e/ou lançamento de NF de retorno de demonstração | F50: Diario | H50: 1 | I50: 1 | K50: 1 | L50: 1 | N50: 1 | O50: 1 | Q50: 1 | R50: 1 | Z50: =H50+K50+N50+Q50+T50+W50 -> 4 | AA50: =I50+L50+O50+R50+U50+X50 -> 4
H51: 1 | I51: 1 | K51: 1 | L51: 1 | N51: 1 | O51: 1 | Q51: 1 | R51: 1 | Z51: =H51+K51+N51+Q51+T51+W51 -> 4 | AA51: =I51+L51+O51+R51+U51+X51 -> 4
B53: Faturamento | D53: Emissão e/ou lançamento de NF de retorno de industrialização | F53: Diario | H53: 1 | I53: 1 | K53: 1 | L53: 1 | N53: 1 | O53: 1 | Z53: =H53+K53+N53+Q53+T53+W53 -> 3 | AA53: =I53+L53+O53+R53+U53+X53 -> 3
H54: 1 | I54: 1 | K54: 1 | L54: 1 | N54: 1 | O54: 1 | Z54: =H54+K54+N54+Q54+T54+W54 -> 3 | AA54: =I54+L54+O54+R54+U54+X54 -> 3
B56: Faturamento | D56: Emissão e/ou lançamento de NF de troca em garantia | F56: Diario | H56: 1 | I56: 1 | K56: 1 | L56: 1 | N56: 1 | O56: 1 | Q56: 1 | R56: 1 | Z56: =H56+K56+N56+Q56+T56+W56 -> 4 | AA56: =I56+L56+O56+R56+U56+X56 -> 4
H57: 1 | I57: 1 | K57: 1 | L57: 1 | N57: 1 | O57: 1 | Q57: 1 | R57: 1 | Z57: =H57+K57+N57+Q57+T57+W57 -> 4 | AA57: =I57+L57+O57+R57+U57+X57 -> 4
B59: Faturamento | D59: Análise e/ou criação de cadastros de clientes e fornecedores no sistema SAP | F59: Diario | H59: 1 | I59: 1 | K59: 1 | L59: 1 | N59: 1 | O59: 1 | Q59: 1 | R59: 1 | Z59: =H59+K59+N59+Q59+T59+W59 -> 4 | AA59: =I59+L59+O59+R59+U59+X59 -> 4
H60: 1 | I60: 1 | K60: 1 | L60: 1 | N60: 1 | O60: 1 | Q60: 1 | R60: 1 | Z60: =H60+K60+N60+Q60+T60+W60 -> 4 | AA60: =I60+L60+O60+R60+U60+X60 -> 4
B62: Faturamento | D62: Análise de possível emissão de guia DIFAL (diferencial de alíquotas) | F62: Diario | H62: 1 | I62: 1 | K62: 1 | L62: 1 | N62: 1 | O62: 1 | Z62: =H62+K62+N62+Q62+T62+W62 -> 3 | AA62: =I62+L62+O62+R62+U62+X62 -> 3
H63: 1 | I63: 1 | K63: 1 | L63: 1 | Z63: =H63+K63+N63+Q63+T63+W63 -> 2 | AA63: =I63+L63+O63+R63+U63+X63 -> 2
B65: Faturamento | D65: Confirmação de pagamento dos pedidos de venda com acesso ao banco Itaú | F65: Diario | H65: 1 | I65: 1 | Z65: =H65+K65+N65+Q65+T65+W65 -> 1 | AA65: =I65+L65+O65+R65+U65+X65 -> 1
H66: 1 | I66: 1 | Z66: =H66+K66+N66+Q66+T66+W66 -> 1 | AA66: =I66+L66+O66+R66+U66+X66 -> 1
B68: Faturamento | D68: Emissão de fatura de adiantamento no pedido de venda | F68: Diario | H68: 1 | I68: 1 | N68: 1 | O68: 1 | Z68: =H68+K68+N68+Q68+T68+W68 -> 2 | AA68: =I68+L68+O68+R68+U68+X68 -> 2
H69: 1 | I69: 1 | N69: 1 | O69: 1 | Z69: =H69+K69+N69+Q69+T69+W69 -> 2 | AA69: =I69+L69+O69+R69+U69+X69 -> 2
B71: Faturamento | D71: Controle das mensalidades de locação na planilha Excel junto com o sistema SAP | F71: Diario | H71: 1 | I71: 1 | K71: 1 | L71: 1 | N71: 1 | O71: 1 | Z71: =H71+K71+N71+Q71+T71+W71 -> 3 | AA71: =I71+L71+O71+R71+U71+X71 -> 3
H72: 1 | I72: 1 | K72: 1 | L72: 1 | N72: 1 | O72: 1 | Z72: =H72+K72+N72+Q72+T72+W72 -> 3 | AA72: =I72+L72+O72+R72+U72+X72 -> 3
B74: Faturamento | D74: Envio manual via e-mail das notas de débito e boletos para o respectivos clientes | F74: Diario | H74: 1 | I74: 1 | K74: 1 | L74: 1 | N74: 1 | O74: 1 | Q74: 1 | R74: 1 | Z74: =H74+K74+N74+Q74+T74+W74 -> 4 | AA74: =I74+L74+O74+R74+U74+X74 -> 4
H75: 1 | I75: 1 | K75: 1 | L75: 1 | N75: 1 | O75: 1 | Q75: 1 | R75: 1 | Z75: =H75+K75+N75+Q75+T75+W75 -> 4 | AA75: =I75+L75+O75+R75+U75+X75 -> 4
B77: Faturamento | D77: Análise e controle das mensalidades de manuntenção de equipamentos, para a posterior emissão de NFS-e | F77: Diario | H77: 1 | I77: 1 | N77: 1 | O77: 1 | Z77: =H77+K77+N77+Q77+T77+W77 -> 2 | AA77: =I77+L77+O77+R77+U77+X77 -> 2
H78: 1 | I78: 1 | N78: 1 | O78: 1 | Z78: =H78+K78+N78+Q78+T78+W78 -> 2 | AA78: =I78+L78+O78+R78+U78+X78 -> 2
B80: Faturamento | D80: Análise de novos contratos de locação novos / Planilhamento / cadastro no SAP, emissão das notas de débito (ND) | F80: Diario | H80: 1 | I80: 1 | K80: 1 | L80: 1 | N80: 1 | O80: 1 | Z80: =H80+K80+N80+Q80+T80+W80 -> 3 | AA80: =I80+L80+O80+R80+U80+X80 -> 3
H81: 1 | I81: 1 | N81: 1 | O81: 1 | Z81: =H81+K81+N81+Q81+T81+W81 -> 2 | AA81: =I81+L81+O81+R81+U81+X81 -> 2
B83: Faturamento | D83: Análise de contratos de locação em andamento | F83: Diario | H83: 1 | I83: 1 | K83: 1 | L83: 1 | N83: 1 | O83: 1 | Z83: =H83+K83+N83+Q83+T83+W83 -> 3 | AA83: =I83+L83+O83+R83+U83+X83 -> 3
H84: 1 | I84: 1 | N84: 1 | O84: 1 | Z84: =H84+K84+N84+Q84+T84+W84 -> 2 | AA84: =I84+L84+O84+R84+U84+X84 -> 2
B86: Faturamento | D86: Análise de possíveis reajuste contratuais nas parcelas dos contratos de locação/manuntenção | F86: Diario | H86: 1 | I86: 1 | N86: 1 | O86: 1 | Z86: =H86+K86+N86+Q86+T86+W86 -> 2 | AA86: =I86+L86+O86+R86+U86+X86 -> 2
H87: 1 | I87: 1 | N87: 1 | O87: 1 | Z87: =H87+K87+N87+Q87+T87+W87 -> 2 | AA87: =I87+L87+O87+R87+U87+X87 -> 2
B89: Faturamento | D89: Controle de retorno de comodato da Geneslab / emissão NF de venda | F89: Diario | H89: 1 | I89: 1 | N89: 1 | O89: 1 | Z89: =H89+K89+N89+Q89+T89+W89 -> 2 | AA89: =I89+L89+O89+R89+U89+X89 -> 2
H90: 1 | I90: 1 | N90: 1 | O90: 1 | Z90: =H90+K90+N90+Q90+T90+W90 -> 2 | AA90: =I90+L90+O90+R90+U90+X90 -> 2
B92: Faturamento | D92: Suporte e Orientações aos setores (help desk, comercial, adequação, almoxarifado) | F92: Diario | H92: 1 | I92: 1 | K92: 1 | L92: 1 | N92: 1 | O92: 1 | Q92: 1 | R92: 1 | Z92: =H92+K92+N92+Q92+T92+W92 -> 4 | AA92: =I92+L92+O92+R92+U92+X92 -> 4
H93: 1 | I93: 1 | K93: 1 | L93: 1 | N93: 1 | O93: 1 | Q93: 1 | Z93: =H93+K93+N93+Q93+T93+W93 -> 4 | AA93: =I93+L93+O93+R93+U93+X93 -> 3
B95: Faturamento | D95: Resolução de problemas e/ou dúvidas de clientes, via e-mail, telefone, whatsapp | F95: Diario | H95: 1 | I95: 1 | K95: 1 | L95: 1 | N95: 1 | O95: 1 | Q95: 1 | R95: 1 | Z95: =H95+K95+N95+Q95+T95+W95 -> 4 | AA95: =I95+L95+O95+R95+U95+X95 -> 4
H96: 1 | I96: 1 | K96: 1 | L96: 1 | N96: 1 | O96: 1 | Q96: 1 | Z96: =H96+K96+N96+Q96+T96+W96 -> 4 | AA96: =I96+L96+O96+R96+U96+X96 -> 3
B98: Faturamento | D98: Análise de impostos e tributações das operações em geral | F98: Diario | H98: 1 | I98: 1 | K98: 1 | L98: 1 | N98: 1 | O98: 1 | Z98: =H98+K98+N98+Q98+T98+W98 -> 3 | AA98: =I98+L98+O98+R98+U98+X98 -> 3
H99: 1 | I99: 1 | K99: 1 | L99: 1 | Z99: =H99+K99+N99+Q99+T99+W99 -> 2 | AA99: =I99+L99+O99+R99+U99+X99 -> 2
B101: Recebimento | D101: Lançamento de notas com pedido de compra | F101: Diario | K101: 1 | L101: 1 | N101: 1 | O101: 1 | Z101: =H101+K101+N101+Q101+T101+W101 -> 2 | AA101: =I101+L101+O101+R101+U101+X101 -> 2
K102: 1 | L102: 1 | N102: 1 | O102: 1 | Z102: =H102+K102+N102+Q102+T102+W102 -> 2 | AA102: =I102+L102+O102+R102+U102+X102 -> 2
B104: Recebimento | D104: Lançamento de notas recorrentes | F104: Diario | K104: 1 | L104: 1 | N104: 1 | O104: 1 | Z104: =H104+K104+N104+Q104+T104+W104 -> 2 | AA104: =I104+L104+O104+R104+U104+X104 -> 2
K105: 1 | L105: 1 | N105: 1 | O105: 1 | Z105: =H105+K105+N105+Q105+T105+W105 -> 2 | AA105: =I105+L105+O105+R105+U105+X105 -> 2
B107: Recebimento | D107: Lançamentos de guias e impostos (LCM) | F107: Diario | K107: 1 | L107: 1 | N107: 1 | O107: 1 | Z107: =H107+K107+N107+Q107+T107+W107 -> 2 | AA107: =I107+L107+O107+R107+U107+X107 -> 2
K108: 1 | L108: 1 | N108: 1 | O108: 1 | Z108: =H108+K108+N108+Q108+T108+W108 -> 2 | AA108: =I108+L108+O108+R108+U108+X108 -> 2
B110: Recebimento | D110: Lançamento da folha de pagamento | F110: Mensal | K110: 1 | L110: 1 | N110: 1 | O110: 1 | Z110: =H110+K110+N110+Q110+T110+W110 -> 2 | AA110: =I110+L110+O110+R110+U110+X110 -> 2
K111: 1 | L111: 1 | N111: 1 | O111: 1 | Z111: =H111+K111+N111+Q111+T111+W111 -> 2 | AA111: =I111+L111+O111+R111+U111+X111 -> 2
B113: Recebimento | D113: Controle de notas de entrada | F113: Diario | K113: 1 | L113: 1 | N113: 1 | O113: 1 | Q113: 1 | R113: 1 | Z113: =H113+K113+N113+Q113+T113+W113 -> 3 | AA113: =I113+L113+O113+R113+U113+X113 -> 3
K114: 1 | L114: 1 | N114: 1 | O114: 1 | Q114: 1 | Z114: =H114+K114+N114+Q114+T114+W114 -> 3 | AA114: =I114+L114+O114+R114+U114+X114 -> 2
B116: Recebimento | D116: Lançamento de fatura de cartão de crédito | F116: Mensal | K116: 1 | L116: 1 | N116: 1 | O116: 1 | Z116: =H116+K116+N116+Q116+T116+W116 -> 2 | AA116: =I116+L116+O116+R116+U116+X116 -> 2
K117: 1 | L117: 1 | N117: 1 | O117: 1 | Z117: =H117+K117+N117+Q117+T117+W117 -> 2 | AA117: =I117+L117+O117+R117+U117+X117 -> 2
B119: Recebimento | D119: Abertura de pedidos recorrentes | F119: Diario | K119: 1 | L119: 1 | N119: 1 | O119: 1 | Z119: =H119+K119+N119+Q119+T119+W119 -> 2 | AA119: =I119+L119+O119+R119+U119+X119 -> 2
K120: 1 | L120: 1 | N120: 1 | O120: 1 | Z120: =H120+K120+N120+Q120+T120+W120 -> 2 | AA120: =I120+L120+O120+R120+U120+X120 -> 2
B122: Recebimento | D122: Fatura de adiantamento para fornecedor | F122: Diario | K122: 1 | L122: 1 | N122: 1 | O122: 1 | Z122: =H122+K122+N122+Q122+T122+W122 -> 2 | AA122: =I122+L122+O122+R122+U122+X122 -> 2
K123: 1 | L123: 1 | N123: 1 | O123: 1 | Z123: =H123+K123+N123+Q123+T123+W123 -> 2 | AA123: =I123+L123+O123+R123+U123+X123 -> 2
B125: Recebimento | D125: Importar arquivos XML de saídas para o Arquivei | F125: Diario | N125: 1 | O125: 1 | Z125: =H125+K125+N125+Q125+T125+W125 -> 1 | AA125: =I125+L125+O125+R125+U125+X125 -> 1
N126: 1 | O126: 1 | Z126: =H126+K126+N126+Q126+T126+W126 -> 1 | AA126: =I126+L126+O126+R126+U126+X126 -> 1
B128: Recebimento | D128: Envio de documentos à contabilidade externa | F128: Mensal | K128: 1 | L128: 1 | N128: 1 | O128: 1 | Z128: =H128+K128+N128+Q128+T128+W128 -> 2 | AA128: =I128+L128+O128+R128+U128+X128 -> 2
N129: 1 | O129: 1 | Z129: =H129+K129+N129+Q129+T129+W129 -> 1 | AA129: =I129+L129+O129+R129+U129+X129 -> 1
B131: Recebimento | D131: Efetivar lançamentos de impostos em débito automático | F131: Mensal | N131: 1 | O131: 1 | Z131: =H131+K131+N131+Q131+T131+W131 -> 1 | AA131: =I131+L131+O131+R131+U131+X131 -> 1
N132: 1 | O132: 1 | Z132: =H132+K132+N132+Q132+T132+W132 -> 1 | AA132: =I132+L132+O132+R132+U132+X132 -> 1
B134: Recebimento | D134: Lançamento de Cte | F134: Diario | N134: 1 | O134: 1 | Z134: =H134+K134+N134+Q134+T134+W134 -> 1 | AA134: =I134+L134+O134+R134+U134+X134 -> 1
N135: 1 | O135: 1 | Z135: =H135+K135+N135+Q135+T135+W135 -> 1 | AA135: =I135+L135+O135+R135+U135+X135 -> 1
B137: Recebimento | D137: Lançamento de multas de trânsito | F137: Diario | N137: 1 | O137: 1 | Z137: =H137+K137+N137+Q137+T137+W137 -> 1 | AA137: =I137+L137+O137+R137+U137+X137 -> 1
N138: 1 | O138: 1 | Z138: =H138+K138+N138+Q138+T138+W138 -> 1 | AA138: =I138+L138+O138+R138+U138+X138 -> 1
B140: Recebimento | D140: Lançamentos de Importação Simpificada (Courrier) | F140: Diario | N140: 1 | O140: 1 | Z140: =H140+K140+N140+Q140+T140+W140 -> 1 | AA140: =I140+L140+O140+R140+U140+X140 -> 1
Z141: =H141+K141+N141+Q141+T141+W141 -> 0 | AA141: =I141+L141+O141+R141+U141+X141 -> 0
B143: Recebimento | D143: Emissão de nota fiscal de Importação Simpificada (Courrier) | F143: Diario | K143: 1 | L143: 1 | N143: 1 | O143: 1 | Z143: =H143+K143+N143+Q143+T143+W143 -> 2 | AA143: =I143+L143+O143+R143+U143+X143 -> 2
K144: 1 | Z144: =H144+K144+N144+Q144+T144+W144 -> 1 | AA144: =I144+L144+O144+R144+U144+X144 -> 0
F146: ________ | Z146: =H146+K146+N146+Q146+T146+W146 -> 0 | AA146: =I146+L146+O146+R146+U146+X146 -> 0
Z147: =H147+K147+N147+Q147+T147+W147 -> 0 | AA147: =I147+L147+O147+R147+U147+X147 -> 0
D149: ______________________________________________________________________________________________ | F149: ________ | Z149: =H149+K149+N149+Q149+T149+W149 -> 0 | AA149: =I149+L149+O149+R149+U149+X149 -> 0
Z150: =H150+K150+N150+Q150+T150+W150 -> 0 | AA150: =I150+L150+O150+R150+U150+X150 -> 0
...

Sheet Maio 2026
B2: Setorização | D2: Tarefas | F2: Periodicidade | H2: Luis | K2: Alexandre | N2: Pamella | Q2: Loraine | T2: Maykon | W2: Kevin
H3: Gerente | K3: Supervisor
D5: Classificação do Colaborador | H5: =H11+H83+H86+H89+H92+H95+H98+H200+H203+H206+H14+H17+H20+H23+H26+H29+H32+H35+H41+H38+H44+H47+H50+H53+H56+H59+H62+H65+H68+H71+H74+H77+H80+H101+H104+H107+H110+H113+H116+H119+H122+H125+H128+H131+H134+H137+H140+H143+H146+H149+H152+H155+H158+H161+H164+H167+H170+H173+H176+H179+H182+H185+H188+H191+H194+H197+H209+H212+H215+H218+H221+H224+H227+H230+H233+H236+H239+H242+H245+H248+H251+H254+H257+H260+H263+H266+H269+H272 -> 41 | I5: =I11+I83+I86+I89+I92+I95+I98+I200+I203+I206+I14+I17+I20+I23+I26+I29+I32+I35+I41+I38+I44+I47+I50+I53+I56+I59+I62+I65+I68+I71+I74+I77+I80+I101+I104+I107+I110+I113+I116+I119+I122+I125+I128+I131+I134+I137+I140+I143+I146+I149+I152+I155+I158+I161+I164+I167+I170+I173+I176+I179+I182+I185+I188+I191+I194+I197+I209+I212+I215+I218+I221+I224+I227+I230+I233+I236+I239+I242+I245+I248+I251+I254+I257+I260+I263+I266+I269+I272 -> 41 | K5: =K11+K83+K86+K89+K92+K95+K98+K200+K203+K206+K14+K17+K20+K23+K26+K29+K32+K35+K41+K38+K44+K47+K50+K53+K56+K59+K62+K65+K68+K71+K74+K77+K80+K101+K104+K107+K110+K113+K116+K119+K122+K125+K128+K131+K134+K137+K140+K143+K146+K149+K152+K155+K158+K161+K164+K167+K170+K173+K176+K179+K182+K185+K188+K191+K194+K197+K209+K212+K215+K218+K221+K224+K227+K230+K233+K236+K239+K242+K245+K248+K251+K254+K257+K260+K263+K266+K269+K272 -> 52 | L5: =L11+L83+L86+L89+L92+L95+L98+L200+L203+L206+L14+L17+L20+L23+L26+L29+L32+L35+L41+L38+L44+L47+L50+L53+L56+L59+L62+L65+L68+L71+L74+L77+L80+L101+L104+L107+L110+L113+L116+L119+L122+L125+L128+L131+L134+L137+L140+L143+L146+L149+L152+L155+L158+L161+L164+L167+L170+L173+L176+L179+L182+L185+L188+L191+L194+L197+L209+L212+L215+L218+L221+L224+L227+L230+L233+L236+L239+L242+L245+L248+L251+L254+L257+L260+L263+L266+L269+L272 -> 52 | N5: =N11+N83+N86+N89+N92+N95+N98+N200+N203+N206+N14+N17+N20+N23+N26+N29+N32+N35+N41+N38+N44+N47+N50+N53+N56+N59+N62+N65+N68+N71+N74+N77+N80+N101+N104+N107+N110+N113+N116+N119+N122+N125+N128+N131+N134+N137+N140+N143+N146+N149+N152+N155+N158+N161+N164+N167+N170+N173+N176+N179+N182+N185+N188+N191+N194+N197+N209+N212+N215+N218+N221+N224+N227+N230+N233+N236+N239+N242+N245+N248+N251+N254+N257+N260+N263+N266+N269+N272 -> 53 | O5: =O11+O83+O86+O89+O92+O95+O98+O200+O203+O206+O14+O17+O20+O23+O26+O29+O32+O35+O41+O38+O44+O47+O50+O53+O56+O59+O62+O65+O68+O71+O74+O77+O80+O101+O104+O107+O110+O113+O116+O119+O122+O125+O128+O131+O134+O137+O140+O143+O146+O149+O152+O155+O158+O161+O164+O167+O170+O173+O176+O179+O182+O185+O188+O191+O194+O197+O209+O212+O215+O218+O221+O224+O227+O230+O233+O236+O239+O242+O245+O248+O251+O254+O257+O260+O263+O266+O269+O272 -> 53 | Q5: =Q11+Q83+Q86+Q89+Q92+Q95+Q98+Q200+Q203+Q206+Q14+Q17+Q20+Q23+Q26+Q29+Q32+Q35+Q41+Q38+Q44+Q47+Q50+Q53+Q56+Q59+Q62+Q65+Q68+Q71+Q74+Q77+Q80+Q101+Q104+Q107+Q110+Q113+Q116+Q119+Q122+Q125+Q128+Q131+Q134+Q137+Q140+Q143+Q146+Q149+Q152+Q155+Q158+Q161+Q164+Q167+Q170+Q173+Q176+Q179+Q182+Q185+Q188+Q191+Q194+Q197+Q209+Q212+Q215+Q218+Q221+Q224+Q227+Q230+Q233+Q236+Q239+Q242+Q245+Q248+Q251+Q254+Q257+Q260+Q263+Q266+Q269+Q272 -> 14 | R5: =R11+R83+R86+R89+R92+R95+R98+R200+R203+R206+R14+R17+R20+R23+R26+R29+R32+R35+R41+R38+R44+R47+R50+R53+R56+R59+R62+R65+R68+R71+R74+R77+R80+R101+R104+R107+R110+R113+R116+R119+R122+R125+R128+R131+R134+R137+R140+R143+R146+R149+R152+R155+R158+R161+R164+R167+R170+R173+R176+R179+R182+R185+R188+R191+R194+R197+R209+R212+R215+R218+R221+R224+R227+R230+R233+R236+R239+R242+R245+R248+R251+R254+R257+R260+R263+R266+R269+R272 -> 14 | T5: =T11+T83+T86+T89+T92+T95+T98+T200+T203+T206+T14+T17+T20+T23+T26+T29+T32+T35+T41+T38+T44+T47+T50+T53+T56+T59+T62+T65+T68+T71+T74+T77+T80+T101+T104+T107+T110+T113+T116+T119+T122+T125+T128+T131+T134+T137+T140+T143+T146+T149+T152+T155+T158+T161+T164+T167+T170+T173+T176+T179+T182+T185+T188+T191+T194+T197+T209+T212+T215+T218+T221+T224+T227+T230+T233+T236+T239+T242+T245+T248+T251+T254+T257+T260+T263+T266+T269+T272 -> 0 | U5: =U11+U83+U86+U89+U92+U95+U98+U200+U203+U206+U14+U17+U20+U23+U26+U29+U32+U35+U41+U38+U44+U47+U50+U53+U56+U59+U62+U65+U68+U71+U74+U77+U80+U101+U104+U107+U110+U113+U116+U119+U122+U125+U128+U131+U134+U137+U140+U143+U146+U149+U152+U155+U158+U161+U164+U167+U170+U173+U176+U179+U182+U185+U188+U191+U194+U197+U209+U212+U215+U218+U221+U224+U227+U230+U233+U236+U239+U242+U245+U248+U251+U254+U257+U260+U263+U266+U269+U272 -> 0 | W5: =W11+W83+W86+W89+W92+W95+W98+W200+W203+W206+W14+W17+W20+W23+W26+W29+W32+W35+W41+W38+W44+W47+W50+W53+W56+W59+W62+W65+W68+W71+W74+W77+W80+W101+W104+W107+W110+W113+W116+W119+W122+W125+W128+W131+W134+W137+W140+W143+W146+W149+W152+W155+W158+W161+W164+W167+W170+W173+W176+W179+W182+W185+W188+W191+W194+W197+W209+W212+W215+W218+W221+W224+W227+W230+W233+W236+W239+W242+W245+W248+W251+W254+W257+W260+W263+W266+W269+W272 -> 7 | X5: =X11+X83+X86+X89+X92+X95+X98+X200+X203+X206+X14+X17+X20+X23+X26+X29+X32+X35+X41+X38+X44+X47+X50+X53+X56+X59+X62+X65+X68+X71+X74+X77+X80+X101+X104+X107+X110+X113+X116+X119+X122+X125+X128+X131+X134+X137+X140+X143+X146+X149+X152+X155+X158+X161+X164+X167+X170+X173+X176+X179+X182+X185+X188+X191+X194+X197+X209+X212+X215+X218+X221+X224+X227+X230+X233+X236+X239+X242+X245+X248+X251+X254+X257+X260+X263+X266+X269+X272 -> 5
H6: =H12+H84+H87+H90+H93+H96+H99+H201+H204+H207+H15+H18+H21+H24+H27+H30+H33+H36+H42+H39+H45+H48+H51+H54+H57+H60+H63+H66+H69+H72+H75+H78+H81+H102+H105+H108+H111+H114+H117+H120+H123+H126+H129+H132+H135+H138+H141+H144+H147+H150+H153+H156+H159+H162+H165+H168+H171+H174+H177+H180+H183+H186+H189+H192+H195+H198+H210+H213+H216+H219+H222+H225+H228+H231+H234+H237+H240+H243+H246+H249+H252+H255+H258+H261+H264+H267+H270+H273 -> 41 | I6: =I12+I84+I87+I90+I93+I96+I99+I201+I204+I207+I15+I18+I21+I24+I27+I30+I33+I36+I42+I39+I45+I48+I51+I54+I57+I60+I63+I66+I69+I72+I75+I78+I81+I102+I105+I108+I111+I114+I117+I120+I123+I126+I129+I132+I135+I138+I141+I144+I147+I150+I153+I156+I159+I162+I165+I168+I171+I174+I177+I180+I183+I186+I189+I192+I195+I198+I210+I213+I216+I219+I222+I225+I228+I231+I234+I237+I240+I243+I246+I249+I252+I255+I258+I261+I264+I267+I270+I273 -> 41 | K6: =K12+K84+K87+K90+K93+K96+K99+K201+K204+K207+K15+K18+K21+K24+K27+K30+K33+K36+K42+K39+K45+K48+K51+K54+K57+K60+K63+K66+K69+K72+K75+K78+K81+K102+K105+K108+K111+K114+K117+K120+K123+K126+K129+K132+K135+K138+K141+K144+K147+K150+K153+K156+K159+K162+K165+K168+K171+K174+K177+K180+K183+K186+K189+K192+K195+K198+K210+K213+K216+K219+K222+K225+K228+K231+K234+K237+K240+K243+K246+K249+K252+K255+K258+K261+K264+K267+K270+K273 -> 49 | L6: =L12+L84+L87+L90+L93+L96+L99+L201+L204+L207+L15+L18+L21+L24+L27+L30+L33+L36+L42+L39+L45+L48+L51+L54+L57+L60+L63+L66+L69+L72+L75+L78+L81+L102+L105+L108+L111+L114+L117+L120+L123+L126+L129+L132+L135+L138+L141+L144+L147+L150+L153+L156+L159+L162+L165+L168+L171+L174+L177+L180+L183+L186+L189+L192+L195+L198+L210+L213+L216+L219+L222+L225+L228+L231+L234+L237+L240+L243+L246+L249+L252+L255+L258+L261+L264+L267+L270+L273 -> 46 | N6: =N12+N84+N87+N90+N93+N96+N99+N201+N204+N207+N15+N18+N21+N24+N27+N30+N33+N36+N42+N39+N45+N48+N51+N54+N57+N60+N63+N66+N69+N72+N75+N78+N81+N102+N105+N108+N111+N114+N117+N120+N123+N126+N129+N132+N135+N138+N141+N144+N147+N150+N153+N156+N159+N162+N165+N168+N171+N174+N177+N180+N183+N186+N189+N192+N195+N198+N210+N213+N216+N219+N222+N225+N228+N231+N234+N237+N240+N243+N246+N249+N252+N255+N258+N261+N264+N267+N270+N273 -> 43 | O6: =O12+O84+O87+O90+O93+O96+O99+O201+O204+O207+O15+O18+O21+O24+O27+O30+O33+O36+O42+O39+O45+O48+O51+O54+O57+O60+O63+O66+O69+O72+O75+O78+O81+O102+O105+O108+O111+O114+O117+O120+O123+O126+O129+O132+O135+O138+O141+O144+O147+O150+O153+O156+O159+O162+O165+O168+O171+O174+O177+O180+O183+O186+O189+O192+O195+O198+O210+O213+O216+O219+O222+O225+O228+O231+O234+O237+O240+O243+O246+O249+O252+O255+O258+O261+O264+O267+O270+O273 -> 42 | Q6: =Q12+Q84+Q87+Q90+Q93+Q96+Q99+Q201+Q204+Q207+Q15+Q18+Q21+Q24+Q27+Q30+Q33+Q36+Q42+Q39+Q45+Q48+Q51+Q54+Q57+Q60+Q63+Q66+Q69+Q72+Q75+Q78+Q81+Q102+Q105+Q108+Q111+Q114+Q117+Q120+Q123+Q126+Q129+Q132+Q135+Q138+Q141+Q144+Q147+Q150+Q153+Q156+Q159+Q162+Q165+Q168+Q171+Q174+Q177+Q180+Q183+Q186+Q189+Q192+Q195+Q198+Q210+Q213+Q216+Q219+Q222+Q225+Q228+Q231+Q234+Q237+Q240+Q243+Q246+Q249+Q252+Q255+Q258+Q261+Q264+Q267+Q270+Q273 -> 14 | R6: =R12+R84+R87+R90+R93+R96+R99+R201+R204+R207+R15+R18+R21+R24+R27+R30+R33+R36+R42+R39+R45+R48+R51+R54+R57+R60+R63+R66+R69+R72+R75+R78+R81+R102+R105+R108+R111+R114+R117+R120+R123+R126+R129+R132+R135+R138+R141+R144+R147+R150+R153+R156+R159+R162+R165+R168+R171+R174+R177+R180+R183+R186+R189+R192+R195+R198+R210+R213+R216+R219+R222+R225+R228+R231+R234+R237+R240+R243+R246+R249+R252+R255+R258+R261+R264+R267+R270+R273 -> 11 | T6: =T12+T84+T87+T90+T93+T96+T99+T201+T204+T207+T15+T18+T21+T24+T27+T30+T33+T36+T42+T39+T45+T48+T51+T54+T57+T60+T63+T66+T69+T72+T75+T78+T81+T102+T105+T108+T111+T114+T117+T120+T123+T126+T129+T132+T135+T138+T141+T144+T147+T150+T153+T156+T159+T162+T165+T168+T171+T174+T177+T180+T183+T186+T189+T192+T195+T198+T210+T213+T216+T219+T222+T225+T228+T231+T234+T237+T240+T243+T246+T249+T252+T255+T258+T261+T264+T267+T270+T273 -> 0 | U6: =U12+U84+U87+U90+U93+U96+U99+U201+U204+U207+U15+U18+U21+U24+U27+U30+U33+U36+U42+U39+U45+U48+U51+U54+U57+U60+U63+U66+U69+U72+U75+U78+U81+U102+U105+U108+U111+U114+U117+U120+U123+U126+U129+U132+U135+U138+U141+U144+U147+U150+U153+U156+U159+U162+U165+U168+U171+U174+U177+U180+U183+U186+U189+U192+U195+U198+U210+U213+U216+U219+U222+U225+U228+U231+U234+U237+U240+U243+U246+U249+U252+U255+U258+U261+U264+U267+U270+U273 -> 0 | W6: =W12+W84+W87+W90+W93+W96+W99+W201+W204+W207+W15+W18+W21+W24+W27+W30+W33+W36+W42+W39+W45+W48+W51+W54+W57+W60+W63+W66+W69+W72+W75+W78+W81+W102+W105+W108+W111+W114+W117+W120+W123+W126+W129+W132+W135+W138+W141+W144+W147+W150+W153+W156+W159+W162+W165+W168+W171+W174+W177+W180+W183+W186+W189+W192+W195+W198+W210+W213+W216+W219+W222+W225+W228+W231+W234+W237+W240+W243+W246+W249+W252+W255+W258+W261+W264+W267+W270+W273 -> 0 | X6: =X12+X84+X87+X90+X93+X96+X99+X201+X204+X207+X15+X18+X21+X24+X27+X30+X33+X36+X42+X39+X45+X48+X51+X54+X57+X60+X63+X66+X69+X72+X75+X78+X81+X102+X105+X108+X111+X114+X117+X120+X123+X126+X129+X132+X135+X138+X141+X144+X147+X150+X153+X156+X159+X162+X165+X168+X171+X174+X177+X180+X183+X186+X189+X192+X195+X198+X210+X213+X216+X219+X222+X225+X228+X231+X234+X237+X240+X243+X246+X249+X252+X255+X258+X261+X264+X267+X270+X273 -> 0
D8: ----------------------------------------------------------------------------------------------------------------------------------------------------------------------> | H8: =H5+I5+H6+I6 -> 164 | I8: Pontos | K8: =K5+L5+K6+L6 -> 199 | L8: Pontos | N8: =N5+O5+N6+O6 -> 191 | O8: Pontos | Q8: =Q5+R5+Q6+R6 -> 53 | R8: Pontos | T8: =T5+U5+T6+U6 -> 0 | U8: Pontos | W8: =W5+X5+W6+X6 -> 12 | X8: Pontos
Z9: Semáforo | AC9: Legenda:
B11: Faturamento | D11: Emissão de NF de venda (NF-e) | F11: Diario | H11: 1 | I11: 1 | K11: 1 | L11: 1 | N11: 1 | O11: 1 | Q11: 1 | R11: 1 | Z11: =H11+K11+N11+Q11+T11+W11 -> 4 | AA11: =I11+L11+O11+R11+U11+X11 -> 4 | AD11: Aprendendo | AE11: 1
H12: 1 | I12: 1 | K12: 1 | L12: 1 | N12: 1 | O12: 1 | Q12: 1 | R12: 1 | Z12: =H12+K12+N12+Q12+T12+W12 -> 4 | AA12: =I12+L12+O12+R12+U12+X12 -> 4
B14: Faturamento | D14: Emissão de NF de exportação (NF-e) | F14: Diario | H14: 1 | I14: 1 | K14: 1 | L14: 1 | N14: 1 | O14: 1 | Z14: =H14+K14+N14+Q14+T14+W14 -> 3 | AA14: =I14+L14+O14+R14+U14+X14 -> 3 | AC14: Consegue fazer | AD14: com ajuda | AE14: 1
H15: 1 | I15: 1 | K15: 1 | L15: 1 | N15: 1 | O15: 1 | Z15: =H15+K15+N15+Q15+T15+W15 -> 3 | AA15: =I15+L15+O15+R15+U15+X15 -> 3 | AE15: 1
B17: Faturamento | D17: Emissão de NF de importação (NF-e) | F17: Diario | H17: 1 | I17: 1 | K17: 1 | L17: 1 | N17: 1 | O17: 1 | Z17: =H17+K17+N17+Q17+T17+W17 -> 3 | AA17: =I17+L17+O17+R17+U17+X17 -> 3 | AC17: Consegue fazer | AD17: sem ajuda | AE17: 1 | AF17: 1
H18: 1 | I18: 1 | K18: 1 | L18: 1 | N18: 1 | O18: 1 | Z18: =H18+K18+N18+Q18+T18+W18 -> 3 | AA18: =I18+L18+O18+R18+U18+X18 -> 3 | AC18: (Sei fazer, mas não sei porque faço) | AE18: 1
B20: Faturamento | D20: Emissão de NF de comodato (NF-e) | F20: Diario | H20: 1 | I20: 1 | K20: 1 | L20: 1 | N20: 1 | O20: 1 | Q20: 1 | R20: 1 | Z20: =H20+K20+N20+Q20+T20+W20 -> 4 | AA20: =I20+L20+O20+R20+U20+X20 -> 4 | AC20: Consegue fazer | AD20: e ensinar | AE20: 1 | AF20: 1
H21: 1 | I21: 1 | K21: 1 | L21: 1 | N21: 1 | O21: 1 | Q21: 1 | R21: 1 | Z21: =H21+K21+N21+Q21+T21+W21 -> 4 | AA21: =I21+L21+O21+R21+U21+X21 -> 4 | AC21: (Sei fazer, e sei porque faço) | AE21: 1 | AF21: 1
B23: Faturamento | D23: Emissão de NF de bonificação ou brinde (NF-e) | F23: Diario | H23: 1 | I23: 1 | K23: 1 | L23: 1 | N23: 1 | O23: 1 | Q23: 1 | R23: 1 | Z23: =H23+K23+N23+Q23+T23+W23 -> 4 | AA23: =I23+L23+O23+R23+U23+X23 -> 4
H24: 1 | I24: 1 | K24: 1 | L24: 1 | N24: 1 | O24: 1 | Q24: 1 | R24: 1 | Z24: =H24+K24+N24+Q24+T24+W24 -> 4 | AA24: =I24+L24+O24+R24+U24+X24 -> 4
B26: Faturamento | D26: Emissão de NF de demonstração (NF-e) | F26: Diario | H26: 1 | I26: 1 | K26: 1 | L26: 1 | N26: 1 | O26: 1 | Q26: 1 | R26: 1 | Z26: =H26+K26+N26+Q26+T26+W26 -> 4 | AA26: =I26+L26+O26+R26+U26+X26 -> 4
H27: 1 | I27: 1 | K27: 1 | L27: 1 | N27: 1 | O27: 1 | Q27: 1 | R27: 1 | Z27: =H27+K27+N27+Q27+T27+W27 -> 4 | AA27: =I27+L27+O27+R27+U27+X27 -> 4
B29: Faturamento | D29: Emissão de NF de troca em garantia (NF-e) | F29: Diario | H29: 1 | I29: 1 | K29: 1 | L29: 1 | N29: 1 | O29: 1 | Q29: 1 | R29: 1 | Z29: =H29+K29+N29+Q29+T29+W29 -> 4 | AA29: =I29+L29+O29+R29+U29+X29 -> 4
H30: 1 | I30: 1 | K30: 1 | L30: 1 | N30: 1 | O30: 1 | Q30: 1 | R30: 1 | Z30: =H30+K30+N30+Q30+T30+W30 -> 4 | AA30: =I30+L30+O30+R30+U30+X30 -> 4
B32: Faturamento | D32: Emissão de NF de industrialização (NF-e) | F32: Diario | H32: 1 | I32: 1 | K32: 1 | L32: 1 | N32: 1 | O32: 1 | Z32: =H32+K32+N32+Q32+T32+W32 -> 3 | AA32: =I32+L32+O32+R32+U32+X32 -> 3
H33: 1 | I33: 1 | K33: 1 | L33: 1 | N33: 1 | O33: 1 | Z33: =H33+K33+N33+Q33+T33+W33 -> 3 | AA33: =I33+L33+O33+R33+U33+X33 -> 3
B35: Faturamento | D35: Emissão de NF de serviço (NFS-e) | F35: Diario | H35: 1 | I35: 1 | K35: 1 | L35: 1 | N35: 1 | O35: 1 | Z35: =H35+K35+N35+Q35+T35+W35 -> 3 | AA35: =I35+L35+O35+R35+U35+X35 -> 3
H36: 1 | I36: 1 | K36: 1 | N36: 1 | O36: 1 | Z36: =H36+K36+N36+Q36+T36+W36 -> 3 | AA36: =I36+L36+O36+R36+U36+X36 -> 2
B38: Faturamento | D38: Emissão de NF de débito (ND) | F38: Diario | H38: 1 | I38: 1 | K38: 1 | L38: 1 | N38: 1 | O38: 1 | Z38: =H38+K38+N38+Q38+T38+W38 -> 3 | AA38: =I38+L38+O38+R38+U38+X38 -> 3
H39: 1 | I39: 1 | K39: 1 | N39: 1 | O39: 1 | Z39: =H39+K39+N39+Q39+T39+W39 -> 3 | AA39: =I39+L39+O39+R39+U39+X39 -> 2
B41: Faturamento | D41: Emissão de NF complementar de ICMS (NF-e) | F41: Diario | H41: 1 | I41: 1 | K41: 1 | L41: 1 | N41: 1 | O41: 1 | Z41: =H41+K41+N41+Q41+T41+W41 -> 3 | AA41: =I41+L41+O41+R41+U41+X41 -> 3
H42: 1 | I42: 1 | K42: 1 | L42: 1 | Z42: =H42+K42+N42+Q42+T42+W42 -> 2 | AA42: =I42+L42+O42+R42+U42+X42 -> 2
B44: Faturamento | D44: Emissão e/ou lançamento de NF de devolução de venda | F44: Diario | H44: 1 | I44: 1 | K44: 1 | L44: 1 | N44: 1 | O44: 1 | Q44: 1 | R44: 1 | Z44: =H44+K44+N44+Q44+T44+W44 -> 4 | AA44: =I44+L44+O44+R44+U44+X44 -> 4
H45: 1 | I45: 1 | K45: 1 | L45: 1 | N45: 1 | O45: 1 | Q45: 1 | R45: 1 | Z45: =H45+K45+N45+Q45+T45+W45 -> 4 | AA45: =I45+L45+O45+R45+U45+X45 -> 4
B47: Faturamento | D47: Emissão e/ou lançamento de NF de retorno de comodato | F47: Diario | H47: 1 | I47: 1 | K47: 1 | L47: 1 | N47: 1 | O47: 1 | Q47: 1 | R47: 1 | Z47: =H47+K47+N47+Q47+T47+W47 -> 4 | AA47: =I47+L47+O47+R47+U47+X47 -> 4
H48: 1 | I48: 1 | K48: 1 | L48: 1 | N48: 1 | O48: 1 | Q48: 1 | R48: 1 | Z48: =H48+K48+N48+Q48+T48+W48 -> 4 | AA48: =I48+L48+O48+R48+U48+X48 -> 4
B50: Faturamento | D50: Emissão e/ou lançamento de NF de retorno de demonstração | F50: Diario | H50: 1 | I50: 1 | K50: 1 | L50: 1 | N50: 1 | O50: 1 | Q50: 1 | R50: 1 | Z50: =H50+K50+N50+Q50+T50+W50 -> 4 | AA50: =I50+L50+O50+R50+U50+X50 -> 4
H51: 1 | I51: 1 | K51: 1 | L51: 1 | N51: 1 | O51: 1 | Q51: 1 | R51: 1 | Z51: =H51+K51+N51+Q51+T51+W51 -> 4 | AA51: =I51+L51+O51+R51+U51+X51 -> 4
B53: Faturamento | D53: Emissão e/ou lançamento de NF de retorno de industrialização | F53: Diario | H53: 1 | I53: 1 | K53: 1 | L53: 1 | N53: 1 | O53: 1 | Z53: =H53+K53+N53+Q53+T53+W53 -> 3 | AA53: =I53+L53+O53+R53+U53+X53 -> 3
H54: 1 | I54: 1 | K54: 1 | L54: 1 | N54: 1 | O54: 1 | Z54: =H54+K54+N54+Q54+T54+W54 -> 3 | AA54: =I54+L54+O54+R54+U54+X54 -> 3
B56: Faturamento | D56: Emissão e/ou lançamento de NF de troca em garantia | F56: Diario | H56: 1 | I56: 1 | K56: 1 | L56: 1 | N56: 1 | O56: 1 | Q56: 1 | R56: 1 | Z56: =H56+K56+N56+Q56+T56+W56 -> 4 | AA56: =I56+L56+O56+R56+U56+X56 -> 4
H57: 1 | I57: 1 | K57: 1 | L57: 1 | N57: 1 | O57: 1 | Q57: 1 | R57: 1 | Z57: =H57+K57+N57+Q57+T57+W57 -> 4 | AA57: =I57+L57+O57+R57+U57+X57 -> 4
B59: Faturamento | D59: Análise e/ou criação de cadastros de clientes e fornecedores no sistema SAP | F59: Diario | H59: 1 | I59: 1 | K59: 1 | L59: 1 | N59: 1 | O59: 1 | Q59: 1 | R59: 1 | Z59: =H59+K59+N59+Q59+T59+W59 -> 4 | AA59: =I59+L59+O59+R59+U59+X59 -> 4
H60: 1 | I60: 1 | K60: 1 | L60: 1 | N60: 1 | O60: 1 | Q60: 1 | R60: 1 | Z60: =H60+K60+N60+Q60+T60+W60 -> 4 | AA60: =I60+L60+O60+R60+U60+X60 -> 4
B62: Faturamento | D62: Análise de possível emissão de guia DIFAL (diferencial de alíquotas) | F62: Diario | H62: 1 | I62: 1 | K62: 1 | L62: 1 | N62: 1 | O62: 1 | Z62: =H62+K62+N62+Q62+T62+W62 -> 3 | AA62: =I62+L62+O62+R62+U62+X62 -> 3
H63: 1 | I63: 1 | K63: 1 | L63: 1 | Z63: =H63+K63+N63+Q63+T63+W63 -> 2 | AA63: =I63+L63+O63+R63+U63+X63 -> 2
B65: Faturamento | D65: Confirmação de pagamento dos pedidos de venda com acesso ao banco Itaú | F65: Diario | H65: 1 | I65: 1 | Z65: =H65+K65+N65+Q65+T65+W65 -> 1 | AA65: =I65+L65+O65+R65+U65+X65 -> 1
H66: 1 | I66: 1 | Z66: =H66+K66+N66+Q66+T66+W66 -> 1 | AA66: =I66+L66+O66+R66+U66+X66 -> 1
B68: Faturamento | D68: Emissão de fatura de adiantamento no pedido de venda | F68: Diario | H68: 1 | I68: 1 | N68: 1 | O68: 1 | Z68: =H68+K68+N68+Q68+T68+W68 -> 2 | AA68: =I68+L68+O68+R68+U68+X68 -> 2
H69: 1 | I69: 1 | N69: 1 | O69: 1 | Z69: =H69+K69+N69+Q69+T69+W69 -> 2 | AA69: =I69+L69+O69+R69+U69+X69 -> 2
B71: Faturamento | D71: Controle das mensalidades de locação na planilha Excel junto com o sistema SAP | F71: Diario | H71: 1 | I71: 1 | K71: 1 | L71: 1 | N71: 1 | O71: 1 | Z71: =H71+K71+N71+Q71+T71+W71 -> 3 | AA71: =I71+L71+O71+R71+U71+X71 -> 3
H72: 1 | I72: 1 | K72: 1 | L72: 1 | N72: 1 | O72: 1 | Z72: =H72+K72+N72+Q72+T72+W72 -> 3 | AA72: =I72+L72+O72+R72+U72+X72 -> 3
B74: Faturamento | D74: Envio manual via e-mail das notas de débito e boletos para o respectivos clientes | F74: Diario | H74: 1 | I74: 1 | K74: 1 | L74: 1 | N74: 1 | O74: 1 | Q74: 1 | R74: 1 | Z74: =H74+K74+N74+Q74+T74+W74 -> 4 | AA74: =I74+L74+O74+R74+U74+X74 -> 4
H75: 1 | I75: 1 | K75: 1 | L75: 1 | N75: 1 | O75: 1 | Q75: 1 | R75: 1 | Z75: =H75+K75+N75+Q75+T75+W75 -> 4 | AA75: =I75+L75+O75+R75+U75+X75 -> 4
B77: Faturamento | D77: Análise e controle das mensalidades de manuntenção de equipamentos, para a posterior emissão de NFS-e | F77: Diario | H77: 1 | I77: 1 | N77: 1 | O77: 1 | Z77: =H77+K77+N77+Q77+T77+W77 -> 2 | AA77: =I77+L77+O77+R77+U77+X77 -> 2
H78: 1 | I78: 1 | N78: 1 | O78: 1 | Z78: =H78+K78+N78+Q78+T78+W78 -> 2 | AA78: =I78+L78+O78+R78+U78+X78 -> 2
B80: Faturamento | D80: Análise de novos contratos de locação novos / Planilhamento / cadastro no SAP, emissão das notas de débito (ND) | F80: Diario | H80: 1 | I80: 1 | K80: 1 | L80: 1 | N80: 1 | O80: 1 | Z80: =H80+K80+N80+Q80+T80+W80 -> 3 | AA80: =I80+L80+O80+R80+U80+X80 -> 3
H81: 1 | I81: 1 | N81: 1 | O81: 1 | Z81: =H81+K81+N81+Q81+T81+W81 -> 2 | AA81: =I81+L81+O81+R81+U81+X81 -> 2
B83: Faturamento | D83: Análise de contratos de locação em andamento | F83: Diario | H83: 1 | I83: 1 | K83: 1 | L83: 1 | N83: 1 | O83: 1 | Z83: =H83+K83+N83+Q83+T83+W83 -> 3 | AA83: =I83+L83+O83+R83+U83+X83 -> 3
H84: 1 | I84: 1 | N84: 1 | O84: 1 | Z84: =H84+K84+N84+Q84+T84+W84 -> 2 | AA84: =I84+L84+O84+R84+U84+X84 -> 2
B86: Faturamento | D86: Análise de possíveis reajuste contratuais nas parcelas dos contratos de locação/manuntenção | F86: Diario | H86: 1 | I86: 1 | N86: 1 | O86: 1 | Z86: =H86+K86+N86+Q86+T86+W86 -> 2 | AA86: =I86+L86+O86+R86+U86+X86 -> 2
H87: 1 | I87: 1 | N87: 1 | O87: 1 | Z87: =H87+K87+N87+Q87+T87+W87 -> 2 | AA87: =I87+L87+O87+R87+U87+X87 -> 2
B89: Faturamento | D89: Controle de retorno de comodato da Geneslab / emissão NF de venda | F89: Diario | H89: 1 | I89: 1 | N89: 1 | O89: 1 | Z89: =H89+K89+N89+Q89+T89+W89 -> 2 | AA89: =I89+L89+O89+R89+U89+X89 -> 2
H90: 1 | I90: 1 | N90: 1 | O90: 1 | Z90: =H90+K90+N90+Q90+T90+W90 -> 2 | AA90: =I90+L90+O90+R90+U90+X90 -> 2
B92: Faturamento | D92: Suporte e Orientações aos setores (help desk, comercial, adequação, almoxarifado) | F92: Diario | H92: 1 | I92: 1 | K92: 1 | L92: 1 | N92: 1 | O92: 1 | Q92: 1 | R92: 1 | Z92: =H92+K92+N92+Q92+T92+W92 -> 4 | AA92: =I92+L92+O92+R92+U92+X92 -> 4
H93: 1 | I93: 1 | K93: 1 | L93: 1 | N93: 1 | O93: 1 | Q93: 1 | Z93: =H93+K93+N93+Q93+T93+W93 -> 4 | AA93: =I93+L93+O93+R93+U93+X93 -> 3
B95: Faturamento | D95: Resolução de problemas e/ou dúvidas de clientes, via e-mail, telefone, whatsapp | F95: Diario | H95: 1 | I95: 1 | K95: 1 | L95: 1 | N95: 1 | O95: 1 | Q95: 1 | R95: 1 | Z95: =H95+K95+N95+Q95+T95+W95 -> 4 | AA95: =I95+L95+O95+R95+U95+X95 -> 4
H96: 1 | I96: 1 | K96: 1 | L96: 1 | N96: 1 | O96: 1 | Q96: 1 | Z96: =H96+K96+N96+Q96+T96+W96 -> 4 | AA96: =I96+L96+O96+R96+U96+X96 -> 3
B98: Faturamento | D98: Análise de impostos e tributações das operações em geral | F98: Diario | H98: 1 | I98: 1 | K98: 1 | L98: 1 | N98: 1 | O98: 1 | Z98: =H98+K98+N98+Q98+T98+W98 -> 3 | AA98: =I98+L98+O98+R98+U98+X98 -> 3
H99: 1 | I99: 1 | K99: 1 | L99: 1 | Z99: =H99+K99+N99+Q99+T99+W99 -> 2 | AA99: =I99+L99+O99+R99+U99+X99 -> 2
B101: Recebimento | D101: Lançamento de notas com pedido de compra | F101: Diario | K101: 1 | L101: 1 | N101: 1 | O101: 1 | W101: 1 | X101: 1 | Z101: =H101+K101+N101+Q101+T101+W101 -> 3 | AA101: =I101+L101+O101+R101+U101+X101 -> 3
K102: 1 | L102: 1 | N102: 1 | O102: 1 | Z102: =H102+K102+N102+Q102+T102+W102 -> 2 | AA102: =I102+L102+O102+R102+U102+X102 -> 2
B104: Recebimento | D104: Lançamento de notas recorrentes | F104: Diario | K104: 1 | L104: 1 | N104: 1 | O104: 1 | W104: 1 | X104: 1 | Z104: =H104+K104+N104+Q104+T104+W104 -> 3 | AA104: =I104+L104+O104+R104+U104+X104 -> 3
K105: 1 | L105: 1 | N105: 1 | O105: 1 | Z105: =H105+K105+N105+Q105+T105+W105 -> 2 | AA105: =I105+L105+O105+R105+U105+X105 -> 2
B107: Recebimento | D107: Lançamentos de guias e impostos (LCM) | F107: Diario | K107: 1 | L107: 1 | N107: 1 | O107: 1 | W107: 1 | X107: 1 | Z107: =H107+K107+N107+Q107+T107+W107 -> 3 | AA107: =I107+L107+O107+R107+U107+X107 -> 3
K108: 1 | L108: 1 | N108: 1 | O108: 1 | Z108: =H108+K108+N108+Q108+T108+W108 -> 2 | AA108: =I108+L108+O108+R108+U108+X108 -> 2
B110: Recebimento | D110: Lançamento da folha de pagamento | F110: Mensal | K110: 1 | L110: 1 | N110: 1 | O110: 1 | Z110: =H110+K110+N110+Q110+T110+W110 -> 2 | AA110: =I110+L110+O110+R110+U110+X110 -> 2
K111: 1 | L111: 1 | N111: 1 | O111: 1 | Z111: =H111+K111+N111+Q111+T111+W111 -> 2 | AA111: =I111+L111+O111+R111+U111+X111 -> 2
B113: Recebimento | D113: Controle de notas de entrada | F113: Diario | K113: 1 | L113: 1 | N113: 1 | O113: 1 | Q113: 1 | R113: 1 | W113: 1 | X113: 1 | Z113: =H113+K113+N113+Q113+T113+W113 -> 4 | AA113: =I113+L113+O113+R113+U113+X113 -> 4
K114: 1 | L114: 1 | N114: 1 | O114: 1 | Q114: 1 | Z114: =H114+K114+N114+Q114+T114+W114 -> 3 | AA114: =I114+L114+O114+R114+U114+X114 -> 2
B116: Recebimento | D116: Lançamento de fatura de cartão de crédito | F116: Mensal | K116: 1 | L116: 1 | N116: 1 | O116: 1 | W116: 1 | Z116: =H116+K116+N116+Q116+T116+W116 -> 3 | AA116: =I116+L116+O116+R116+U116+X116 -> 2
K117: 1 | L117: 1 | N117: 1 | O117: 1 | Z117: =H117+K117+N117+Q117+T117+W117 -> 2 | AA117: =I117+L117+O117+R117+U117+X117 -> 2
B119: Recebimento | D119: Abertura de pedidos recorrentes | F119: Diario | K119: 1 | L119: 1 | N119: 1 | O119: 1 | Z119: =H119+K119+N119+Q119+T119+W119 -> 2 | AA119: =I119+L119+O119+R119+U119+X119 -> 2
K120: 1 | L120: 1 | N120: 1 | O120: 1 | Z120: =H120+K120+N120+Q120+T120+W120 -> 2 | AA120: =I120+L120+O120+R120+U120+X120 -> 2
B122: Recebimento | D122: Fatura de adiantamento para fornecedor | F122: Diario | K122: 1 | L122: 1 | N122: 1 | O122: 1 | W122: 1 | Z122: =H122+K122+N122+Q122+T122+W122 -> 3 | AA122: =I122+L122+O122+R122+U122+X122 -> 2
K123: 1 | L123: 1 | N123: 1 | O123: 1 | Z123: =H123+K123+N123+Q123+T123+W123 -> 2 | AA123: =I123+L123+O123+R123+U123+X123 -> 2
B125: Recebimento | D125: Importar arquivos XML de saídas para o Arquivei | F125: Diario | N125: 1 | O125: 1 | Z125: =H125+K125+N125+Q125+T125+W125 -> 1 | AA125: =I125+L125+O125+R125+U125+X125 -> 1
N126: 1 | O126: 1 | Z126: =H126+K126+N126+Q126+T126+W126 -> 1 | AA126: =I126+L126+O126+R126+U126+X126 -> 1
B128: Recebimento | D128: Envio de documentos à contabilidade externa | F128: Mensal | K128: 1 | L128: 1 | N128: 1 | O128: 1 | Z128: =H128+K128+N128+Q128+T128+W128 -> 2 | AA128: =I128+L128+O128+R128+U128+X128 -> 2
N129: 1 | O129: 1 | Z129: =H129+K129+N129+Q129+T129+W129 -> 1 | AA129: =I129+L129+O129+R129+U129+X129 -> 1
B131: Recebimento | D131: Efetivar lançamentos de impostos em débito automático | F131: Mensal | N131: 1 | O131: 1 | Z131: =H131+K131+N131+Q131+T131+W131 -> 1 | AA131: =I131+L131+O131+R131+U131+X131 -> 1
N132: 1 | O132: 1 | Z132: =H132+K132+N132+Q132+T132+W132 -> 1 | AA132: =I132+L132+O132+R132+U132+X132 -> 1
B134: Recebimento | D134: Lançamento de Cte | F134: Diario | N134: 1 | O134: 1 | W134: 1 | X134: 1 | Z134: =H134+K134+N134+Q134+T134+W134 -> 2 | AA134: =I134+L134+O134+R134+U134+X134 -> 2
N135: 1 | O135: 1 | Z135: =H135+K135+N135+Q135+T135+W135 -> 1 | AA135: =I135+L135+O135+R135+U135+X135 -> 1
B137: Recebimento | D137: Lançamento de multas de trânsito | F137: Diario | N137: 1 | O137: 1 | Z137: =H137+K137+N137+Q137+T137+W137 -> 1 | AA137: =I137+L137+O137+R137+U137+X137 -> 1
N138: 1 | O138: 1 | Z138: =H138+K138+N138+Q138+T138+W138 -> 1 | AA138: =I138+L138+O138+R138+U138+X138 -> 1
B140: Recebimento | D140: Lançamentos de Importação Simpificada (Courrier) | F140: Diario | N140: 1 | O140: 1 | Z140: =H140+K140+N140+Q140+T140+W140 -> 1 | AA140: =I140+L140+O140+R140+U140+X140 -> 1
Z141: =H141+K141+N141+Q141+T141+W141 -> 0 | AA141: =I141+L141+O141+R141+U141+X141 -> 0
B143: Recebimento | D143: Emissão de nota fiscal de Importação Simpificada (Courrier) | F143: Diario | K143: 1 | L143: 1 | N143: 1 | O143: 1 | Z143: =H143+K143+N143+Q143+T143+W143 -> 2 | AA143: =I143+L143+O143+R143+U143+X143 -> 2
K144: 1 | Z144: =H144+K144+N144+Q144+T144+W144 -> 1 | AA144: =I144+L144+O144+R144+U144+X144 -> 0
F146: ________ | Z146: =H146+K146+N146+Q146+T146+W146 -> 0 | AA146: =I146+L146+O146+R146+U146+X146 -> 0
Z147: =H147+K147+N147+Q147+T147+W147 -> 0 | AA147: =I147+L147+O147+R147+U147+X147 -> 0
D149: ______________________________________________________________________________________________ | F149: ________ | Z149: =H149+K149+N149+Q149+T149+W149 -> 0 | AA149: =I149+L149+O149+R149+U149+X149 -> 0
Z150: =H150+K150+N150+Q150+T150+W150 -> 0 | AA150: =I150+L150+O150+R150+U150+X150 -> 0
...

Sheet Junho 2026
B2: Setorização | D2: Tarefas | F2: Periodicidade | H2: Luis | K2: Alexandre | N2: Pamella | Q2: Loraine | T2: Maykon | W2: Kevin
H3: Gerente | K3: Supervisor
D5: Classificação do Colaborador | H5: =H11+H83+H86+H89+H92+H95+H98+H200+H203+H206+H14+H17+H20+H23+H26+H29+H32+H35+H41+H38+H44+H47+H50+H53+H56+H59+H62+H65+H68+H71+H74+H77+H80+H101+H104+H107+H110+H113+H116+H119+H122+H125+H128+H131+H134+H137+H140+H143+H146+H149+H152+H155+H158+H161+H164+H167+H170+H173+H176+H179+H182+H185+H188+H191+H194+H197+H209+H212+H215+H218+H221+H224+H227+H230+H233+H236+H239+H242+H245+H248+H251+H254+H257+H260+H263+H266+H269+H272 -> 41 | I5: =I11+I83+I86+I89+I92+I95+I98+I200+I203+I206+I14+I17+I20+I23+I26+I29+I32+I35+I41+I38+I44+I47+I50+I53+I56+I59+I62+I65+I68+I71+I74+I77+I80+I101+I104+I107+I110+I113+I116+I119+I122+I125+I128+I131+I134+I137+I140+I143+I146+I149+I152+I155+I158+I161+I164+I167+I170+I173+I176+I179+I182+I185+I188+I191+I194+I197+I209+I212+I215+I218+I221+I224+I227+I230+I233+I236+I239+I242+I245+I248+I251+I254+I257+I260+I263+I266+I269+I272 -> 41 | K5: =K11+K83+K86+K89+K92+K95+K98+K200+K203+K206+K14+K17+K20+K23+K26+K29+K32+K35+K41+K38+K44+K47+K50+K53+K56+K59+K62+K65+K68+K71+K74+K77+K80+K101+K104+K107+K110+K113+K116+K119+K122+K125+K128+K131+K134+K137+K140+K143+K146+K149+K152+K155+K158+K161+K164+K167+K170+K173+K176+K179+K182+K185+K188+K191+K194+K197+K209+K212+K215+K218+K221+K224+K227+K230+K233+K236+K239+K242+K245+K248+K251+K254+K257+K260+K263+K266+K269+K272 -> 52 | L5: =L11+L83+L86+L89+L92+L95+L98+L200+L203+L206+L14+L17+L20+L23+L26+L29+L32+L35+L41+L38+L44+L47+L50+L53+L56+L59+L62+L65+L68+L71+L74+L77+L80+L101+L104+L107+L110+L113+L116+L119+L122+L125+L128+L131+L134+L137+L140+L143+L146+L149+L152+L155+L158+L161+L164+L167+L170+L173+L176+L179+L182+L185+L188+L191+L194+L197+L209+L212+L215+L218+L221+L224+L227+L230+L233+L236+L239+L242+L245+L248+L251+L254+L257+L260+L263+L266+L269+L272 -> 52 | N5: =N11+N83+N86+N89+N92+N95+N98+N200+N203+N206+N14+N17+N20+N23+N26+N29+N32+N35+N41+N38+N44+N47+N50+N53+N56+N59+N62+N65+N68+N71+N74+N77+N80+N101+N104+N107+N110+N113+N116+N119+N122+N125+N128+N131+N134+N137+N140+N143+N146+N149+N152+N155+N158+N161+N164+N167+N170+N173+N176+N179+N182+N185+N188+N191+N194+N197+N209+N212+N215+N218+N221+N224+N227+N230+N233+N236+N239+N242+N245+N248+N251+N254+N257+N260+N263+N266+N269+N272 -> 53 | O5: =O11+O83+O86+O89+O92+O95+O98+O200+O203+O206+O14+O17+O20+O23+O26+O29+O32+O35+O41+O38+O44+O47+O50+O53+O56+O59+O62+O65+O68+O71+O74+O77+O80+O101+O104+O107+O110+O113+O116+O119+O122+O125+O128+O131+O134+O137+O140+O143+O146+O149+O152+O155+O158+O161+O164+O167+O170+O173+O176+O179+O182+O185+O188+O191+O194+O197+O209+O212+O215+O218+O221+O224+O227+O230+O233+O236+O239+O242+O245+O248+O251+O254+O257+O260+O263+O266+O269+O272 -> 53 | Q5: =Q11+Q83+Q86+Q89+Q92+Q95+Q98+Q200+Q203+Q206+Q14+Q17+Q20+Q23+Q26+Q29+Q32+Q35+Q41+Q38+Q44+Q47+Q50+Q53+Q56+Q59+Q62+Q65+Q68+Q71+Q74+Q77+Q80+Q101+Q104+Q107+Q110+Q113+Q116+Q119+Q122+Q125+Q128+Q131+Q134+Q137+Q140+Q143+Q146+Q149+Q152+Q155+Q158+Q161+Q164+Q167+Q170+Q173+Q176+Q179+Q182+Q185+Q188+Q191+Q194+Q197+Q209+Q212+Q215+Q218+Q221+Q224+Q227+Q230+Q233+Q236+Q239+Q242+Q245+Q248+Q251+Q254+Q257+Q260+Q263+Q266+Q269+Q272 -> 14 | R5: =R11+R83+R86+R89+R92+R95+R98+R200+R203+R206+R14+R17+R20+R23+R26+R29+R32+R35+R41+R38+R44+R47+R50+R53+R56+R59+R62+R65+R68+R71+R74+R77+R80+R101+R104+R107+R110+R113+R116+R119+R122+R125+R128+R131+R134+R137+R140+R143+R146+R149+R152+R155+R158+R161+R164+R167+R170+R173+R176+R179+R182+R185+R188+R191+R194+R197+R209+R212+R215+R218+R221+R224+R227+R230+R233+R236+R239+R242+R245+R248+R251+R254+R257+R260+R263+R266+R269+R272 -> 14 | T5: =T11+T83+T86+T89+T92+T95+T98+T200+T203+T206+T14+T17+T20+T23+T26+T29+T32+T35+T41+T38+T44+T47+T50+T53+T56+T59+T62+T65+T68+T71+T74+T77+T80+T101+T104+T107+T110+T113+T116+T119+T122+T125+T128+T131+T134+T137+T140+T143+T146+T149+T152+T155+T158+T161+T164+T167+T170+T173+T176+T179+T182+T185+T188+T191+T194+T197+T209+T212+T215+T218+T221+T224+T227+T230+T233+T236+T239+T242+T245+T248+T251+T254+T257+T260+T263+T266+T269+T272 -> 0 | U5: =U11+U83+U86+U89+U92+U95+U98+U200+U203+U206+U14+U17+U20+U23+U26+U29+U32+U35+U41+U38+U44+U47+U50+U53+U56+U59+U62+U65+U68+U71+U74+U77+U80+U101+U104+U107+U110+U113+U116+U119+U122+U125+U128+U131+U134+U137+U140+U143+U146+U149+U152+U155+U158+U161+U164+U167+U170+U173+U176+U179+U182+U185+U188+U191+U194+U197+U209+U212+U215+U218+U221+U224+U227+U230+U233+U236+U239+U242+U245+U248+U251+U254+U257+U260+U263+U266+U269+U272 -> 0 | W5: =W11+W83+W86+W89+W92+W95+W98+W200+W203+W206+W14+W17+W20+W23+W26+W29+W32+W35+W41+W38+W44+W47+W50+W53+W56+W59+W62+W65+W68+W71+W74+W77+W80+W101+W104+W107+W110+W113+W116+W119+W122+W125+W128+W131+W134+W137+W140+W143+W146+W149+W152+W155+W158+W161+W164+W167+W170+W173+W176+W179+W182+W185+W188+W191+W194+W197+W209+W212+W215+W218+W221+W224+W227+W230+W233+W236+W239+W242+W245+W248+W251+W254+W257+W260+W263+W266+W269+W272 -> 14 | X5: =X11+X83+X86+X89+X92+X95+X98+X200+X203+X206+X14+X17+X20+X23+X26+X29+X32+X35+X41+X38+X44+X47+X50+X53+X56+X59+X62+X65+X68+X71+X74+X77+X80+X101+X104+X107+X110+X113+X116+X119+X122+X125+X128+X131+X134+X137+X140+X143+X146+X149+X152+X155+X158+X161+X164+X167+X170+X173+X176+X179+X182+X185+X188+X191+X194+X197+X209+X212+X215+X218+X221+X224+X227+X230+X233+X236+X239+X242+X245+X248+X251+X254+X257+X260+X263+X266+X269+X272 -> 12
H6: =H12+H84+H87+H90+H93+H96+H99+H201+H204+H207+H15+H18+H21+H24+H27+H30+H33+H36+H42+H39+H45+H48+H51+H54+H57+H60+H63+H66+H69+H72+H75+H78+H81+H102+H105+H108+H111+H114+H117+H120+H123+H126+H129+H132+H135+H138+H141+H144+H147+H150+H153+H156+H159+H162+H165+H168+H171+H174+H177+H180+H183+H186+H189+H192+H195+H198+H210+H213+H216+H219+H222+H225+H228+H231+H234+H237+H240+H243+H246+H249+H252+H255+H258+H261+H264+H267+H270+H273 -> 41 | I6: =I12+I84+I87+I90+I93+I96+I99+I201+I204+I207+I15+I18+I21+I24+I27+I30+I33+I36+I42+I39+I45+I48+I51+I54+I57+I60+I63+I66+I69+I72+I75+I78+I81+I102+I105+I108+I111+I114+I117+I120+I123+I126+I129+I132+I135+I138+I141+I144+I147+I150+I153+I156+I159+I162+I165+I168+I171+I174+I177+I180+I183+I186+I189+I192+I195+I198+I210+I213+I216+I219+I222+I225+I228+I231+I234+I237+I240+I243+I246+I249+I252+I255+I258+I261+I264+I267+I270+I273 -> 41 | K6: =K12+K84+K87+K90+K93+K96+K99+K201+K204+K207+K15+K18+K21+K24+K27+K30+K33+K36+K42+K39+K45+K48+K51+K54+K57+K60+K63+K66+K69+K72+K75+K78+K81+K102+K105+K108+K111+K114+K117+K120+K123+K126+K129+K132+K135+K138+K141+K144+K147+K150+K153+K156+K159+K162+K165+K168+K171+K174+K177+K180+K183+K186+K189+K192+K195+K198+K210+K213+K216+K219+K222+K225+K228+K231+K234+K237+K240+K243+K246+K249+K252+K255+K258+K261+K264+K267+K270+K273 -> 49 | L6: =L12+L84+L87+L90+L93+L96+L99+L201+L204+L207+L15+L18+L21+L24+L27+L30+L33+L36+L42+L39+L45+L48+L51+L54+L57+L60+L63+L66+L69+L72+L75+L78+L81+L102+L105+L108+L111+L114+L117+L120+L123+L126+L129+L132+L135+L138+L141+L144+L147+L150+L153+L156+L159+L162+L165+L168+L171+L174+L177+L180+L183+L186+L189+L192+L195+L198+L210+L213+L216+L219+L222+L225+L228+L231+L234+L237+L240+L243+L246+L249+L252+L255+L258+L261+L264+L267+L270+L273 -> 46 | N6: =N12+N84+N87+N90+N93+N96+N99+N201+N204+N207+N15+N18+N21+N24+N27+N30+N33+N36+N42+N39+N45+N48+N51+N54+N57+N60+N63+N66+N69+N72+N75+N78+N81+N102+N105+N108+N111+N114+N117+N120+N123+N126+N129+N132+N135+N138+N141+N144+N147+N150+N153+N156+N159+N162+N165+N168+N171+N174+N177+N180+N183+N186+N189+N192+N195+N198+N210+N213+N216+N219+N222+N225+N228+N231+N234+N237+N240+N243+N246+N249+N252+N255+N258+N261+N264+N267+N270+N273 -> 43 | O6: =O12+O84+O87+O90+O93+O96+O99+O201+O204+O207+O15+O18+O21+O24+O27+O30+O33+O36+O42+O39+O45+O48+O51+O54+O57+O60+O63+O66+O69+O72+O75+O78+O81+O102+O105+O108+O111+O114+O117+O120+O123+O126+O129+O132+O135+O138+O141+O144+O147+O150+O153+O156+O159+O162+O165+O168+O171+O174+O177+O180+O183+O186+O189+O192+O195+O198+O210+O213+O216+O219+O222+O225+O228+O231+O234+O237+O240+O243+O246+O249+O252+O255+O258+O261+O264+O267+O270+O273 -> 42 | Q6: =Q12+Q84+Q87+Q90+Q93+Q96+Q99+Q201+Q204+Q207+Q15+Q18+Q21+Q24+Q27+Q30+Q33+Q36+Q42+Q39+Q45+Q48+Q51+Q54+Q57+Q60+Q63+Q66+Q69+Q72+Q75+Q78+Q81+Q102+Q105+Q108+Q111+Q114+Q117+Q120+Q123+Q126+Q129+Q132+Q135+Q138+Q141+Q144+Q147+Q150+Q153+Q156+Q159+Q162+Q165+Q168+Q171+Q174+Q177+Q180+Q183+Q186+Q189+Q192+Q195+Q198+Q210+Q213+Q216+Q219+Q222+Q225+Q228+Q231+Q234+Q237+Q240+Q243+Q246+Q249+Q252+Q255+Q258+Q261+Q264+Q267+Q270+Q273 -> 14 | R6: =R12+R84+R87+R90+R93+R96+R99+R201+R204+R207+R15+R18+R21+R24+R27+R30+R33+R36+R42+R39+R45+R48+R51+R54+R57+R60+R63+R66+R69+R72+R75+R78+R81+R102+R105+R108+R111+R114+R117+R120+R123+R126+R129+R132+R135+R138+R141+R144+R147+R150+R153+R156+R159+R162+R165+R168+R171+R174+R177+R180+R183+R186+R189+R192+R195+R198+R210+R213+R216+R219+R222+R225+R228+R231+R234+R237+R240+R243+R246+R249+R252+R255+R258+R261+R264+R267+R270+R273 -> 11 | T6: =T12+T84+T87+T90+T93+T96+T99+T201+T204+T207+T15+T18+T21+T24+T27+T30+T33+T36+T42+T39+T45+T48+T51+T54+T57+T60+T63+T66+T69+T72+T75+T78+T81+T102+T105+T108+T111+T114+T117+T120+T123+T126+T129+T132+T135+T138+T141+T144+T147+T150+T153+T156+T159+T162+T165+T168+T171+T174+T177+T180+T183+T186+T189+T192+T195+T198+T210+T213+T216+T219+T222+T225+T228+T231+T234+T237+T240+T243+T246+T249+T252+T255+T258+T261+T264+T267+T270+T273 -> 0 | U6: =U12+U84+U87+U90+U93+U96+U99+U201+U204+U207+U15+U18+U21+U24+U27+U30+U33+U36+U42+U39+U45+U48+U51+U54+U57+U60+U63+U66+U69+U72+U75+U78+U81+U102+U105+U108+U111+U114+U117+U120+U123+U126+U129+U132+U135+U138+U141+U144+U147+U150+U153+U156+U159+U162+U165+U168+U171+U174+U177+U180+U183+U186+U189+U192+U195+U198+U210+U213+U216+U219+U222+U225+U228+U231+U234+U237+U240+U243+U246+U249+U252+U255+U258+U261+U264+U267+U270+U273 -> 0 | W6: =W12+W84+W87+W90+W93+W96+W99+W201+W204+W207+W15+W18+W21+W24+W27+W30+W33+W36+W42+W39+W45+W48+W51+W54+W57+W60+W63+W66+W69+W72+W75+W78+W81+W102+W105+W108+W111+W114+W117+W120+W123+W126+W129+W132+W135+W138+W141+W144+W147+W150+W153+W156+W159+W162+W165+W168+W171+W174+W177+W180+W183+W186+W189+W192+W195+W198+W210+W213+W216+W219+W222+W225+W228+W231+W234+W237+W240+W243+W246+W249+W252+W255+W258+W261+W264+W267+W270+W273 -> 9 | X6: =X12+X84+X87+X90+X93+X96+X99+X201+X204+X207+X15+X18+X21+X24+X27+X30+X33+X36+X42+X39+X45+X48+X51+X54+X57+X60+X63+X66+X69+X72+X75+X78+X81+X102+X105+X108+X111+X114+X117+X120+X123+X126+X129+X132+X135+X138+X141+X144+X147+X150+X153+X156+X159+X162+X165+X168+X171+X174+X177+X180+X183+X186+X189+X192+X195+X198+X210+X213+X216+X219+X222+X225+X228+X231+X234+X237+X240+X243+X246+X249+X252+X255+X258+X261+X264+X267+X270+X273 -> 2
D8: ----------------------------------------------------------------------------------------------------------------------------------------------------------------------> | H8: =H5+I5+H6+I6 -> 164 | I8: Pontos | K8: =K5+L5+K6+L6 -> 199 | L8: Pontos | N8: =N5+O5+N6+O6 -> 191 | O8: Pontos | Q8: =Q5+R5+Q6+R6 -> 53 | R8: Pontos | T8: =T5+U5+T6+U6 -> 0 | U8: Pontos | W8: =W5+X5+W6+X6 -> 37 | X8: Pontos
Z9: Semáforo | AC9: Legenda:
B11: Faturamento | D11: Emissão de NF de venda (NF-e) | F11: Diario | H11: 1 | I11: 1 | K11: 1 | L11: 1 | N11: 1 | O11: 1 | Q11: 1 | R11: 1 | Z11: =H11+K11+N11+Q11+T11+W11 -> 4 | AA11: =I11+L11+O11+R11+U11+X11 -> 4 | AD11: Aprendendo | AE11: 1
H12: 1 | I12: 1 | K12: 1 | L12: 1 | N12: 1 | O12: 1 | Q12: 1 | R12: 1 | Z12: =H12+K12+N12+Q12+T12+W12 -> 4 | AA12: =I12+L12+O12+R12+U12+X12 -> 4
B14: Faturamento | D14: Emissão de NF de exportação (NF-e) | F14: Diario | H14: 1 | I14: 1 | K14: 1 | L14: 1 | N14: 1 | O14: 1 | Z14: =H14+K14+N14+Q14+T14+W14 -> 3 | AA14: =I14+L14+O14+R14+U14+X14 -> 3 | AC14: Consegue fazer | AD14: com ajuda | AE14: 1
H15: 1 | I15: 1 | K15: 1 | L15: 1 | N15: 1 | O15: 1 | Z15: =H15+K15+N15+Q15+T15+W15 -> 3 | AA15: =I15+L15+O15+R15+U15+X15 -> 3 | AE15: 1
B17: Faturamento | D17: Emissão de NF de importação (NF-e) | F17: Diario | H17: 1 | I17: 1 | K17: 1 | L17: 1 | N17: 1 | O17: 1 | Z17: =H17+K17+N17+Q17+T17+W17 -> 3 | AA17: =I17+L17+O17+R17+U17+X17 -> 3 | AC17: Consegue fazer | AD17: sem ajuda | AE17: 1 | AF17: 1
H18: 1 | I18: 1 | K18: 1 | L18: 1 | N18: 1 | O18: 1 | Z18: =H18+K18+N18+Q18+T18+W18 -> 3 | AA18: =I18+L18+O18+R18+U18+X18 -> 3 | AC18: (Sei fazer, mas não sei porque faço) | AE18: 1
B20: Faturamento | D20: Emissão de NF de comodato (NF-e) | F20: Diario | H20: 1 | I20: 1 | K20: 1 | L20: 1 | N20: 1 | O20: 1 | Q20: 1 | R20: 1 | Z20: =H20+K20+N20+Q20+T20+W20 -> 4 | AA20: =I20+L20+O20+R20+U20+X20 -> 4 | AC20: Consegue fazer | AD20: e ensinar | AE20: 1 | AF20: 1
H21: 1 | I21: 1 | K21: 1 | L21: 1 | N21: 1 | O21: 1 | Q21: 1 | R21: 1 | Z21: =H21+K21+N21+Q21+T21+W21 -> 4 | AA21: =I21+L21+O21+R21+U21+X21 -> 4 | AC21: (Sei fazer, e sei porque faço) | AE21: 1 | AF21: 1
B23: Faturamento | D23: Emissão de NF de bonificação ou brinde (NF-e) | F23: Diario | H23: 1 | I23: 1 | K23: 1 | L23: 1 | N23: 1 | O23: 1 | Q23: 1 | R23: 1 | Z23: =H23+K23+N23+Q23+T23+W23 -> 4 | AA23: =I23+L23+O23+R23+U23+X23 -> 4
H24: 1 | I24: 1 | K24: 1 | L24: 1 | N24: 1 | O24: 1 | Q24: 1 | R24: 1 | Z24: =H24+K24+N24+Q24+T24+W24 -> 4 | AA24: =I24+L24+O24+R24+U24+X24 -> 4
B26: Faturamento | D26: Emissão de NF de demonstração (NF-e) | F26: Diario | H26: 1 | I26: 1 | K26: 1 | L26: 1 | N26: 1 | O26: 1 | Q26: 1 | R26: 1 | Z26: =H26+K26+N26+Q26+T26+W26 -> 4 | AA26: =I26+L26+O26+R26+U26+X26 -> 4
H27: 1 | I27: 1 | K27: 1 | L27: 1 | N27: 1 | O27: 1 | Q27: 1 | R27: 1 | Z27: =H27+K27+N27+Q27+T27+W27 -> 4 | AA27: =I27+L27+O27+R27+U27+X27 -> 4
B29: Faturamento | D29: Emissão de NF de troca em garantia (NF-e) | F29: Diario | H29: 1 | I29: 1 | K29: 1 | L29: 1 | N29: 1 | O29: 1 | Q29: 1 | R29: 1 | Z29: =H29+K29+N29+Q29+T29+W29 -> 4 | AA29: =I29+L29+O29+R29+U29+X29 -> 4
H30: 1 | I30: 1 | K30: 1 | L30: 1 | N30: 1 | O30: 1 | Q30: 1 | R30: 1 | Z30: =H30+K30+N30+Q30+T30+W30 -> 4 | AA30: =I30+L30+O30+R30+U30+X30 -> 4
B32: Faturamento | D32: Emissão de NF de industrialização (NF-e) | F32: Diario | H32: 1 | I32: 1 | K32: 1 | L32: 1 | N32: 1 | O32: 1 | Z32: =H32+K32+N32+Q32+T32+W32 -> 3 | AA32: =I32+L32+O32+R32+U32+X32 -> 3
H33: 1 | I33: 1 | K33: 1 | L33: 1 | N33: 1 | O33: 1 | Z33: =H33+K33+N33+Q33+T33+W33 -> 3 | AA33: =I33+L33+O33+R33+U33+X33 -> 3
B35: Faturamento | D35: Emissão de NF de serviço (NFS-e) | F35: Diario | H35: 1 | I35: 1 | K35: 1 | L35: 1 | N35: 1 | O35: 1 | Z35: =H35+K35+N35+Q35+T35+W35 -> 3 | AA35: =I35+L35+O35+R35+U35+X35 -> 3
H36: 1 | I36: 1 | K36: 1 | N36: 1 | O36: 1 | Z36: =H36+K36+N36+Q36+T36+W36 -> 3 | AA36: =I36+L36+O36+R36+U36+X36 -> 2
B38: Faturamento | D38: Emissão de NF de débito (ND) | F38: Diario | H38: 1 | I38: 1 | K38: 1 | L38: 1 | N38: 1 | O38: 1 | Z38: =H38+K38+N38+Q38+T38+W38 -> 3 | AA38: =I38+L38+O38+R38+U38+X38 -> 3
H39: 1 | I39: 1 | K39: 1 | N39: 1 | O39: 1 | Z39: =H39+K39+N39+Q39+T39+W39 -> 3 | AA39: =I39+L39+O39+R39+U39+X39 -> 2
B41: Faturamento | D41: Emissão de NF complementar de ICMS (NF-e) | F41: Diario | H41: 1 | I41: 1 | K41: 1 | L41: 1 | N41: 1 | O41: 1 | Z41: =H41+K41+N41+Q41+T41+W41 -> 3 | AA41: =I41+L41+O41+R41+U41+X41 -> 3
H42: 1 | I42: 1 | K42: 1 | L42: 1 | Z42: =H42+K42+N42+Q42+T42+W42 -> 2 | AA42: =I42+L42+O42+R42+U42+X42 -> 2
